Workbook

Sheet 00_README
A1: IP MASTER DATASET 2021–2025 – TRƯỜNG ĐẠI HỌC THÀNH ĐÔ
A3: Mục | B3: Nội dung
A4: Mục đích | B4: Khung dữ liệu phục vụ đề tài cấp cơ sở: kiểm kê kết quả KHCN → nhận diện TSTT → xác lập/bảo hộ → ứng dụng/chuyển giao → giá trị.
A5: Trạng thái | B5: Bản v0.7: hoàn thiện blueprint Chương 2, kế hoạch bảng/biểu đồ và bản nháp các mục 2.1–2.4. Cấu trúc Chương 2 đi theo logic: thể chế → năng lực tạo đầu ra/TSTT → portfolio quyền → quy trình nhận diện/bảo hộ → ứng dụng/khai thác → case tracing → gap → đánh giá chung.
A6: Nguyên tắc đơn vị phân tích | B6: PROJECT = 1 đề tài; OUTPUT = 1 đầu ra; IP_ASSET = 1 TSTT hoặc cụm TSTT; PROTECTION = 1 hồ sơ/quyền; UTILIZATION_VALUE = 1 lần/hình thức khai thác.
A7: Không đồng nhất | B7: Không coi số văn bằng bảo hộ là tổng số TSTT. TSTT tiềm năng được nhận diện trước, sau đó mới xét hình thức quyền phù hợp.
A8: Mã thiếu dữ liệu | B8: Để trống = chưa có bằng chứng; 'Chưa xác minh' = có dấu hiệu nhưng chưa đủ hồ sơ; không suy diễn từ tên đề tài.
A9: Nguồn chính | B9: Tổng hợp đề tài KHCN cấp cơ sở của GV 2021–2025; Quy chế hoạt động KHCN 2021; Quy chế quản trị TSTT; các bảng công bố/sách/giáo trình.
A10: Chiến lược | B10: Mã Strategic Cluster theo 4 trụ cột: Smart Mobility, Digital Services, Global Communication, Wellness & Care; có thể dùng 'Khác/Chưa phân loại'.
A11: Khuyến nghị sử dụng | B11: Hoàn thiện dữ liệu thô trước khi tính tỷ lệ và kết luận. Mọi chỉ số KPI hiện tại chỉ phản ánh các dòng mẫu đã nhập.
A12: Phiên bản | B12: v0.7 – Chapter 2 writing blueprint + table/figure plan + draft sections 2.1–2.4.
A14: v0.8 (Claude, 16/9/2026) | B14: Dọn trùng lặp thế hệ bảng, chuẩn hóa từ điển loại đầu ra, tách mẫu số, thêm KPI bằng công thức và 8 phép kiểm tra tự động. Chi tiết ở 00_CHANGELOG_v08. Sheet có tiền tố ZZ_CU_ là bản cũ, không dùng để trích dẫn.

Sheet 00_CHANGELOG_v08
A1: NHẬT KÝ THAY ĐỔI – TỪ v0.7 SANG v0.8
A2: Không xóa dữ liệu gốc. Mọi thay đổi đều cộng thêm hoặc đổi tên, có thể lần ngược.
A4: STT | B4: Vấn đề ở v0.7 | C4: Xử lý ở v0.8 | D4: Sheet liên quan
A5: 1 | B5: Hai thế hệ bảng cùng tồn tại: 01_PROJECT 7 dòng và 01_PROJECT_ALL 38 dòng; 02_OUTPUT 19 dòng và 02_OUTPUT_ALL 90 dòng; 03_IP_ASSET 7 dòng; 08_KPI_DASHBOARD. Nguy cơ trích nhầm số. | C5: Đổi tên thành ZZ_CU_… và dồn xuống cuối file. Dữ liệu vẫn giữ nguyên để đối chiếu, nhưng không dùng để trích dẫn. | D5: ZZ_CU_01_PROJECT; ZZ_CU_02_OUTPUT; ZZ_CU_03_IP_ASSET; ZZ_CU_08_KPI_DASHBOARD
A6: 2 | B6: 02_OUTPUT dùng mã Output cũ dạng O2022-37-01, khác mã hiện hành O-2022-37-01. Ghép nhầm là chắc chắn nếu dùng lẫn. | C6: Ghi nhận xung đột mã; bảng cũ chỉ để tham chiếu lịch sử. Mã chính thức là mã của 02_OUTPUT_ALL. | D6: ZZ_CU_02_OUTPUT
A7: 3 | B7: 04_PROTECTION và 05_UTIL_VALUE trống, mỗi sheet 1000 dòng ràng buộc nhập liệu, nhưng đã bị 13B_PROTECTION_FULL thay thế. | C7: Đổi tên thành TPL_… để chỉ rõ đây là biểu mẫu thu thập dữ liệu về sau, không phải dữ liệu thực. | D7: TPL_04_PROTECTION; TPL_05_UTIL_VALUE
A8: 4 | B8: Từ điển loại đầu ra bị vỡ: 09_LOOKUPS có 11 giá trị, dữ liệu dùng 14 giá trị, 9 giá trị nằm ngoài từ điển; 'Sản phẩm/prototype' và 'Mô hình/prototype' trùng nghĩa. | C8: Lập bảng ánh xạ 14 giá trị gốc sang 8 nhóm chuẩn. Giữ nguyên cột gốc, thêm cột P và Q tính bằng VLOOKUP nên sửa từ điển là dữ liệu tự cập nhật. | D8: 09B_MAP_LOAI_DAURA; 02_OUTPUT_ALL cột P, Q
A9: 5 | B9: 34/90 dòng đầu ra là báo cáo tổng kết — sản phẩm hành chính bắt buộc. Để trong mẫu số làm loãng mọi tỷ lệ chuyển hóa. | C9: Thêm cột Nhóm mẫu số với 4 giá trị: Bắt buộc hành chính, Công bố, Ứng viên TSTT, Khác/quản trị. Mọi tỷ lệ ở 08B đều loại nhóm bắt buộc khỏi mẫu số. | D9: 02_OUTPUT_ALL cột Q; 08B_KPI_v08
A10: 6 | B10: 08_KPI_ALL gõ tay toàn bộ giá trị, tỷ lệ để dạng 0,4736 và không ghi mẫu số. | C10: Lập 08B_KPI_v08 tính bằng công thức, mỗi chỉ số có cột tử số, mẫu số và ghi chú diễn giải. Ô tỷ lệ ở 08_KPI_ALL được định dạng lại thành phần trăm. | D10: 08B_KPI_v08
A11: 7 | B11: Không có cơ chế phát hiện lỗi khi dữ liệu được bổ sung. | C11: Lập 8 phép kiểm tra tự động: trùng mã, khóa mồ côi, giá trị ngoài từ điển, tổng nhóm mẫu số. Mọi dòng phải trả về OK. | D11: 24_QC_CHECKS
A12: 8 | B12: Portfolio SHTT mới dựa vào danh sách nội bộ, chưa đối chiếu nguồn độc lập. | C12: Chưa xử lý ở v0.8. Đề nghị tra ngược 9 đối tượng đã có số trên cơ sở dữ liệu công khai của Cục Sở hữu trí tuệ, ghi kết quả vào 13B thành cột xác minh độc lập. | D12: 13B_PROTECTION_FULL
A13: 9 | B13: File chứa tên cá nhân, tên doanh nghiệp đối tác, số văn bằng, kèm nhận định về việc thiếu hồ sơ. | C13: Chưa xử lý ở v0.8. Trước khi đưa vào luận án hoặc báo cáo, cân nhắc mã hóa tên cá nhân và tên doanh nghiệp. | D13: Toàn file

Sheet 01_PROJECT_ALL
A1: Project_ID | B1: Năm giao/nhóm | C1: Mã đề tài | D1: Tên đề tài | E1: Cấp | F1: Chủ nhiệm | G1: Đơn vị chủ trì | H1: Nhóm ngành chuẩn hóa | I1: Strategic_Cluster | J1: Ngày nghiệm thu | K1: Xếp loại | L1: Kinh phí_VND | M1: Hình thức kinh phí | N1: Số người tham gia | O1: Đầu ra ứng dụng ghi trong hồ sơ? | P1: Số đầu ra (formula) | Q1: Nguồn | R1: Ghi chú xác minh
A2: P2021-20 | B2: 2021 | C2: 20-2021/KHCN | D2: Nghiên cứu năng lực nghe hiểu của sinh viên cử nhân thực hành tiếng Nhật năm thứ 2 tại Trường Đại học Thành Đô | E2: Cơ sở | F2: Lê Thanh Phương | G2: Khoa DL-NN | H2: Ngôn ngữ/Giáo dục | I2: Global Communication | J2: 44816 | K2: Đạt | M2: Quy đổi giờ NCKH | N2: 1 | O2: Không ghi nhận | P2: =COUNTIF(02_OUTPUT_ALL!$B:$B,A2) -> 1 | Q2: Tổng hợp đề tài KHCN cấp cơ sở của GV 2021-2025.pdf, tr.1 | R2: Năm nhóm theo mục NĂM 2021; nghiệm thu năm 2022.
A3: P2021-22 | B3: 2021 | C3: 22-2021/KHCN | D3: Đánh giá giáo trình Network dùng cho sinh viên năm thứ nhất Trường Đại học Thành Đô | E3: Cơ sở | F3: Nguyễn Thị Vân Anh | G3: Khoa DL-NN | H3: Ngôn ngữ/Giáo dục | I3: Global Communication | J3: 44816 | K3: Đạt | M3: Quy đổi giờ NCKH | N3: 1 | O3: Không ghi nhận | P3: =COUNTIF(02_OUTPUT_ALL!$B:$B,A3) -> 1 | Q3: Tổng hợp đề tài KHCN cấp cơ sở của GV 2021-2025.pdf, tr.1
A4: P2021-24 | B4: 2021 | C4: 24-2021/KHCN | D4: Đánh giá ứng dụng mô hình học tập kết hợp (Blended Learning) trong việc dạy và học tiếng Anh tại Trường Đại học Thành Đô | E4: Cơ sở | F4: Đinh Thị Thanh Huyền | G4: Khoa DL-NN | H4: Ngôn ngữ/Giáo dục | I4: Global Communication | J4: 44816 | K4: Tốt | M4: Quy đổi giờ NCKH | N4: 1 | O4: Không ghi nhận | P4: =COUNTIF(02_OUTPUT_ALL!$B:$B,A4) -> 1 | Q4: Tổng hợp đề tài KHCN cấp cơ sở của GV 2021-2025.pdf, tr.1
A5: P2021-27 | B5: 2021 | C5: 27-2021/KHCN | D5: Thực trạng và động lực phát triển chuyên môn của giáo viên | E5: Cơ sở | F5: Phan Thị Thanh Thảo | G5: Khoa DL-NN | H5: Khoa học giáo dục | I5: Khác/Chưa phân loại | J5: 44370 | K5: Đạt | M5: Quy đổi giờ NCKH | N5: 6 | O5: Không ghi nhận | P5: =COUNTIF(02_OUTPUT_ALL!$B:$B,A5) -> 3 | Q5: Tổng hợp đề tài KHCN cấp cơ sở của GV 2021-2025.pdf, tr.1
A6: P2021-28 | B6: 2021 | C6: 28-2021/KHCN | D6: Hoạt động công bố quốc tế tại Việt Nam: Thực trạng và ý nghĩa đối với cộng đồng và những nhà hoạch định chính sách | E6: Cơ sở | F6: Phan Thị Thanh Thảo | G6: Khoa DL-NN | H6: Khoa học giáo dục/Chính sách KHCN | I6: Khác/Chưa phân loại | J6: 44370 | K6: Đạt | M6: Quy đổi giờ NCKH | N6: 8 | O6: Không ghi nhận | P6: =COUNTIF(02_OUTPUT_ALL!$B:$B,A6) -> 3 | Q6: Tổng hợp đề tài KHCN cấp cơ sở của GV 2021-2025.pdf, tr.2
A7: P2021-37 | B7: 2021 | C7: 37-2021/KHCN | D7: Rào cản của các doanh nghiệp vừa và nhỏ trong việc áp dụng thương mại điện tử tại Việt Nam | E7: Cơ sở | F7: Nguyễn Thị Hay | G7: Khoa KT | H7: Kinh tế/Thương mại điện tử | I7: Digital Services | J7: 44536 | K7: Đạt | M7: Quy đổi giờ NCKH | N7: 2 | O7: Không ghi nhận | P7: =COUNTIF(02_OUTPUT_ALL!$B:$B,A7) -> 2 | Q7: Tổng hợp đề tài KHCN cấp cơ sở của GV 2021-2025.pdf, tr.2
A8: P2022-01 | B8: 2022 | C8: 01-2022/KHCN | D8: Đề án thành lập Tạp chí Nghiên cứu khoa học và phát triển thuộc Trường Đại học Thành Đô | E8: Cơ sở | F8: Vũ Thị Thanh Minh | G8: Phòng KHCN | H8: Quản lý KHCN/Xuất bản khoa học | I8: Khác/Chưa phân loại | J8: 44613 | K8: Tốt | M8: Quy đổi giờ NCKH | N8: 5 | O8: Có | P8: =COUNTIF(02_OUTPUT_ALL!$B:$B,A8) -> 1 | Q8: Tổng hợp đề tài KHCN cấp cơ sở của GV 2021-2025.pdf, tr.2 | R8: Sản phẩm là Tạp chí Nghiên cứu khoa học và phát triển.
A9: P2022-02 | B9: 2022 | C9: 02-2022/KHCN | D9: Nghiên cứu xây dựng Quy chế tuyển sinh và đào tạo trình độ thạc sỹ theo Thông tư số 23/2021/TT-BGDĐT của Bộ Giáo dục và Đào tạo tại Trường Đại học Thành Đô | E9: Cơ sở | F9: Trần Hữu Dào | G9: Khoa SĐH | H9: Quản trị giáo dục/Pháp quy nội bộ | I9: Khác/Chưa phân loại | J9: 44627 | K9: Đạt | M9: Quy đổi giờ NCKH | N9: 1 | O9: Có | P9: =COUNTIF(02_OUTPUT_ALL!$B:$B,A9) -> 1 | Q9: Tổng hợp đề tài KHCN cấp cơ sở của GV 2021-2025.pdf, tr.2 | R9: Sản phẩm là Quy chế tuyển sinh và đào tạo trình độ thạc sĩ.
A10: P2022-12 | B10: 2022 | C10: 12-2022/KHCN | D10: Nâng cao khả năng được tuyển dụng của sinh viên ngành tiếng Anh Khoa Du lịch - Ngoại ngữ qua kỳ thực tập doanh nghiệp | E10: Cơ sở | F10: Đinh Thị Thanh Huyền | G10: Khoa DL-NN | H10: Ngôn ngữ/Đào tạo gắn doanh nghiệp | I10: Global Communication | J10: 44872 | K10: Tốt | M10: Quy đổi giờ NCKH | N10: 1 | O10: Không ghi nhận | P10: =COUNTIF(02_OUTPUT_ALL!$B:$B,A10) -> 1 | Q10: Tổng hợp đề tài KHCN cấp cơ sở của GV 2021-2025.pdf, tr.2
A11: P2022-13 | B11: 2022 | C11: 13-2022/KHCN | D11: Đánh giá giáo trình "New English file" dành cho học viên cao học tại Trường Đại học Thành Đô | E11: Cơ sở | F11: Phan Thị Thanh Thảo | G11: Khoa DL-NN | H11: Ngôn ngữ/Giáo dục | I11: Global Communication | J11: 44872 | K11: Tốt | M11: Quy đổi giờ NCKH | N11: 2 | O11: Không ghi nhận | P11: =COUNTIF(02_OUTPUT_ALL!$B:$B,A11) -> 1 | Q11: Tổng hợp đề tài KHCN cấp cơ sở của GV 2021-2025.pdf, tr.3
A12: P2022-14 | B12: 2022 | C12: 14-2022/KHCN | D12: A study on job satisfaction among teachers at TDU (Đánh giá sự hài lòng của giảng viên tại Đại học Thành Đô) | E12: Cơ sở | F12: Nguyễn Thị Vân Anh | G12: Khoa DL-NN | H12: Khoa học giáo dục/Nhân sự | I12: Khác/Chưa phân loại | J12: 44872 | K12: Tốt | M12: Quy đổi giờ NCKH | N12: 1 | O12: Không ghi nhận | P12: =COUNTIF(02_OUTPUT_ALL!$B:$B,A12) -> 1 | Q12: Tổng hợp đề tài KHCN cấp cơ sở của GV 2021-2025.pdf, tr.3
A13: P2022-15 | B13: 2022 | C13: 15-2022/KHCN | D13: Nghiên cứu ảnh hưởng của hình thức dạy học trực tuyến đến kết quả học tập của sinh viên Khoa Du lịch - Ngoại ngữ, Trường Đại học Thành Đô | E13: Cơ sở | F13: Phan Thị Phương Thảo | G13: Khoa DL-NN | H13: Khoa học giáo dục | I13: Global Communication | J13: 44873 | K13: Tốt | M13: Quy đổi giờ NCKH | N13: 1 | O13: Không ghi nhận | P13: =COUNTIF(02_OUTPUT_ALL!$B:$B,A13) -> 1 | Q13: Tổng hợp đề tài KHCN cấp cơ sở của GV 2021-2025.pdf, tr.3
A14: P2022-37 | B14: 2022 | C14: 37-2022/KHCN | D14: Tính toán thiết kế panel kiểm tra và sửa chữa hệ thống khởi động điện trên ô tô | E14: Cơ sở | F14: Phạm Viết Xuân | G14: Khoa CNKT Ô tô | H14: Kỹ thuật ô tô | I14: Smart Mobility | J14: 44874 | K14: Đạt | L14: 5000000 | M14: Tiền mặt | N14: 1 | O14: Có | P14: =COUNTIF(02_OUTPUT_ALL!$B:$B,A14) -> 2 | Q14: Tổng hợp đề tài KHCN cấp cơ sở của GV 2021-2025.pdf, tr.3
A15: P2022-39 | B15: 2022 | C15: 39-2022/KHCN | D15: Nghiên cứu chế tạo vật liệu cầm máu trên cơ sở chitosan và cao nhọ nồi | E15: Cơ sở | F15: Nguyễn Ngọc Linh | G15: Khoa Dược | H15: Dược/Vật liệu y sinh | I15: Wellness & Care | J15: 44875 | K15: Đạt | L15: 29000000 | M15: Tiền mặt | N15: 5 | O15: Có | P15: =COUNTIF(02_OUTPUT_ALL!$B:$B,A15) -> 2 | Q15: Tổng hợp đề tài KHCN cấp cơ sở của GV 2021-2025.pdf, tr.3
A16: P2022-40 | B16: 2022 | C16: 40-2022/KHCN | D16: Nghiên cứu xây dựng bộ mẫu dược liệu áp dụng giảng dạy tại Trường Đại học Thành Đô | E16: Cơ sở | F16: Lê Văn Tuyến | G16: Khoa Dược | H16: Dược/Giáo dục dược | I16: Wellness & Care | J16: 44875 | K16: Đạt | L16: 50000000 | M16: Tiền mặt | N16: 7 | O16: Có | P16: =COUNTIF(02_OUTPUT_ALL!$B:$B,A16) -> 2 | Q16: Tổng hợp đề tài KHCN cấp cơ sở của GV 2021-2025.pdf, tr.3
A17: P2022-51 | B17: 2022 | C17: 51-2022/KHCN | D17: Quản lý hoạt động huy động vốn của các công ty chứng khoán tại Việt Nam: Thực trạng và một số kiến nghị | E17: Cơ sở | F17: Đinh Thị Phi Nga | G17: Khoa Kinh tế | H17: Tài chính/Chứng khoán | I17: Digital Services | J17: 44876 | K17: Đạt | M17: Quy đổi giờ NCKH | N17: 2 | O17: Không ghi nhận | P17: =COUNTIF(02_OUTPUT_ALL!$B:$B,A17) -> 2 | Q17: Tổng hợp đề tài KHCN cấp cơ sở của GV 2021-2025.pdf, tr.4
A18: P2023-01 | B18: 2023 | C18: 01-2023/KHCN | D18: Bồi dưỡng phương pháp tư duy biện chứng Hồ Chí Minh cho sinh viên Trường Đại học Thành Đô hiện nay | E18: Cơ sở | F18: Ngô Nhị Ngọc Linh | G18: Khoa KHCB | H18: Lý luận chính trị/Giáo dục | I18: Khác/Chưa phân loại | J18: 45246 | K18: Khá | L18: 3000000 | M18: Tiền mặt | N18: 2 | O18: Có | P18: =COUNTIF(02_OUTPUT_ALL!$B:$B,A18) -> 3 | Q18: Tổng hợp đề tài KHCN cấp cơ sở của GV 2021-2025.pdf, tr.4 | R18: Có mô tả ứng dụng tại Trường.
A19: P2023-02 | B19: 2023 | C19: 02-2023/KHCN | D19: Tiếp cận CDIO để nâng cao chất lượng dạy học học phần thực hành hướng dẫn du lịch tại Trường Đại học Thành Đô | E19: Cơ sở | F19: Nguyễn Thị Bích | G19: Khoa DL-NN | H19: Du lịch/Giáo dục | I19: Global Communication | J19: 45253 | K19: Tốt | L19: 5000000 | M19: Tiền mặt | N19: 2 | O19: Có | P19: =COUNTIF(02_OUTPUT_ALL!$B:$B,A19) -> 3 | Q19: Tổng hợp đề tài KHCN cấp cơ sở của GV 2021-2025.pdf, tr.4 | R19: Có mô tả ứng dụng tại Trường.
A20: P2023-03 | B20: 2023 | C20: 03-2023/KHCN | D20: Sử dụng phương pháp học tập dự án để thúc đẩy sự tự chủ của sinh viên trong học phần cú pháp học | E20: Cơ sở | F20: Phan Thị Thanh Thảo | G20: Khoa DL-NN | H20: Ngôn ngữ/Giáo dục | I20: Global Communication | J20: 45257 | K20: Tốt | L20: 3000000 | M20: Tiền mặt | N20: 3 | O20: Có | P20: =COUNTIF(02_OUTPUT_ALL!$B:$B,A20) -> 3 | Q20: Tổng hợp đề tài KHCN cấp cơ sở của GV 2021-2025.pdf, tr.5 | R20: Hồ sơ ghi bài báo ISSN nhưng chú thích '(ko có bài báo)'.
A21: P2023-04 | B21: 2023 | C21: 04-2023/KHCN | D21: Flipped classroom in higher education: Students' perspective | E21: Cơ sở | F21: Nguyễn Thị Vân Anh | G21: Khoa DL-NN | H21: Khoa học giáo dục | I21: Global Communication | J21: 45257 | K21: Đạt | L21: 3000000 | M21: Tiền mặt | N21: 3 | O21: Có | P21: =COUNTIF(02_OUTPUT_ALL!$B:$B,A21) -> 3 | Q21: Tổng hợp đề tài KHCN cấp cơ sở của GV 2021-2025.pdf, tr.5 | R21: Hồ sơ ghi bài báo ISSN nhưng chú thích '(ko có bài báo)'.
A22: P2023-05 | B22: 2023 | C22: 05-2023/KHCN | D22: Chính sách khuyến khích cho các công bố khoa học tại một số trường đại học ngoài công lập ở Việt Nam | E22: Cơ sở | F22: Nguyễn Thị Hảo | G22: Khoa Điện, Điện tử | H22: Chính sách KHCN/Quản trị đại học | I22: Khác/Chưa phân loại | J22: 45246 | K22: Tốt | L22: 5000000 | M22: Tiền mặt | N22: 4 | O22: Có | P22: =COUNTIF(02_OUTPUT_ALL!$B:$B,A22) -> 3 | Q22: Tổng hợp đề tài KHCN cấp cơ sở của GV 2021-2025.pdf, tr.6 | R22: Ứng dụng làm tài liệu tham khảo xây dựng chính sách/quy chế KHCN.
A23: P2023-07 | B23: 2023 | C23: 07-2023/KHCN | D23: Nâng cao nhận thức về luật hình sự Việt Nam cho sinh viên Trường Đại học Thành Đô | E23: Cơ sở | F23: Vũ Thị Thu Hà | G23: Khoa Kinh tế - Luật | H23: Luật/Giáo dục pháp luật | I23: Khác/Chưa phân loại | J23: 45254 | K23: Đạt | L23: 1000000 | M23: Tiền mặt | N23: 2 | O23: Có | P23: =COUNTIF(02_OUTPUT_ALL!$B:$B,A23) -> 3 | Q23: Tổng hợp đề tài KHCN cấp cơ sở của GV 2021-2025.pdf, tr.6 | R23: Hồ sơ ghi bài báo ISSN nhưng chú thích '(ko có bài báo)'.
A24: P2023-08 | B24: 2023 | C24: 08-2023/KHCN | D24: Ứng dụng mô hình hợp tác giáo dục giữa Nhà trường - Doanh nghiệp trong nghiên cứu chiết xuất tinh dầu từ vỏ bưởi | E24: Cơ sở | F24: Phan Thị Thanh Thảo | G24: Viện REK | H24: Dược/Hợp tác ĐH-DN | I24: Wellness & Care | J24: 45243 | K24: Tốt | L24: 50000000 | M24: Tiền mặt | N24: 8 | O24: Có | P24: =COUNTIF(02_OUTPUT_ALL!$B:$B,A24) -> 3 | Q24: Tổng hợp đề tài KHCN cấp cơ sở của GV 2021-2025.pdf, tr.7 | R24: Sản phẩm ghi chuyển giao cho Trường để thương mại hóa.
A25: P2024-06 | B25: 2024 | C25: 06-2024/KHCN | D25: Nghiên cứu ứng dụng quy trình sản xuất xà phòng tảo biển hữu cơ | E25: Cơ sở | F25: Nguyễn Ngọc Linh | G25: Khoa Dược | H25: Dược/Mỹ phẩm | I25: Wellness & Care | J25: 45611 | K25: Tốt | L25: 58000000 | M25: Tiền mặt | N25: 4 | O25: Có | P25: =COUNTIF(02_OUTPUT_ALL!$B:$B,A25) -> 4 | Q25: Tổng hợp đề tài KHCN cấp cơ sở của GV 2021-2025.pdf, tr.7
A26: P2024-07 | B26: 2024 | C26: 07-2024/KHCN | D26: Nghiên cứu xây dựng bộ tiêu bản hiển vi cố định trong giảng dạy học phần Ký sinh trùng tại Trường Đại học Thành Đô | E26: Cơ sở | F26: Phạm Thị Bích Đào | G26: Khoa Dược | H26: Dược/Ký sinh trùng/Giáo dục | I26: Wellness & Care | J26: 45611 | K26: Tốt | L26: 43000000 | M26: Tiền mặt | N26: 2 | O26: Có | P26: =COUNTIF(02_OUTPUT_ALL!$B:$B,A26) -> 4 | Q26: Tổng hợp đề tài KHCN cấp cơ sở của GV 2021-2025.pdf, tr.7
A27: P2024-08 | B27: 2024 | C27: 08-2024/KHCN | D27: Cải tiến quy trình chiết xuất Rutin từ hoa Hòe (Sophora japonica L.) trong giảng dạy tại Trường Đại học Thành Đô | E27: Cơ sở | F27: Vũ Quốc Mạnh | G27: Khoa Dược | H27: Dược/Chiết xuất dược liệu | I27: Wellness & Care | J27: 45611 | K27: Tốt | L27: 13250000 | M27: Tiền mặt | N27: 2 | O27: Có | P27: =COUNTIF(02_OUTPUT_ALL!$B:$B,A27) -> 5 | Q27: Tổng hợp đề tài KHCN cấp cơ sở của GV 2021-2025.pdf, tr.8
A28: P2024-09 | B28: 2024 | C28: 09-2024/KHCN | D28: Nghiên cứu bào chế sản phẩm hỗ trợ giảm cân theo y học cổ truyền | E28: Cơ sở | F28: Nguyễn Đăng Việt | G28: Khoa Dược | H28: Dược/Bào chế | I28: Wellness & Care | J28: 45611 | K28: Đạt | L28: 8500000 | M28: Tiền mặt | N28: 3 | O28: Có | P28: =COUNTIF(02_OUTPUT_ALL!$B:$B,A28) -> 4 | Q28: Tổng hợp đề tài KHCN cấp cơ sở của GV 2021-2025.pdf, tr.8
A29: P2024-10 | B29: 2024 | C29: 10-2024/KHCN | D29: Triết lý nhân sinh trong thơ văn của Nguyễn Đình Chiểu và vận dụng giáo dục đạo đức cho sinh viên Trường Đại học Thành Đô hiện nay | E29: Cơ sở | F29: Ngô Nhị Ngọc Linh | G29: Khoa KHCB | H29: Nhân văn/Giáo dục | I29: Khác/Chưa phân loại | J29: 45597 | K29: Đạt | L29: 3000000 | M29: Tiền mặt | N29: 3 | O29: Không ghi nhận | P29: =COUNTIF(02_OUTPUT_ALL!$B:$B,A29) -> 2 | Q29: Tổng hợp đề tài KHCN cấp cơ sở của GV 2021-2025.pdf, tr.8
A30: P2024-12 | B30: 2024 | C30: 12-2024/KHCN | D30: Tích hợp giáo dục vì sự phát triển bền vững trong dạy học “sinh thái học và môi trường” (Sinh học 12) | E30: Cơ sở | F30: Hà Văn Dũng | G30: Viện ReK | H30: Khoa học giáo dục/Phát triển bền vững | I30: Khác/Chưa phân loại | J30: 45594 | K30: Đạt | M30: Tự tìm nhà tài trợ | N30: 5 | O30: Không ghi nhận | P30: =COUNTIF(02_OUTPUT_ALL!$B:$B,A30) -> 3 | Q30: Tổng hợp đề tài KHCN cấp cơ sở của GV 2021-2025.pdf, tr.9
A31: P2024-13 | B31: 2024 | C31: 13-2024/KHCN | D31: Quan điểm của Francis Fukuyama về sự cáo chung của lịch sử trong tác phẩm Sự cáo chung của lịch sử và Con người cuối cùng | E31: Cơ sở | F31: Ngô Nhị Ngọc Linh | G31: Khoa KHCB | H31: Triết học/Nhân văn | I31: Khác/Chưa phân loại | J31: 45597 | K31: Đạt | M31: Tự tìm nhà tài trợ | N31: 3 | O31: Không ghi nhận | P31: =COUNTIF(02_OUTPUT_ALL!$B:$B,A31) -> 2 | Q31: Tổng hợp đề tài KHCN cấp cơ sở của GV 2021-2025.pdf, tr.9
A32: P2024-14 | B32: 2024 | C32: 14-2024/KHCN | D32: Rèn luyện năng lực dạy học tích hợp giáo dục vì sự phát triển bền vững cho sinh viên ngành sư phạm sinh học | E32: Cơ sở | F32: Hà Văn Dũng | G32: Viện ReK | H32: Khoa học giáo dục/Phát triển bền vững | I32: Khác/Chưa phân loại | J32: 45785 | K32: Đạt | L32: 19500000 | M32: Tự tìm nguồn tài trợ | N32: 5 | O32: Không ghi nhận | P32: =COUNTIF(02_OUTPUT_ALL!$B:$B,A32) -> 3 | Q32: Tổng hợp đề tài KHCN cấp cơ sở của GV 2021-2025.pdf, phần chuyển tiếp 2024-2025 | R32: Nghiệm thu năm 2025.
A33: P2025-01 | B33: 2025 | C33: 01-2025/KHCN | D33: Sử dụng chiến lược scaffolding để tăng cường sự tham gia của sinh viên trong lớp học tiếng Anh đa trình độ | E33: Cơ sở | F33: Phan Thị Thanh Thảo | G33: Viện QT&CN | H33: Ngôn ngữ/Giáo dục | I33: Global Communication | J33: 46006 | K33: Tốt | L33: 5000000 | M33: Tiền mặt | N33: 3 | O33: Không ghi nhận | P33: =COUNTIF(02_OUTPUT_ALL!$B:$B,A33) -> 2 | Q33: Tổng hợp đề tài KHCN cấp cơ sở của GV 2021-2025.pdf, mục NĂM 2025 | R33: Nguồn viết 'scarfolding'; chuẩn hóa thành scaffolding trong tên phân tích.
A34: P2025-02 | B34: 2025 | C34: 02-2025/KHCN | D34: Phát triển kiến thức và kỹ năng đổi mới sáng tạo cho sinh viên ngành quản trị kinh doanh Trường Đại học Thành Đô | E34: Cơ sở | F34: Nguyễn Thị Hay | G34: Viện QT&CN | H34: Quản trị kinh doanh/Đổi mới sáng tạo | I34: Digital Services | J34: 46008 | K34: Tốt | M34: Tính giờ NCKH đề tài + bài báo | N34: 1 | O34: Không ghi nhận | P34: =COUNTIF(02_OUTPUT_ALL!$B:$B,A34) -> 2 | Q34: Tổng hợp đề tài KHCN cấp cơ sở của GV 2021-2025.pdf, mục NĂM 2025
A35: P2025-03 | B35: 2025 | C35: 03-2025/KHCN | D35: Nghiên cứu các nhân tố ảnh hưởng đến khả năng tự quyết toán thuế TNCN của người nộp thuế TNCN trên địa bàn thành phố Hà Nội | E35: Cơ sở | F35: Trần Thị Thùy | G35: Viện QT&CN | H35: Kinh tế/Tài chính công/Thuế | I35: Digital Services | J35: 46009 | K35: Tốt | M35: Tính giờ NCKH đề tài + bài báo | N35: 2 | O35: Không ghi nhận | P35: =COUNTIF(02_OUTPUT_ALL!$B:$B,A35) -> 2 | Q35: Tổng hợp đề tài KHCN cấp cơ sở của GV 2021-2025.pdf, mục NĂM 2025
A36: P2025-04 | B36: 2025 | C36: 04-2025/KHCN | D36: Hoàn thiện kỹ năng soạn thảo hợp đồng cho sinh viên Trường Đại học Thành Đô | E36: Cơ sở | F36: Vũ Thị Thu Hà | G36: Viện QT&CN | H36: Luật/Giáo dục kỹ năng | I36: Khác/Chưa phân loại | J36: 46010 | K36: Tốt | M36: Tính giờ NCKH đề tài + bài báo | N36: 3 | O36: Không ghi nhận | P36: =COUNTIF(02_OUTPUT_ALL!$B:$B,A36) -> 1 | Q36: Tổng hợp đề tài KHCN cấp cơ sở của GV 2021-2025.pdf, mục NĂM 2025 | R36: Hồ sơ trích xuất hiện thấy sản phẩm bài báo; cần kiểm tra có báo cáo toàn văn riêng hay không.
A37: P2025-06 | B37: 2025 | C37: 06-2025/KHCN | D37: Nghiên cứu bào chế cồn thuốc xoa bóp hỗ trợ giảm đau nhức xương khớp quy mô phòng thí nghiệm | E37: Cơ sở | F37: Nguyễn Đăng Việt | G37: Viện Y-Dược | H37: Dược/Bào chế | I37: Wellness & Care | J37: 46016 | K37: Tốt | L37: 30000000 | M37: Tiền mặt + tính giờ NCKH | N37: 4 | O37: Có | P37: =COUNTIF(02_OUTPUT_ALL!$B:$B,A37) -> 3 | Q37: Tổng hợp đề tài KHCN cấp cơ sở của GV 2021-2025.pdf, mục NĂM 2025 | R37: Công thức mới, dự kiến đăng ký GPHI.
A38: P2025-07 | B38: 2025 | C38: 07-2025/KHCN | D38: Nghiên cứu bào chế viên ngậm hỗ trợ giảm ho từ Gừng và Húng chanh | E38: Cơ sở | F38: Ngô Thị Thu | G38: Viện Y-Dược | H38: Dược/Bào chế | I38: Wellness & Care | J38: 46016 | K38: Tốt | L38: 30000000 | M38: Tiền mặt + tính giờ NCKH | N38: 4 | O38: Có | P38: =COUNTIF(02_OUTPUT_ALL!$B:$B,A38) -> 4 | Q38: Tổng hợp đề tài KHCN cấp cơ sở của GV 2021-2025.pdf, mục NĂM 2025 | R38: Quy trình mới, dự kiến đăng ký GPHI.
A39: P2025-09 | B39: 2025 | C39: 09-2025/KHCN | D39: Nghiên cứu chiết xuất và đánh giá hoạt tính dược học của lá Quế hoa (Osmanthus fragrans) hướng tới ứng dụng trong thực phẩm chức năng | E39: Cơ sở | F39: Nguyễn Ngọc Linh | G39: Viện Y-Dược | H39: Dược/Hoạt chất tự nhiên | I39: Wellness & Care | J39: 46016 | K39: Xuất sắc | L39: 80000000 | M39: Tiền mặt + tính giờ NCKH; xin thêm 20 triệu | N39: 5 | O39: Có - giai đoạn 2 dự kiến | P39: =COUNTIF(02_OUTPUT_ALL!$B:$B,A39) -> 3 | Q39: Tổng hợp đề tài KHCN cấp cơ sở của GV 2021-2025.pdf, mục NĂM 2025 | R39: Giai đoạn 2 ghi 'Sáng chế' nhưng chưa có bằng chứng đã nộp/cấp.

Sheet 02_OUTPUT_ALL
A1: Output_ID | B1: Project_ID | C1: Năm | D1: Tên đầu ra theo hồ sơ | E1: Loại đầu ra | F1: Số lượng | G1: Đơn vị tính | H1: Trạng thái bằng chứng | I1: Dấu hiệu TSTT? | J1: Hình thức quyền/biện pháp sơ bộ | K1: Ưu tiên quản trị IP | L1: Có dấu hiệu ứng dụng? | M1: Đối chiếu với CSDL công bố | N1: Nguồn | O1: Ghi chú coding | P1: Loại đầu ra chuẩn hóa (v0.8) | Q1: Nhóm mẫu số (v0.8)
A2: O-2021-20-01 | B2: P2021-20 | C2: 2021 | D2: Báo cáo tổng kết đề tài | E2: Báo cáo nghiên cứu | F2: 1 | G2: báo cáo | H2: Đã nghiệm thu | I2: Có | J2: Quyền tác giả | K2: Thấp | L2: Không | M2: Chưa cần | N2: Tổng hợp đề tài KHCN cấp cơ sở của GV 2021-2025.pdf, tr.1 | P2: =IFERROR(VLOOKUP($E2,09B_MAP_LOAI_DAURA!$A$5:$C$18,2,0),"KHÔNG CÓ TRONG TỪ ĐIỂN") -> Báo cáo tổng kết đề tài | Q2: =IFERROR(VLOOKUP($E2,09B_MAP_LOAI_DAURA!$A$5:$C$18,3,0),"KHÔNG CÓ TRONG TỪ ĐIỂN") -> Bắt buộc hành chính
A3: O-2021-22-01 | B3: P2021-22 | C3: 2021 | D3: Báo cáo tổng kết đề tài | E3: Báo cáo nghiên cứu | F3: 1 | G3: báo cáo | H3: Đã nghiệm thu | I3: Có | J3: Quyền tác giả | K3: Thấp | L3: Không | M3: Chưa cần | N3: Tổng hợp đề tài KHCN cấp cơ sở của GV 2021-2025.pdf, tr.1 | P3: =IFERROR(VLOOKUP($E3,09B_MAP_LOAI_DAURA!$A$5:$C$18,2,0),"KHÔNG CÓ TRONG TỪ ĐIỂN") -> Báo cáo tổng kết đề tài | Q3: =IFERROR(VLOOKUP($E3,09B_MAP_LOAI_DAURA!$A$5:$C$18,3,0),"KHÔNG CÓ TRONG TỪ ĐIỂN") -> Bắt buộc hành chính
A4: O-2021-24-01 | B4: P2021-24 | C4: 2021 | D4: Báo cáo tổng kết đề tài | E4: Báo cáo nghiên cứu | F4: 1 | G4: báo cáo | H4: Đã nghiệm thu | I4: Có | J4: Quyền tác giả | K4: Thấp | L4: Không | M4: Chưa cần | N4: Tổng hợp đề tài KHCN cấp cơ sở của GV 2021-2025.pdf, tr.1 | P4: =IFERROR(VLOOKUP($E4,09B_MAP_LOAI_DAURA!$A$5:$C$18,2,0),"KHÔNG CÓ TRONG TỪ ĐIỂN") -> Báo cáo tổng kết đề tài | Q4: =IFERROR(VLOOKUP($E4,09B_MAP_LOAI_DAURA!$A$5:$C$18,3,0),"KHÔNG CÓ TRONG TỪ ĐIỂN") -> Bắt buộc hành chính
A5: O-2021-27-01 | B5: P2021-27 | C5: 2021 | D5: Báo cáo tổng kết đề tài | E5: Báo cáo nghiên cứu | F5: 1 | G5: báo cáo | H5: Đã nghiệm thu | I5: Có | J5: Quyền tác giả | K5: Thấp | L5: Không | M5: Chưa cần | N5: Tổng hợp đề tài KHCN cấp cơ sở của GV 2021-2025.pdf, tr.1 | P5: =IFERROR(VLOOKUP($E5,09B_MAP_LOAI_DAURA!$A$5:$C$18,2,0),"KHÔNG CÓ TRONG TỪ ĐIỂN") -> Báo cáo tổng kết đề tài | Q5: =IFERROR(VLOOKUP($E5,09B_MAP_LOAI_DAURA!$A$5:$C$18,3,0),"KHÔNG CÓ TRONG TỪ ĐIỂN") -> Bắt buộc hành chính
A6: O-2021-27-02 | B6: P2021-27 | C6: 2021 | D6: Bài báo đăng tạp chí quốc tế | E6: Bài báo | F6: 1 | G6: bài | H6: Hồ sơ ghi nhận | I6: Có | J6: Quyền tác giả | K6: Thấp | L6: Không | M6: Cần đối chiếu | N6: Tổng hợp đề tài KHCN cấp cơ sở của GV 2021-2025.pdf, tr.1 | P6: =IFERROR(VLOOKUP($E6,09B_MAP_LOAI_DAURA!$A$5:$C$18,2,0),"KHÔNG CÓ TRONG TỪ ĐIỂN") -> Công bố khoa học | Q6: =IFERROR(VLOOKUP($E6,09B_MAP_LOAI_DAURA!$A$5:$C$18,3,0),"KHÔNG CÓ TRONG TỪ ĐIỂN") -> Công bố
A7: O-2021-27-03 | B7: P2021-27 | C7: 2021 | D7: Bài báo đăng tạp chí trong nước | E7: Bài báo | F7: 1 | G7: bài | H7: Hồ sơ ghi nhận | I7: Có | J7: Quyền tác giả | K7: Thấp | L7: Không | M7: Cần đối chiếu | N7: Tổng hợp đề tài KHCN cấp cơ sở của GV 2021-2025.pdf, tr.1 | P7: =IFERROR(VLOOKUP($E7,09B_MAP_LOAI_DAURA!$A$5:$C$18,2,0),"KHÔNG CÓ TRONG TỪ ĐIỂN") -> Công bố khoa học | Q7: =IFERROR(VLOOKUP($E7,09B_MAP_LOAI_DAURA!$A$5:$C$18,3,0),"KHÔNG CÓ TRONG TỪ ĐIỂN") -> Công bố
A8: O-2021-28-01 | B8: P2021-28 | C8: 2021 | D8: Báo cáo tổng kết đề tài | E8: Báo cáo nghiên cứu | F8: 1 | G8: báo cáo | H8: Đã nghiệm thu | I8: Có | J8: Quyền tác giả | K8: Thấp | L8: Không | M8: Chưa cần | N8: Tổng hợp đề tài KHCN cấp cơ sở của GV 2021-2025.pdf, tr.2 | P8: =IFERROR(VLOOKUP($E8,09B_MAP_LOAI_DAURA!$A$5:$C$18,2,0),"KHÔNG CÓ TRONG TỪ ĐIỂN") -> Báo cáo tổng kết đề tài | Q8: =IFERROR(VLOOKUP($E8,09B_MAP_LOAI_DAURA!$A$5:$C$18,3,0),"KHÔNG CÓ TRONG TỪ ĐIỂN") -> Bắt buộc hành chính
A9: O-2021-28-02 | B9: P2021-28 | C9: 2021 | D9: Bài báo đăng tạp chí quốc tế | E9: Bài báo | F9: 1 | G9: bài | H9: Hồ sơ ghi nhận | I9: Có | J9: Quyền tác giả | K9: Thấp | L9: Không | M9: Cần đối chiếu | N9: Tổng hợp đề tài KHCN cấp cơ sở của GV 2021-2025.pdf, tr.2 | P9: =IFERROR(VLOOKUP($E9,09B_MAP_LOAI_DAURA!$A$5:$C$18,2,0),"KHÔNG CÓ TRONG TỪ ĐIỂN") -> Công bố khoa học | Q9: =IFERROR(VLOOKUP($E9,09B_MAP_LOAI_DAURA!$A$5:$C$18,3,0),"KHÔNG CÓ TRONG TỪ ĐIỂN") -> Công bố
A10: O-2021-28-03 | B10: P2021-28 | C10: 2021 | D10: Bài báo đăng tạp chí trong nước | E10: Bài báo | F10: 2 | G10: bài | H10: Hồ sơ ghi nhận | I10: Có | J10: Quyền tác giả | K10: Thấp | L10: Không | M10: Cần đối chiếu | N10: Tổng hợp đề tài KHCN cấp cơ sở của GV 2021-2025.pdf, tr.2 | P10: =IFERROR(VLOOKUP($E10,09B_MAP_LOAI_DAURA!$A$5:$C$18,2,0),"KHÔNG CÓ TRONG TỪ ĐIỂN") -> Công bố khoa học | Q10: =IFERROR(VLOOKUP($E10,09B_MAP_LOAI_DAURA!$A$5:$C$18,3,0),"KHÔNG CÓ TRONG TỪ ĐIỂN") -> Công bố
A11: O-2021-37-01 | B11: P2021-37 | C11: 2021 | D11: Báo cáo tổng kết đề tài | E11: Báo cáo nghiên cứu | F11: 1 | G11: báo cáo | H11: Đã nghiệm thu | I11: Có | J11: Quyền tác giả | K11: Thấp | L11: Không | M11: Chưa cần | N11: Tổng hợp đề tài KHCN cấp cơ sở của GV 2021-2025.pdf, tr.2 | P11: =IFERROR(VLOOKUP($E11,09B_MAP_LOAI_DAURA!$A$5:$C$18,2,0),"KHÔNG CÓ TRONG TỪ ĐIỂN") -> Báo cáo tổng kết đề tài | Q11: =IFERROR(VLOOKUP($E11,09B_MAP_LOAI_DAURA!$A$5:$C$18,3,0),"KHÔNG CÓ TRONG TỪ ĐIỂN") -> Bắt buộc hành chính
A12: O-2021-37-02 | B12: P2021-37 | C12: 2021 | D12: Bài báo đăng tạp chí trong nước | E12: Bài báo | F12: 1 | G12: bài | H12: Hồ sơ ghi nhận | I12: Có | J12: Quyền tác giả | K12: Thấp | L12: Không | M12: Cần đối chiếu | N12: Tổng hợp đề tài KHCN cấp cơ sở của GV 2021-2025.pdf, tr.2 | P12: =IFERROR(VLOOKUP($E12,09B_MAP_LOAI_DAURA!$A$5:$C$18,2,0),"KHÔNG CÓ TRONG TỪ ĐIỂN") -> Công bố khoa học | Q12: =IFERROR(VLOOKUP($E12,09B_MAP_LOAI_DAURA!$A$5:$C$18,3,0),"KHÔNG CÓ TRONG TỪ ĐIỂN") -> Công bố
A13: O-2022-01-01 | B13: P2022-01 | C13: 2022 | D13: Tạp chí Nghiên cứu khoa học và phát triển thuộc Trường Đại học Thành Đô | E13: Sản phẩm tổ chức/hạ tầng học thuật | F13: 1 | G13: tạp chí | H13: Đã nghiệm thu | I13: Có | J13: Tên/nhãn hiệu, nội dung tạp chí, quy trình vận hành - cần tách quyền | K13: Trung bình | L13: Có | M13: Cần kiểm tra | N13: Tổng hợp đề tài KHCN cấp cơ sở của GV 2021-2025.pdf, tr.2 | P13: =IFERROR(VLOOKUP($E13,09B_MAP_LOAI_DAURA!$A$5:$C$18,2,0),"KHÔNG CÓ TRONG TỪ ĐIỂN") -> Sản phẩm tổ chức/quản trị | Q13: =IFERROR(VLOOKUP($E13,09B_MAP_LOAI_DAURA!$A$5:$C$18,3,0),"KHÔNG CÓ TRONG TỪ ĐIỂN") -> Khác/quản trị
... A91: O-2025-09-03 | B91: P2025-09 | C91: 2025 | D91: Sáng chế - Giai đoạn 2 | E91: Sáng chế dự kiến | F91: 1 | G91: đầu ra dự kiến | H91: Kế hoạch giai đoạn 2; chưa có bằng chứng nộp/cấp | I91: Có | J91: Sáng chế - cần xác minh giai đoạn và hồ sơ đơn | K91: Cao | L91: Dự kiến | M91: Chưa cần | N91: Tổng hợp đề tài KHCN cấp cơ sở của GV 2021-2025.pdf, mục NĂM 2025 | P91: =IFERROR(VLOOKUP($E91,09B_MAP_LOAI_DAURA!$A$5:$C$18,2,0),"KHÔNG CÓ TRONG TỪ ĐIỂN") -> Đối tượng SHCN dự kiến | Q91: =IFERROR(VLOOKUP($E91,09B_MAP_LOAI_DAURA!$A$5:$C$18,3,0),"KHÔNG CÓ TRONG TỪ ĐIỂN") -> Ứng viên TSTT

Sheet 03_IP_PRIORITY_ALL
A1: Priority_IP_ID | B1: Output_ID | C1: Project_ID | D1: Năm | E1: TSTT/đầu ra ưu tiên | F1: Loại đầu ra | G1: Mức ưu tiên | H1: Hình thức quyền/biện pháp sơ bộ | I1: Dấu hiệu ứng dụng | J1: Đã nhận diện chính thức? | K1: Đã sàng lọc IP? | L1: Chủ sở hữu đã xác minh? | M1: Hành động đề xuất | N1: Nguồn | O1: Trạng thái bằng chứng
A2: PRI-001 | B2: O-2022-01-01 | C2: P2022-01 | D2: 2022 | E2: Tạp chí Nghiên cứu khoa học và phát triển thuộc Trường Đại học Thành Đô | F2: Sản phẩm tổ chức/hạ tầng học thuật | G2: Trung bình | H2: Tên/nhãn hiệu, nội dung tạp chí, quy trình vận hành - cần tách quyền | I2: Có | J2: Chưa kiểm tra | K2: Chưa kiểm tra | L2: Chưa kiểm tra | M2: Tách quyền đối với tên/nhãn hiệu, nội dung, quy trình vận hành; xác minh chủ sở hữu và cơ chế khai thác. | N2: Tổng hợp đề tài KHCN cấp cơ sở của GV 2021-2025.pdf, tr.2 | O2: Đã nghiệm thu
A3: PRI-002 | B3: O-2022-02-01 | C3: P2022-02 | D3: 2022 | E3: Quy chế tuyển sinh và đào tạo trình độ thạc sĩ tại Trường Đại học Thành Đô | F3: Văn bản/quy trình quản trị | G3: Trung bình | H3: Quyền tác giả đối với hình thức thể hiện; tri thức/quy trình quản trị | I3: Có | J3: Chưa kiểm tra | K3: Chưa kiểm tra | L3: Chưa kiểm tra | M3: Tài liệu hóa phương pháp/quy trình, xác định chủ sở hữu và bằng chứng sử dụng; xem xét quyền tác giả/know-how và giá trị ứng dụng. | N3: Tổng hợp đề tài KHCN cấp cơ sở của GV 2021-2025.pdf, tr.2 | O3: Đã nghiệm thu
A4: PRI-003 | B4: O-2022-37-02 | C4: P2022-37 | D4: 2022 | E4: Mô hình kiểm tra và sửa chữa hệ thống khởi động điện trên ô tô | F4: Mô hình/prototype | G4: Cao | H4: Giải pháp kỹ thuật/KDCN/know-how - cần sàng lọc | I4: Có | J4: Chưa kiểm tra | K4: Chưa kiểm tra | L4: Chưa kiểm tra | M4: Rà soát tính mới/trình độ sáng tạo/khả năng áp dụng; kiểm tra công bố trước bảo hộ, chủ sở hữu và lựa chọn sáng chế/GPHI/BMKD/KDCN phù hợp. | N4: Tổng hợp đề tài KHCN cấp cơ sở của GV 2021-2025.pdf, tr.3 | O4: Đã nghiệm thu
A5: PRI-004 | B5: O-2022-39-02 | C5: P2022-39 | D5: 2022 | E5: Sản phẩm cầm máu ở dạng màng | F5: Sản phẩm/prototype | G5: Cao | H5: Giải pháp kỹ thuật/sáng chế-GPHI/know-how - cần sàng lọc | I5: Có | J5: Chưa kiểm tra | K5: Chưa kiểm tra | L5: Chưa kiểm tra | M5: Rà soát tính mới/trình độ sáng tạo/khả năng áp dụng; kiểm tra công bố trước bảo hộ, chủ sở hữu và lựa chọn sáng chế/GPHI/BMKD/KDCN phù hợp. | N5: Tổng hợp đề tài KHCN cấp cơ sở của GV 2021-2025.pdf, tr.3 | O5: Đã nghiệm thu
A6: PRI-005 | B6: O-2022-40-02 | C6: P2022-40 | D6: 2022 | E6: Bộ mẫu cây thuốc | F6: Bộ mẫu/collection | G6: Trung bình | H6: Tác phẩm sưu tập/CSDL/học liệu - cần xác định cấu trúc | I6: Có | J6: Chưa kiểm tra | K6: Chưa kiểm tra | L6: Chưa kiểm tra | M6: Xác định cấu trúc sáng tạo, quyền tác giả/CSDL nếu phù hợp; đo mức sử dụng trong đào tạo và chi phí thay thế. | N6: Tổng hợp đề tài KHCN cấp cơ sở của GV 2021-2025.pdf, tr.3 | O6: Đã nghiệm thu
A7: PRI-006 | B7: O-2023-01-03 | C7: P2023-01 | D7: 2023 | E7: Giải pháp bồi dưỡng phương pháp tư duy biện chứng Hồ Chí Minh cho sinh viên Trường Đại học Thành Đô | F7: Giải pháp/phương pháp ứng dụng | G7: Trung bình | H7: Quyền tác giả/know-how phương pháp giáo dục | I7: Có | J7: Chưa kiểm tra | K7: Chưa kiểm tra | L7: Chưa kiểm tra | M7: Tài liệu hóa phương pháp/quy trình, xác định chủ sở hữu và bằng chứng sử dụng; xem xét quyền tác giả/know-how và giá trị ứng dụng. | N7: Tổng hợp đề tài KHCN cấp cơ sở của GV 2021-2025.pdf, tr.4 | O7: Hồ sơ ghi ứng dụng tại Trường
A8: PRI-007 | B8: O-2023-02-03 | C8: P2023-02 | D8: 2023 | E8: Giải pháp nâng cao chất lượng đào tạo học phần Thực hành hướng dẫn du lịch tại Trường Đại học Thành Đô | F8: Giải pháp/phương pháp ứng dụng | G8: Trung bình | H8: Quyền tác giả/know-how phương pháp đào tạo | I8: Có | J8: Chưa kiểm tra | K8: Chưa kiểm tra | L8: Chưa kiểm tra | M8: Tài liệu hóa phương pháp/quy trình, xác định chủ sở hữu và bằng chứng sử dụng; xem xét quyền tác giả/know-how và giá trị ứng dụng. | N8: Tổng hợp đề tài KHCN cấp cơ sở của GV 2021-2025.pdf, tr.4 | O8: Hồ sơ ghi ứng dụng tại Trường
A9: PRI-008 | B9: O-2023-03-03 | C9: P2023-03 | D9: 2023 | E9: Phương pháp giảng dạy giúp sinh viên tự học nhằm nâng cao chất lượng học tập | F9: Giải pháp/phương pháp ứng dụng | G9: Trung bình | H9: Quyền tác giả/know-how phương pháp giáo dục | I9: Có | J9: Chưa kiểm tra | K9: Chưa kiểm tra | L9: Chưa kiểm tra | M9: Tài liệu hóa phương pháp/quy trình, xác định chủ sở hữu và bằng chứng sử dụng; xem xét quyền tác giả/know-how và giá trị ứng dụng. | N9: Tổng hợp đề tài KHCN cấp cơ sở của GV 2021-2025.pdf, tr.5 | O9: Hồ sơ ghi ứng dụng tại Trường
A10: PRI-009 | B10: O-2023-04-03 | C10: P2023-04 | D10: 2023 | E10: Ứng dụng flipped classroom cho sinh viên | F10: Giải pháp/phương pháp ứng dụng | G10: Trung bình | H10: Quyền tác giả/know-how phương pháp giáo dục | I10: Có | J10: Chưa kiểm tra | K10: Chưa kiểm tra | L10: Chưa kiểm tra | M10: Tài liệu hóa phương pháp/quy trình, xác định chủ sở hữu và bằng chứng sử dụng; xem xét quyền tác giả/know-how và giá trị ứng dụng. | N10: Tổng hợp đề tài KHCN cấp cơ sở của GV 2021-2025.pdf, tr.5 | O10: Hồ sơ ghi ứng dụng tại Trường
A11: PRI-010 | B11: O-2023-05-03 | C11: P2023-05 | D11: 2023 | E11: Tài liệu/giải pháp tham khảo xây dựng chính sách và Quy chế hoạt động KHCN | F11: Giải pháp/phương pháp ứng dụng | G11: Trung bình | H11: Quyền tác giả/know-how quản trị | I11: Có | J11: Chưa kiểm tra | K11: Chưa kiểm tra | L11: Chưa kiểm tra | M11: Tài liệu hóa phương pháp/quy trình, xác định chủ sở hữu và bằng chứng sử dụng; xem xét quyền tác giả/know-how và giá trị ứng dụng. | N11: Tổng hợp đề tài KHCN cấp cơ sở của GV 2021-2025.pdf, tr.6 | O11: Hồ sơ ghi khả năng ứng dụng
A12: PRI-011 | B12: O-2023-07-03 | C12: P2023-07 | D12: 2023 | E12: Giải pháp nâng cao nhận thức pháp luật cho sinh viên | F12: Giải pháp/phương pháp ứng dụng | G12: Trung bình | H12: Quyền tác giả/know-how giáo dục pháp luật | I12: Có | J12: Chưa kiểm tra | K12: Chưa kiểm tra | L12: Chưa kiểm tra | M12: Tài liệu hóa phương pháp/quy trình, xác định chủ sở hữu và bằng chứng sử dụng; xem xét quyền tác giả/know-how và giá trị ứng dụng. | N12: Tổng hợp đề tài KHCN cấp cơ sở của GV 2021-2025.pdf, tr.6 | O12: Hồ sơ ghi ứng dụng tại Trường
A13: PRI-012 | B13: O-2023-08-02 | C13: P2023-08 | D13: 2023 | E13: Tinh dầu Citrus grandis (L.) Osbeck 100ml | F13: Sản phẩm/prototype | G13: Cao | H13: Hiện thân của quy trình/know-how; có thể sàng lọc sáng chế-GPHI | I13: Có | J13: Chưa kiểm tra | K13: Chưa kiểm tra | L13: Chưa kiểm tra | M13: Rà soát tính mới/trình độ sáng tạo/khả năng áp dụng; kiểm tra công bố trước bảo hộ, chủ sở hữu và lựa chọn sáng chế/GPHI/BMKD/KDCN phù hợp. | N13: Tổng hợp đề tài KHCN cấp cơ sở của GV 2021-2025.pdf, tr.7 | O13: Đã nghiệm thu
... A27: PRI-026 | B27: O-2025-09-03 | C27: P2025-09 | D27: 2025 | E27: Sáng chế - Giai đoạn 2 | F27: Sáng chế dự kiến | G27: Cao | H27: Sáng chế - cần xác minh giai đoạn và hồ sơ đơn | I27: Dự kiến | J27: Chưa kiểm tra | K27: Chưa kiểm tra | L27: Chưa kiểm tra | M27: Rà soát tính mới/trình độ sáng tạo/khả năng áp dụng; kiểm tra công bố trước bảo hộ, chủ sở hữu và lựa chọn sáng chế/GPHI/BMKD/KDCN phù hợp. | N27: Tổng hợp đề tài KHCN cấp cơ sở của GV 2021-2025.pdf, mục NĂM 2025 | O27: Kế hoạch giai đoạn 2; chưa có bằng chứng nộp/cấp

Sheet 13B_PROTECTION_FULL
A1: Source_ID | B1: Loại hình chuẩn hóa | C1: Tên và nội dung | D1: Số/Ký mã hiệu theo nguồn | E1: Năm | F1: Nơi cấp | G1: Vai trò theo nguồn | H1: Chủ sở hữu | I1: Trạng thái hồ sơ suy ra tối thiểu | J1: Phạm vi đối với nghiên cứu ĐHTĐ | K1: Project_ID liên quan sơ bộ | L1: Mức độ liên kết | M1: Ghi chú phương pháp
A2: SRC-IP-001 | B2: Bản quyền tác giả | C2: Bộ Logo Trường Đại học Thành Đô | D2: 6534/2021/QTG | E2: 2021 | F2: Cục Bản quyền tác giả, Bộ Văn hóa, Thể thao và Du lịch | G2: Tác giả | H2: ĐHTĐ | I2: Đã có số đăng ký | J2: Trực tiếp ĐHTĐ
A3: SRC-IP-002 | B3: Bản quyền tác giả | C3: Bộ Logo UNIGO | D3: 1584/2022/QTG | E3: 2022 | F3: Cục Bản quyền tác giả, Bộ Văn hóa, Thể thao và Du lịch | G3: Tác giả | H3: CTY UNIGO | I3: Đã có số đăng ký | J3: Ngoài phạm vi ĐHTĐ trực tiếp | M3: Giữ trong danh mục nguồn đầy đủ nhưng không đưa vào tử số TSTT trực tiếp của ĐHTĐ.
A4: SRC-IP-003 | B4: Bản quyền tác giả | C4: Bộ Logo Hệ sinh thái giáo dục Trường Đại học Thành Đô | D4: 5790/2023/QTG | E4: 2023 | F4: Cục Bản quyền tác giả, Bộ Văn hóa, Thể thao và Du lịch | G4: Tác giả | H4: ĐHTĐ | I4: Đã có số đăng ký | J4: Trực tiếp ĐHTĐ
A5: SRC-IP-004 | B5: Bản quyền tác giả | C5: Bộ Logo Chương trình Thần đồng Tiếng Việt - Vietnamese LangMaster Kids | D5: 5550/2025/QTG | E5: 2025 | F5: Cục Bản quyền tác giả, Bộ Văn hóa, Thể thao và Du lịch | G5: Tác giả | H5: Trường UNIGO | I5: Đã có số đăng ký | J5: Ngoài phạm vi ĐHTĐ trực tiếp | M5: Giữ để phân biệt tài sản hệ sinh thái với tài sản của ĐHTĐ.
A6: SRC-IP-005 | B6: Nhãn hiệu | C6: Nhãn hiệu chữ "Unigo" | D6: 364106 | E6: 2020 | F6: Cục Sở hữu trí tuệ, Bộ KH&CN | G6: Không ghi | H6: Phan Thị Thanh Thảo | I6: Đã có số văn bằng/ký hiệu | J6: Ngoài phạm vi ĐHTĐ trực tiếp | M6: Năm 2020, ngoài giai đoạn phân tích chính 2021-2025.
A7: SRC-IP-006 | B7: Nhãn hiệu | C7: Thanh do University | D7: 468353 | E7: 2023 | F7: Cục Sở hữu trí tuệ, Bộ KH&CN | G7: Tác giả | H7: ĐHTĐ | I7: Đã có số văn bằng/ký hiệu | J7: Trực tiếp ĐHTĐ
A8: SRC-IP-007 | B8: Nhãn hiệu | C8: Thado Edupark | D8: 545780 | E8: 2025 | F8: Cục Sở hữu trí tuệ, Bộ KH&CN | G8: Tác giả | H8: ĐHTĐ | I8: Đã có số văn bằng/ký hiệu | J8: Trực tiếp ĐHTĐ
A9: SRC-IP-008 | B9: Nhãn hiệu | C9: Double2n | D9: Tiếp nhận đơn | E9: 2023 | F9: Cục Sở hữu trí tuệ, Bộ KH&CN | G9: Đồng tác giả | H9: ĐHTĐ, CTY Thanh Huế | I9: Tiếp nhận đơn; chưa coi là đã được cấp | J9: Trực tiếp ĐHTĐ | M9: Không có số đơn trong danh sách nguồn được cung cấp.
A10: SRC-IP-009 | B10: Nhãn hiệu | C10: Thần Đồng Tiếng Việt | D10: Chờ tiếp nhận | E10: 2025 | F10: Cục Sở hữu trí tuệ, Bộ KH&CN | G10: Không ghi | H10: Phan Thị Thanh Thảo | I10: Chờ tiếp nhận; chưa coi là đã nộp/được cấp | J10: Ngoài phạm vi ĐHTĐ trực tiếp
A11: SRC-IP-010 | B11: Kiểu dáng công nghiệp | C11: Dung dịch vệ sinh phụ nữ | D11: 3-0039693-000 | E11: 2024 | F11: Cục Sở hữu trí tuệ, Bộ KH&CN | G11: Đồng tác giả | H11: ĐHTĐ, CTY Thanh Huế | I11: Đã có số/ký mã hiệu | J11: Trực tiếp ĐHTĐ
A12: SRC-IP-011 | B12: Kiểu dáng công nghiệp | C12: Tinh dầu vỏ bưởi đào | D12: 3-0039694-000 | E12: 2024 | F12: Cục Sở hữu trí tuệ, Bộ KH&CN | G12: Đồng tác giả | H12: ĐHTĐ, CTY Thanh Huế | I12: Đã có số/ký mã hiệu | J12: Trực tiếp ĐHTĐ | K12: P2023-08 | L12: Cao | M12: Tên sản phẩm và bối cảnh hợp tác phù hợp; vẫn cần hồ sơ gốc để khẳng định nguồn từ đề tài.
A13: SRC-IP-012 | B13: Kiểu dáng công nghiệp | C13: Xịt miệng - họng thảo dược | D13: 3-0039902-000 | E13: 2024 | F13: Cục Sở hữu trí tuệ, Bộ KH&CN | G13: Đồng tác giả | H13: ĐHTĐ, CTY Thanh Huế | I13: Đã có số/ký mã hiệu | J13: Trực tiếp ĐHTĐ | M13: Chưa có đầu ra đề tài hiện tại đủ mạnh để liên kết.
A14: SRC-IP-013 | B14: Kiểu dáng công nghiệp | C14: Dầu gội nha đam - bưởi đào | D14: 3-0039695-000 | E14: 2024 | F14: Cục Sở hữu trí tuệ, Bộ KH&CN | G14: Đồng tác giả | H14: ĐHTĐ, CTY Thanh Huế | I14: Đã có số/ký mã hiệu | J14: Trực tiếp ĐHTĐ | M14: Chưa có đầu ra đề tài hiện tại đủ mạnh để liên kết.
A15: SRC-IP-014 | B15: Kiểu dáng công nghiệp | C15: Kem ủ xả tóc - Chiết xuất từ Bưởi - Bơ - Dừa | D15: 3-0039696-000 | E15: 2024 | F15: Cục Sở hữu trí tuệ, Bộ KH&CN | G15: Đồng tác giả | H15: ĐHTĐ, CTY Thanh Huế | I15: Đã có số/ký mã hiệu | J15: Trực tiếp ĐHTĐ | M15: Chưa có đầu ra đề tài hiện tại đủ mạnh để liên kết.
A16: SRC-IP-015 | B16: Sáng chế | C16: Các hợp chất furofuran lignan glucoside và phương pháp chiết các hợp chất này từ lá của cây quế hoa (Osmanthus fragrans) | E16: 2025 | F16: Cục Sở hữu trí tuệ, Bộ KH&CN | G16: Nguyễn Ngọc Linh (ghi tại cột Vai trò) | H16: ĐHTĐ | I16: Có trong danh sách; chưa có số/ký mã hiệu trong nguồn | J16: Trực tiếp ĐHTĐ | K16: P2025-09 | L16: Rất cao | M16: Không suy ra đã nộp hay đã cấp khi chưa có số đơn/văn bằng.
A17: SRC-IP-016 | B17: Sáng chế | C17: Phương pháp chiết tách và phân lập hợp chất Isoembigenin từ cây Piper aduncum L. | E17: 2026 | F17: Cục Sở hữu trí tuệ, Bộ KH&CN | G17: Nguyễn Ngọc Linh (ghi tại cột Vai trò) | H17: ĐHTĐ | I17: Có trong danh sách; chưa có số/ký mã hiệu trong nguồn | J17: Trực tiếp ĐHTĐ | M17: Ngoài giai đoạn 2021-2025; giữ để theo dõi pipeline tiếp theo.

Sheet 08B_KPI_v08
A1: KPI BẢN v0.8 – MỌI CHỈ SỐ GHI RÕ MẪU SỐ VÀ TÍNH BẰNG CÔNG THỨC
A2: Thay thế 08_KPI_ALL (giá trị gõ tay). Tỷ lệ chỉ tính trên mẫu số đã loại đầu ra hành chính bắt buộc.
A4: Mã | B4: Chỉ số | C4: Tử số | D4: Mẫu số | E4: Giá trị | F4: Ghi chú diễn giải
A5: K01 | B5: Tổng số đề tài cấp cơ sở đã kiểm kê | E5: =COUNTA(01_PROJECT_ALL!$A$2:$A$39) -> 38 | F5: Đơn vị phân tích: 1 đề tài.
A6: K02 | B6: Tổng số dòng đầu ra | E6: =COUNTA(02_OUTPUT_ALL!$A$2:$A$91) -> 90 | F6: Dòng đầu ra, không phải số sản phẩm.
A7: K03 | B7: Trong đó: báo cáo tổng kết (bắt buộc hành chính) | E7: =COUNTIF(02_OUTPUT_ALL!$Q$2:$Q$91,"Bắt buộc hành chính") -> 34 | F7: Loại khỏi mọi mẫu số tính tỷ lệ.
A8: K04 | B8: Trong đó: công bố khoa học | E8: =COUNTIF(02_OUTPUT_ALL!$Q$2:$Q$91,"Công bố") -> 30 | F8: Bài báo, kỷ yếu; chưa đối chiếu DOI.
A9: K05 | B9: Trong đó: ứng viên tài sản trí tuệ | E9: =COUNTIF(02_OUTPUT_ALL!$Q$2:$Q$91,"Ứng viên TSTT") -> 24 | F9: Sản phẩm, quy trình, bộ mẫu, học liệu, SHCN dự kiến.
A10: K06 | B10: Trong đó: sản phẩm tổ chức/quản trị | E10: =COUNTIF(02_OUTPUT_ALL!$Q$2:$Q$91,"Khác/quản trị") -> 2 | F10: Không đưa vào phân tích TSTT.
A11: K07 | B11: Mẫu số phân tích TSTT | E11: =E6-E7 -> 56 | F11: K02 trừ K03.
A12: K08 | B12: Tỷ lệ ứng viên TSTT trên mẫu số phân tích | C12: =E9 -> 24 | D12: =E11 -> 56 | E12: =IFERROR(C12/D12,"") -> 0.42857143 | F12: Không gọi là tỷ lệ bảo hộ.
A13: K09 | B13: Số đề tài có ít nhất 1 ứng viên TSTT | E13: =SUMPRODUCT(--(COUNTIFS(02_OUTPUT_ALL!$B$2:$B$91,01_PROJECT_ALL!$A$2:$A$39,02_OUTPUT_ALL!$Q$2:$Q$91,"Ứng viên TSTT")>0)) -> 17 | F13: Tính trên 38 đề tài.
A14: K10 | B14: Tỷ lệ đề tài có ít nhất 1 ứng viên TSTT | C14: =E13 -> 17 | D14: =E5 -> 38 | E14: =IFERROR(C14/D14,"") -> 0.44736842 | F14: Mẫu số gồm cả đề tài thuần lý thuyết.
A15: K11 | B15: Số đề tài hồ sơ ghi có đầu ra ứng dụng | E15: =COUNTIF(01_PROJECT_ALL!$O$2:$O$39,"Có") -> 18 | F15: 19 đề tài ghi 'Không ghi nhận' — không suy ra là không có.
A16: K12 | B16: Tỷ lệ đề tài hồ sơ ghi có đầu ra ứng dụng | C16: =E15 -> 18 | D16: =E5 -> 38 | E16: =IFERROR(C16/D16,"") -> 0.47368421 | F16: Là tỷ lệ ghi nhận trong hồ sơ, không phải tỷ lệ ứng dụng thực tế.
A17: K13 | B17: Đối tượng SHTT ĐHTĐ sở hữu/đồng sở hữu, 2021–2025 | E17: =COUNTIFS(13B_PROTECTION_FULL!$J$2:$J$17,"Trực tiếp ĐHTĐ",13B_PROTECTION_FULL!$E$2:$E$17,"<=2025") -> 11 | F17: Loại tài sản của UNIGO và cá nhân.
A18: K14 | B18: Trong đó đã có số văn bằng/số đăng ký | E18: =COUNTIFS(13B_PROTECTION_FULL!$J$2:$J$17,"Trực tiếp ĐHTĐ",13B_PROTECTION_FULL!$E$2:$E$17,"<=2025",13B_PROTECTION_FULL!$I$2:$I$17,"Đã có*") -> 9 | F18: Loại Double2n (tiếp nhận đơn) và sáng chế chưa có số.
A19: K15 | B19: Tỷ lệ đối tượng đã có số trên portfolio trực tiếp | C19: =E18 -> 9 | D19: =E17 -> 11 | E19: =IFERROR(C19/D19,"") -> 0.81818182 | F19: Chỉ mô tả trạng thái hồ sơ, không phải hiệu quả bảo hộ.
A21: Lưu ý: K05 (ứng viên TSTT theo từ điển v0.8) khác K-cũ 'đầu ra ưu tiên IP' ở 03_IP_PRIORITY_ALL vì hai tiêu chí phân loại khác nhau. Khi viết luận án phải nêu rõ đang dùng định nghĩa nào.

Sheet 24_QC_CHECKS
A1: KIỂM TRA CHẤT LƯỢNG DỮ LIỆU – TỰ ĐỘNG
A2: Mọi dòng phải cho kết quả OK. Chạy lại sau mỗi lần sửa dữ liệu.
A4: Mã | B4: Nội dung kiểm tra | C4: Kỳ vọng | D4: Kết quả | E4: Kết luận
A5: QC01 | B5: Số Project_ID bị trùng trong 01_PROJECT_ALL | C5: 0 | D5: =COUNTA(01_PROJECT_ALL!$A$2:$A$39)-SUMPRODUCT(1/COUNTIF(01_PROJECT_ALL!$A$2:$A$39,01_PROJECT_ALL!$A$2:$A$39)) -> 0 | E5: =IF(D5=C5,"OK","CẦN XỬ LÝ") -> OK
A6: QC02 | B6: Số Output_ID bị trùng trong 02_OUTPUT_ALL | C6: 0 | D6: =COUNTA(02_OUTPUT_ALL!$A$2:$A$91)-SUMPRODUCT(1/COUNTIF(02_OUTPUT_ALL!$A$2:$A$91,02_OUTPUT_ALL!$A$2:$A$91)) -> 0 | E6: =IF(D6=C6,"OK","CẦN XỬ LÝ") -> OK
A7: QC03 | B7: Đầu ra trỏ tới đề tài không tồn tại | C7: 0 | D7: =SUMPRODUCT(--(COUNTIF(01_PROJECT_ALL!$A$2:$A$39,02_OUTPUT_ALL!$B$2:$B$91)=0)) -> 0 | E7: =IF(D7=C7,"OK","CẦN XỬ LÝ") -> OK
A8: QC04 | B8: Dòng ưu tiên IP trỏ tới đầu ra không tồn tại | C8: 0 | D8: =SUMPRODUCT(--(COUNTIF(02_OUTPUT_ALL!$A$2:$A$91,03_IP_PRIORITY_ALL!$B$2:$B$27)=0)) -> 0 | E8: =IF(D8=C8,"OK","CẦN XỬ LÝ") -> OK
A9: QC05 | B9: Loại đầu ra không có trong từ điển 09B | C9: 0 | D9: =SUMPRODUCT(--(COUNTIF(09B_MAP_LOAI_DAURA!$A$5:$A$18,02_OUTPUT_ALL!$E$2:$E$91)=0)) -> 0 | E9: =IF(D9=C9,"OK","CẦN XỬ LÝ") -> OK
A10: QC06 | B10: Tổng 4 nhóm mẫu số phải bằng tổng dòng đầu ra | C10: 0 | D10: =COUNTA(02_OUTPUT_ALL!$A$2:$A$91)-COUNTIF(02_OUTPUT_ALL!$Q$2:$Q$91,"Bắt buộc hành chính")-COUNTIF(02_OUTPUT_ALL!$Q$2:$Q$91,"Công bố")-COUNTIF(02_OUTPUT_ALL!$Q$2:$Q$91,"Ứng viên TSTT")-COUNTIF(02_OUTPUT_ALL!$Q$2:$Q$91,"Khác/quản trị") -> 0 | E10: =IF(D10=C10,"OK","CẦN XỬ LÝ") -> OK
A11: QC07 | B11: Đề tài không có dòng đầu ra nào | C11: 0 | D11: =SUMPRODUCT(--(COUNTIF(02_OUTPUT_ALL!$B$2:$B$91,01_PROJECT_ALL!$A$2:$A$39)=0)) -> 0 | E11: =IF(D11=C11,"OK","CẦN XỬ LÝ") -> OK
A12: QC08 | B12: Đối tượng SHTT thiếu cả số văn bằng lẫn ghi chú trạng thái | C12: 0 | D12: =SUMPRODUCT(--((13B_PROTECTION_FULL!$D$2:$D$17="")*(13B_PROTECTION_FULL!$I$2:$I$17=""))) -> 0 | E12: =IF(D12=C12,"OK","CẦN XỬ LÝ") -> OK

Sheet 09B_MAP_LOAI_DAURA
A1: BẢNG ÁNH XẠ LOẠI ĐẦU RA – CHUẨN HÓA v0.8
A2: Giữ nguyên giá trị gốc trong 02_OUTPUT_ALL cột E; cột P và Q là giá trị chuẩn hóa tra theo bảng này.
A4: Giá trị gốc trong hồ sơ | B4: Loại đầu ra chuẩn hóa (8 nhóm) | C4: Nhóm mẫu số
A5: Báo cáo nghiên cứu | B5: Báo cáo tổng kết đề tài | C5: Bắt buộc hành chính
A6: Bài báo | B6: Công bố khoa học | C6: Công bố
A7: Công bố khoa học | B7: Công bố khoa học | C7: Công bố
A8: Bài hội thảo | B8: Công bố khoa học | C8: Công bố
A9: Sản phẩm/prototype | B9: Sản phẩm/mô hình/prototype | C9: Ứng viên TSTT
A10: Mô hình/prototype | B10: Sản phẩm/mô hình/prototype | C10: Ứng viên TSTT
A11: Quy trình/công thức | B11: Quy trình/giải pháp/công thức | C11: Ứng viên TSTT
A12: Giải pháp/phương pháp ứng dụng | B12: Quy trình/giải pháp/công thức | C12: Ứng viên TSTT
A13: Bộ mẫu/collection | B13: Bộ mẫu/CSDL/học liệu | C13: Ứng viên TSTT
A14: Cẩm nang/học liệu | B14: Bộ mẫu/CSDL/học liệu | C14: Ứng viên TSTT
A15: Sáng chế dự kiến | B15: Đối tượng SHCN dự kiến | C15: Ứng viên TSTT
... A18: Văn bản/quy trình quản trị | B18: Sản phẩm tổ chức/quản trị | C18: Khác/quản trị

Sheet 06_LEGAL_GAP
A1: Gap_ID | B1: Khâu quản trị | C1: Yêu cầu/quy định nội bộ | D1: Nguồn quy định | E1: Bằng chứng thực tế cần thu | F1: Bằng chứng hiện có | G1: Mức tuân thủ (0-2) | H1: Mức độ rủi ro | I1: Khoảng cách sơ bộ | J1: Dữ liệu cần xin thêm | K1: Khuyến nghị kiểm tra
A2: G01 | B2: Nhận diện và kiểm kê TSTT | C2: Quy chế quản trị TSTT bao quát tạo lập, xác lập, bảo vệ và khai thác thương mại TSTT; cần có cơ chế nhận diện TSTT phát sinh. | D2: QC SHTT ĐHTĐ.docx | E2: Sổ/CSDL TSTT, phiếu khai báo, hồ sơ nhận diện | F2: Người dùng xác nhận hiện không có phiếu khai báo/biên bản nhận diện hoặc sổ/CSDL tương đương. | H2: Cao | I2: Khoảng trống về tài liệu hóa và khả năng truy vết khâu nhận diện; chưa đủ căn cứ để kết luận hoạt động nhận diện không diễn ra. | J2: CSDL/sổ đăng ký TSTT | K2: Kiểm tra có danh mục TSTT tập trung và thời điểm ghi nhận.
A3: G02 | B3: Xác định chủ sở hữu | C3: Quy chế KHCN 2021 quy định quyền SHTT đối với kết quả nghiên cứu đề tài thuộc Trường; tác giả hưởng quyền tác giả và các bên thỏa thuận quyền nộp đơn/phân chia lợi ích. | D3: QĐ 213/QĐ-ĐHTĐ 2021 | E3: Hợp đồng/thuyết minh/biên bản xác định chủ sở hữu từng đề tài | F3: Có quy định chung; chưa đối chiếu hồ sơ từng dự án | H3: Cao | I3: Có nguy cơ gap giữa quy định chung và hồ sơ cụ thể | J3: Hợp đồng đề tài; thỏa thuận đồng sở hữu | K3: Lấy mẫu 10–20 đề tài có sản phẩm ứng dụng để audit.
A4: G03 | B4: Bảo mật trước công bố | C4: Quy chế KHCN 2021 yêu cầu bảo mật kết quả; phổ biến/sử dụng phải có thỏa thuận bằng văn bản trong trường hợp thuộc phạm vi điều chỉnh. | D4: QĐ 213/QĐ-ĐHTĐ 2021 | E4: Ngày công bố bài báo vs ngày sàng lọc/nộp đơn | F4: Có các đề tài vừa có bài báo vừa dự kiến đăng ký GPHI | H4: Cao | I4: Có rủi ro công bố trước khi hoàn tất sàng lọc IP | J4: Ngày accepted/published và ngày nộp đơn | K4: Ưu tiên audit P2025-06 và P2025-07.
A5: G04 | B5: Đăng ký xác lập quyền | C5: Cần thống nhất quyền nộp đơn và thực hiện đăng ký khi có tài sản đủ điều kiện. | D5: QĐ 213/QĐ-ĐHTĐ 2021; QC SHTT | E5: Số đơn, ngày nộp, trạng thái, chủ đơn | F5: Có danh sách đơn/văn bằng tổng hợp, nhưng người dùng xác nhận không có hồ sơ sàng lọc/tra cứu khả năng bảo hộ. | H5: Cao | I5: Có đầu ra được bảo hộ/đang xử lý nhưng thiếu hồ sơ giải thích quyết định chọn đối tượng, loại quyền và thời điểm nộp. | J5: Danh sách đơn SHTT của Trường | K5: Đối chiếu từng IP_ID với dữ liệu/hồ sơ trường.
A6: G05 | B6: Ứng dụng/chuyển giao | C6: Quy chế KHCN quy định chuyển giao và phân chia lợi ích; sản phẩm hợp tác DN phải tuân thủ hợp đồng và quyền SHTT. | D6: QĐ 213/QĐ-ĐHTĐ 2021 | E6: Hợp đồng chuyển giao, biên bản bàn giao, đối tác, doanh thu | F6: Người dùng xác nhận không có hợp đồng chuyển giao/cấp phép/biên bản thương mại hóa trong bộ hồ sơ hiện có. | H6: Cao | I6: Không thể xác nhận giao dịch thương mại chỉ từ mô tả 'chuyển giao/ứng dụng' trong hồ sơ nghiệm thu. | J6: Hợp đồng/biên bản/doanh thu | K6: Phân biệt chuyển giao nội bộ, cấp phép, bán sản phẩm, CGCN ra ngoài.
A7: G06 | B7: Phân chia lợi ích | C7: Quy chế KHCN 2021 có tỷ lệ phân chia lợi nhuận cho một số trường hợp thương mại hóa/chuyển giao. | D7: QĐ 213/QĐ-ĐHTĐ 2021 | E7: Chứng từ phân chia lợi ích thực tế | F7: Chưa có trong bộ dữ liệu | H7: Trung bình | I7: Chưa đánh giá | J7: Hồ sơ tài chính, quyết định chi | K7: Kiểm tra đã từng kích hoạt cơ chế này chưa.
A8: G07 | B8: Định giá TSTT | C8: Đề cương nghiên cứu đặt vấn đề hiệu quả quản lý/bảo hộ/thương mại hóa; dữ liệu hiện chưa cho thấy quy trình định giá. | D8: Đề xuất KHCN 2026 + hồ sơ nội bộ cần kiểm chứng | E8: Hồ sơ thẩm định/định giá, tiêu chí lựa chọn | F8: Chưa có trong bộ dữ liệu | H8: Trung bình | I8: Có thể là khoảng trống quản trị | J8: Biên bản định giá/thẩm định | K8: Không kết luận 'không có' trước khi kiểm tra hồ sơ tài chính/pháp chế.
A9: G08 | B9: Theo dõi vòng đời quyền | C9: Quản trị TSTT cần theo dõi tình trạng đơn/văn bằng và khai thác. | D9: QC SHTT ĐHTĐ.docx | E9: Ngày nộp/cấp/gia hạn/hết hạn/chi phí | F9: Bảng thống kê văn bằng hiện mới là ảnh/danh sách rời | H9: Trung bình | I9: Dữ liệu phân tán | J9: Sổ theo dõi văn bằng | K9: Chuẩn hóa thành PROTECTION table.
A10: G09 | B10: Liên kết ĐH-DN | C10: Quy chế KHCN khuyến khích hợp tác nghiên cứu, chuyển giao công nghệ với doanh nghiệp. | D10: QĐ 213/QĐ-ĐHTĐ 2021 | E10: Hợp đồng hợp tác, contribution, điều khoản IP | F10: Một số đề tài có yếu tố hợp tác ĐH-DN | H10: Trung bình | I10: Chưa biết điều khoản IP được xác lập từ đầu hay sau nghiên cứu | J10: Hợp đồng hợp tác | K10: Audit điều khoản background IP/foreground IP.
A11: G10 | B11: Ứng dụng nội bộ | C11: Kết quả KHCN có thể phục vụ đào tạo, nghiên cứu và phát triển Nhà trường. | D11: QĐ 213/QĐ-ĐHTĐ 2021 | E11: Minh chứng sử dụng trong môn học/phòng thực hành/quản trị | F11: Một số sản phẩm có mục tiêu đào tạo rõ (bộ mẫu, panel) | H11: Trung bình | I11: Chưa có chỉ số đo mức sử dụng | J11: Kế hoạch môn học, biên bản bàn giao, số lượt sử dụng | K11: Tách 'có sản phẩm' khỏi 'được sử dụng thực tế'.
A12: G11 | B12: Cơ sở dữ liệu và số hóa | C12: Đề cương nhấn mạnh số hóa quản trị TSTT; QC TSTT tạo nền cho quản lý tập trung. | D12: Đề xuất KHCN 2026; QC SHTT | E12: Phần mềm/CSDL/IP disclosure workflow | F12: Chưa có bằng chứng trong bộ dữ liệu | H12: Trung bình | I12: Chưa đánh giá | J12: Quy trình phần mềm/phân quyền | K12: Khảo sát Phòng KHCN về hệ thống đang dùng.
A13: G12 | B13: Động lực cá nhân | C13: Quy chế có cơ chế quyền lợi/khen thưởng; hiệu quả phụ thuộc nhận thức và động lực giảng viên. | D13: QĐ 213/QĐ-ĐHTĐ 2021; đề cương 2026 | E13: Khảo sát TPB/động lực, phỏng vấn | F13: Chưa có dữ liệu khảo sát | H13: Trung bình | I13: Chưa đánh giá | J13: Khảo sát giảng viên/chuyên gia | K13: Đo thái độ, chuẩn chủ quan, perceived control, incentive fairness.

Sheet 07_CODEBOOK
A1: Dataset | B1: Biến | C1: Nhãn/ý nghĩa | D1: Kiểu | E1: Mã hóa/giá trị hợp lệ | F1: Bắt buộc? | G1: Nguồn dự kiến | H1: Ghi chú coding
A2: PROJECT | B2: Project_ID | C2: Mã duy nhất đề tài | D2: Text | E2: PYYYY-XX | F2: Có | G2: Hồ sơ đề tài | H2: Không đổi sau khi gán
A3: PROJECT | B3: Năm | C3: Năm nghiệm thu/ghi nhận | D3: Integer | E3: 2021–2025 | F3: Có | G3: Hồ sơ đề tài | H3: Ưu tiên năm nghiệm thu
A4: PROJECT | B4: Mã đề tài | C4: Mã quản lý nội bộ | D4: Text | E4: Theo quyết định | F4: Có | G4: Hồ sơ đề tài
A5: PROJECT | B5: Tên đề tài | C5: Tên đầy đủ | D5: Text | E5: Nguyên văn | F5: Có | G5: Hồ sơ đề tài | H5: Không tự chuẩn hóa làm mất nghĩa
A6: PROJECT | B6: Cấp đề tài | C6: Cấp quản lý | D6: Category | E6: Cơ sở/Quốc gia/Bộ/Tỉnh/Khác | F6: Có | G6: Hồ sơ
A7: PROJECT | B7: Chủ nhiệm | C7: Chủ nhiệm đề tài | D7: Text | F7: Có | G7: Hồ sơ
A8: PROJECT | B8: Đơn vị chủ trì | C8: Khoa/viện/phòng | D8: Category | E8: Chuẩn hóa tên đơn vị | F8: Có | G8: Hồ sơ | H8: Giữ thêm tên gốc nếu đổi tổ chức
A9: PROJECT | B9: Nhóm ngành chuẩn hóa | C9: Nhóm chuyên môn | D9: Category | E9: Dược/Kỹ thuật/Kinh tế/CNTT/NN-DL/... | F9: Không | G9: Suy từ đơn vị+nội dung | H9: Có bảng mapping
A10: PROJECT | B10: Strategic_Cluster | C10: Trụ cột chiến lược 2030 | D10: Category | E10: Smart Mobility/Digital Services/Global Communication/Wellness & Care/Khác | F10: Không | G10: Khung chiến lược
A11: PROJECT | B11: Ngày nghiệm thu | C11: Ngày nghiệm thu | D11: Date | E11: dd/mm/yyyy | F11: Không | G11: QĐ/biên bản
A12: PROJECT | B12: Xếp loại | C12: Kết quả nghiệm thu | D12: Category | E12: Đạt/Tốt/Xuất sắc/Khác | F12: Không | G12: Hồ sơ
A13: PROJECT | B13: Kinh phí_VND | C13: Kinh phí thực hiện | D13: Number | E13: VND | F13: Không | G13: Hồ sơ | H13: Tách phần quy đổi giờ nếu cần
A14: PROJECT | B14: Số thành viên | C14: Quy mô nhóm | D14: Integer | E14: >=1 | F14: Không | G14: Hồ sơ | H14: Tính chủ nhiệm + thành viên
A15: PROJECT | B15: Có DN tham gia? | C15: Có doanh nghiệp trong nhóm/hợp tác | D15: Category | E15: Có/Không/Chưa xác minh | F15: Không | G15: Hồ sơ/hợp đồng | H15: Không suy từ tên đề tài
A16: PROJECT | B16: Có SV tham gia? | C16: Có người học tham gia | D16: Category | E16: Có/Không/Chưa xác minh | F16: Không | G16: Hồ sơ
A17: PROJECT | B17: Số đầu ra | C17: Tổng output liên kết | D17: Formula | E17: COUNTIF OUTPUT | F17: Tự động | G17: Dataset
A18: OUTPUT | B18: Output_ID | C18: Mã đầu ra | D18: Text | E18: OYYYY-Project-Seq | F18: Có | G18: Dataset
A19: OUTPUT | B19: Project_ID | C19: Khóa liên kết đề tài | D19: Text | E19: Phải tồn tại ở PROJECT | F19: Có | G19: Dataset
A20: OUTPUT | B20: Tên đầu ra | C20: Tên sản phẩm/đầu ra | D20: Text | E20: Nguyên văn tối đa | F20: Có | G20: Sản phẩm nghiệm thu
A21: OUTPUT | B21: Loại đầu ra | C21: Loại vật mang kết quả | D21: Category | E21: Báo cáo/Bài báo/Sách-GT/CSDL/Phần mềm/Quy trình/Sản phẩm/Mô hình/Thiết kế/Nhãn hiệu/Khác | F21: Có | G21: Coding
A22: OUTPUT | B22: Số lượng | C22: Số lượng đầu ra | D22: Number | E22: >=0 | F22: Không | G22: Hồ sơ
A23: OUTPUT | B23: Đã công bố? | C23: Trạng thái công bố | D23: Category | E23: Có/Có nội bộ/Chưa/Chưa xác minh | F23: Không | G23: Hồ sơ
A24: OUTPUT | B24: Dấu hiệu TSTT? | C24: Có khả năng là TSTT | D24: Category | E24: Có/Không/Chưa xác minh | F24: Có | G24: Coding | H24: Không đồng nghĩa đủ điều kiện bảo hộ độc quyền
A25: OUTPUT | B25: Nhóm TSTT sơ bộ | C25: Phân nhóm sơ bộ | D25: Category | E25: Học thuật/Công nghệ/Số/Thương hiệu/Khác | F25: Không | G25: Coding
A26: OUTPUT | B26: Khả năng tạo giá trị | C26: Dạng giá trị tiềm năng | D26: Multi-category | E26: Khoa học/Đào tạo/Công nghệ/Kinh tế/Chiến lược/Xã hội | F26: Không | G26: Coding
A27: OUTPUT | B27: Bằng chứng nguồn | C27: Nguồn chứng minh | D27: Text | E27: Tên file + trang/dòng | F27: Có | G27: File nội bộ
A28: OUTPUT | B28: Mức tin cậy | C28: Độ chắc chắn coding | D28: Category | E28: Cao/Trung bình/Thấp | F28: Có | G28: Coder
A29: IP_ASSET | B29: IP_ID | C29: Mã TSTT/cụm TSTT | D29: Text | E29: IPYYYY-XX-A | F29: Có | G29: Dataset
A30: IP_ASSET | B30: Tên TSTT/cụm TSTT | C30: Đối tượng quản trị | D30: Text | F30: Có | G30: Output/hồ sơ
A31: IP_ASSET | B31: Nhóm TSTT | C31: Nhóm bản chất | D31: Category | E31: Học thuật/Công nghệ/Số/Thương hiệu/Dữ liệu/Khác | F31: Có | G31: Coding
A32: IP_ASSET | B32: Hình thức quyền dự kiến | C32: Quyền có thể áp dụng | D32: Category | E32: QTG/Sáng chế/GPHI/KDCN/Nhãn hiệu/BMKD/CSDL/Khác/Chưa xác minh | F32: Không | G32: Sàng lọc IP | H32: Không tự kết luận nếu thiếu tra cứu
A33: IP_ASSET | B33: Chủ thể sáng tạo rõ? | C33: Xác định tác giả/người tạo | D33: Category | E33: Có/Không/Chưa xác minh | F33: Có | G33: Hồ sơ
A34: IP_ASSET | B34: Chủ sở hữu rõ? | C34: Có bằng chứng sở hữu cụ thể | D34: Category | E34: Có/Không/Chưa xác minh | F34: Có | G34: Hợp đồng/quy chế
A35: IP_ASSET | B35: Trường sở hữu/đồng sở hữu? | C35: Vị thế của Trường | D35: Category | E35: Có/Đồng sở hữu/Không/Chưa xác minh | F35: Không | G35: Hồ sơ
A36: IP_ASSET | B36: Nguồn lực trường? | C36: Có sử dụng nguồn lực Trường | D36: Category | E36: Có/Không/Một phần/Chưa xác minh | F36: Không | G36: Hồ sơ
A37: IP_ASSET | B37: Có đối tác ngoài trường? | C37: Có đối tác tạo lập/khai thác | D37: Category | E37: Có/Không/Chưa xác minh | F37: Không | G37: Hợp đồng
A38: IP_ASSET | B38: Đã được nhận diện chính thức? | C38: Có trong sổ/CSDL/phiếu disclosure | D38: Category | E38: Có/Không/Chưa xác minh | F38: Có | G38: Phòng KHCN
A39: IP_ASSET | B39: Đã sàng lọc khả năng bảo hộ? | C39: Có biên bản/ý kiến sàng lọc | D39: Category | E39: Có/Không/Chưa xác minh | F39: Có | G39: Phòng KHCN
A40: IP_ASSET | B40: Mức tiềm năng bảo hộ | C40: Điểm sơ bộ | D40: Integer | E40: 0–3 | F40: Không | G40: Hội đồng/chuyên gia | H40: Không chấm khi chưa có tiêu chí
A41: IP_ASSET | B41: Mức tiềm năng ứng dụng | C41: Điểm sơ bộ | D41: Integer | E41: 0–3 | F41: Không | G41: Hội đồng/chuyên gia
A42: IP_ASSET | B42: Rủi ro công bố trước bảo hộ | C42: Rủi ro novelty/confidentiality | D42: Category | E42: Thấp/Trung bình/Cao/Chưa xác minh | F42: Không | G42: Đối chiếu thời gian
A43: IP_ASSET | B43: Tình trạng IP | C43: Giai đoạn vòng đời | D43: Category | E43: Tiềm năng/Đang sàng lọc/Dự kiến đăng ký/Đã nộp/Đã cấp/Không tiếp tục | F43: Có | G43: Hồ sơ
A44: PROTECTION | B44: Protection_ID | C44: Mã hồ sơ bảo hộ | D44: Text | F44: Có | G44: Dataset
A45: PROTECTION | B45: IP_ID | C45: Khóa TSTT | D45: Text | F45: Có | G45: Dataset
A46: PROTECTION | B46: Loại quyền/hồ sơ | C46: Loại đơn/quyền | D46: Category | E46: QTG/Sáng chế/GPHI/KDCN/Nhãn hiệu/... | F46: Có | G46: Hồ sơ
A47: PROTECTION | B47: Ngày phát sinh kết quả | C47: Mốc hình thành tài sản | D47: Date | F47: Không | G47: Hồ sơ
A48: PROTECTION | B48: Ngày khai báo IP | C48: Ngày disclosure nội bộ | D48: Date | F48: Không | G48: Phiếu khai báo
A49: PROTECTION | B49: Ngày sàng lọc | C49: Ngày đánh giá IP | D49: Date | F49: Không | G49: Biên bản
A50: PROTECTION | B50: Ngày nộp đơn | C50: Ngày nộp chính thức | D50: Date | F50: Không | G50: Đơn
A51: PROTECTION | B51: Số đơn | C51: Mã đơn | D51: Text | F51: Không | G51: Đơn
A52: PROTECTION | B52: Chủ đơn | C52: Applicant | D52: Text | F52: Không | G52: Đơn
A53: PROTECTION | B53: Tình trạng | C53: Trạng thái hồ sơ | D53: Category | E53: Dự kiến/Đã nộp/Thẩm định/Được cấp/Từ chối/Rút bỏ/Hết hiệu lực | F53: Có | G53: Hồ sơ
A54: PROTECTION | B54: Ngày cấp | C54: Ngày cấp quyền | D54: Date | F54: Không | G54: Văn bằng
A55: PROTECTION | B55: Số văn bằng | C55: Mã văn bằng | D55: Text | F55: Không | G55: Văn bằng
A56: PROTECTION | B56: Chi phí bảo hộ_VND | C56: Chi phí đăng ký/duy trì | D56: Number | E56: VND | F56: Không | G56: Tài chính
A57: PROTECTION | B57: Time_to_IP_days | C57: Thời gian từ kết quả đến nộp đơn | D57: Formula | E57: Ngày nộp - ngày phát sinh | F57: Tự động | G57: Dataset
A58: UTIL_VALUE | B58: Util_ID | C58: Mã lần khai thác | D58: Text | F58: Có | G58: Dataset
A59: UTIL_VALUE | B59: IP_ID | C59: Khóa TSTT | D59: Text | F59: Có | G59: Dataset
A60: UTIL_VALUE | B60: Hình thức sử dụng | C60: Kiểu khai thác | D60: Category | E60: Giảng dạy/Nghiên cứu tiếp/Ứng dụng nội bộ/Thử nghiệm DN/Sử dụng ngoài trường/Chuyển giao/Thương mại hóa | F60: Có | G60: Bằng chứng
A61: UTIL_VALUE | B61: Mức sử dụng | C61: Mã cấp độ | D61: Integer | E61: 0 chưa dùng;1 giảng dạy;2 nghiên cứu tiếp;3 nội bộ;4 chuẩn bị/thử nghiệm;5 ngoài trường;6 chuyển giao;7 thương mại hóa | F61: Có | G61: Coding
A62: UTIL_VALUE | B62: Đơn vị sử dụng | C62: Bên sử dụng | D62: Text | F62: Không | G62: Biên bản/hợp đồng
A63: UTIL_VALUE | B63: Đối tác | C63: Tổ chức ngoài trường | D63: Text | F63: Không | G63: Hợp đồng
A64: UTIL_VALUE | B64: Doanh thu_VND | C64: Doanh thu phát sinh | D64: Number | E64: VND | F64: Không | G64: Tài chính
A65: UTIL_VALUE | B65: Tiết kiệm chi phí_VND | C65: Giá trị tránh chi phí | D65: Number | E65: VND | F65: Không | G65: Tài chính
A66: UTIL_VALUE | B66: Số người dùng | C66: Quy mô thụ hưởng | D66: Number | E66: >=0 | F66: Không | G66: Đơn vị sử dụng
A67: UTIL_VALUE | B67: Giá trị khoa học | C67: Điểm 0–3 | D67: Integer | E67: 0–3 | F67: Không | G67: Chuyên gia
A68: UTIL_VALUE | B68: Giá trị đào tạo | C68: Điểm 0–3 | D68: Integer | E68: 0–3 | F68: Không | G68: Chuyên gia
A69: UTIL_VALUE | B69: Giá trị công nghệ | C69: Điểm 0–3 | D69: Integer | E69: 0–3 | F69: Không | G69: Chuyên gia
A70: UTIL_VALUE | B70: Giá trị kinh tế | C70: Điểm 0–3 | D70: Integer | E70: 0–3 | F70: Không | G70: Chuyên gia
A71: UTIL_VALUE | B71: Giá trị chiến lược | C71: Điểm 0–3 | D71: Integer | E71: 0–3 | F71: Không | G71: Chuyên gia/ranking mapping
A72: UTIL_VALUE | B72: Tình trạng định giá | C72: Mức định giá | D72: Category | E72: Chưa/Ước tính sơ bộ/Thẩm định chuyên nghiệp | F72: Không | G72: Hồ sơ
A73: LEGAL_GAP | B73: Khâu quản trị | C73: Bước trong chu trình IP | D73: Category | E73: Nhận diện/Sở hữu/Bảo mật/Đăng ký/Khai thác/Phân chia lợi ích/Định giá/Theo dõi/... | F73: Có | G73: Khung nghiên cứu
A74: LEGAL_GAP | B74: Yêu cầu/quy định nội bộ | C74: Chuẩn phải đạt | D74: Text | F74: Có | G74: Quy chế
A75: LEGAL_GAP | B75: Bằng chứng thực tế cần thu | C75: Evidence checklist | D75: Text | F75: Có | G75: Thiết kế audit
A76: LEGAL_GAP | B76: Bằng chứng hiện có | C76: Evidence đã thu | D76: Text | F76: Không | G76: Dataset
A77: LEGAL_GAP | B77: Mức tuân thủ | C77: Điểm compliance | D77: Integer | E77: 0 không có;1 một phần;2 đầy đủ | F77: Không | G77: Đánh giá sau audit
A78: LEGAL_GAP | B78: Mức độ rủi ro | C78: Risk rating | D78: Category | E78: Thấp/Trung bình/Cao | F78: Không | G78: Nhóm nghiên cứu
A79: LEGAL_GAP | B79: Khoảng cách sơ bộ | C79: Gap finding | D79: Text | F79: Không | G79: Phân tích | H79: Không kết luận khi thiếu hồ sơ

Sheet 09_LOOKUPS
A1: Strategic Cluster | B1: Loại đầu ra | C1: Nhóm TSTT | D1: Trạng thái IP | E1: Mức sử dụng | F1: Mức tin cậy
A2: Smart Mobility | B2: Báo cáo nghiên cứu | C2: Học thuật | D2: Tiềm năng | E2: 0 | F2: Cao
A3: Digital Services | B3: Bài báo | C3: Công nghệ | D3: Đang sàng lọc | E3: 1 | F3: Trung bình
A4: Global Communication | B4: Sách/Giáo trình/Học liệu | C4: Số | D4: Dự kiến đăng ký | E4: 2 | F4: Thấp
A5: Wellness & Care | B5: CSDL | C5: Thương hiệu | D5: Đã nộp | E5: 3
A6: Khác/Chưa phân loại | B6: Phần mềm | C6: Dữ liệu | D6: Đã cấp | E6: 4
B7: Quy trình/công thức | C7: Khác | D7: Không tiếp tục | E7: 5
B8: Sản phẩm/prototype | E8: 6
B9: Mô hình/prototype | E9: 7
B10: Thiết kế/KDCN
B11: Nhãn hiệu
B12: Khác

Sheet 10_CROSSLINK_STATUS
A1: Crosslink_ID | B1: Output_ID | C1: Project_ID | D1: Năm | E1: Đầu ra ghi trong hồ sơ | F1: CSDL đích | G1: Match_Status | H1: Tiêu đề ghép được | I1: DOI/Link | J1: Mức tin cậy ghép | K1: Trạng thái bằng chứng gốc | L1: Nguồn | M1: Ghi chú
A2: XL-001 | B2: O-2021-27-02 | C2: P2021-27 | D2: 2021 | E2: Bài báo đăng tạp chí quốc tế | F2: Bài báo quốc tế | G2: Chưa đối chiếu | K2: Hồ sơ ghi nhận | L2: Tổng hợp đề tài KHCN cấp cơ sở của GV 2021-2025.pdf, tr.1 | M2: Không khẳng định đầu ra đã công bố cho đến khi ghép được tiêu đề/tác giả/năm hoặc DOI/link.
A3: XL-002 | B3: O-2021-27-03 | C3: P2021-27 | D3: 2021 | E3: Bài báo đăng tạp chí trong nước | F3: Bài báo trong nước/khác | G3: Chưa đối chiếu | K3: Hồ sơ ghi nhận | L3: Tổng hợp đề tài KHCN cấp cơ sở của GV 2021-2025.pdf, tr.1 | M3: Không khẳng định đầu ra đã công bố cho đến khi ghép được tiêu đề/tác giả/năm hoặc DOI/link.
A4: XL-003 | B4: O-2021-28-02 | C4: P2021-28 | D4: 2021 | E4: Bài báo đăng tạp chí quốc tế | F4: Bài báo quốc tế | G4: Chưa đối chiếu | K4: Hồ sơ ghi nhận | L4: Tổng hợp đề tài KHCN cấp cơ sở của GV 2021-2025.pdf, tr.2 | M4: Không khẳng định đầu ra đã công bố cho đến khi ghép được tiêu đề/tác giả/năm hoặc DOI/link.
A5: XL-004 | B5: O-2021-28-03 | C5: P2021-28 | D5: 2021 | E5: Bài báo đăng tạp chí trong nước | F5: Bài báo trong nước/khác | G5: Chưa đối chiếu | K5: Hồ sơ ghi nhận | L5: Tổng hợp đề tài KHCN cấp cơ sở của GV 2021-2025.pdf, tr.2 | M5: Không khẳng định đầu ra đã công bố cho đến khi ghép được tiêu đề/tác giả/năm hoặc DOI/link.
A6: XL-005 | B6: O-2021-37-02 | C6: P2021-37 | D6: 2021 | E6: Bài báo đăng tạp chí trong nước | F6: Bài báo trong nước/khác | G6: Chưa đối chiếu | K6: Hồ sơ ghi nhận | L6: Tổng hợp đề tài KHCN cấp cơ sở của GV 2021-2025.pdf, tr.2 | M6: Không khẳng định đầu ra đã công bố cho đến khi ghép được tiêu đề/tác giả/năm hoặc DOI/link.
A7: XL-006 | B7: O-2022-51-02 | C7: P2022-51 | D7: 2022 | E7: Bài báo đăng tạp chí có ISSN | F7: Bài báo trong nước/khác | G7: Chưa đối chiếu | K7: Hồ sơ ghi nhận | L7: Tổng hợp đề tài KHCN cấp cơ sở của GV 2021-2025.pdf, tr.4 | M7: Không khẳng định đầu ra đã công bố cho đến khi ghép được tiêu đề/tác giả/năm hoặc DOI/link.
A8: XL-007 | B8: O-2023-01-01 | C8: P2023-01 | D8: 2023 | E8: Bài báo đăng trên tạp chí trong nước có chỉ số ISSN | F8: Bài báo trong nước/khác | G8: Chưa đối chiếu | K8: Hồ sơ ghi nhận | L8: Tổng hợp đề tài KHCN cấp cơ sở của GV 2021-2025.pdf, tr.4 | M8: Không khẳng định đầu ra đã công bố cho đến khi ghép được tiêu đề/tác giả/năm hoặc DOI/link.
A9: XL-008 | B9: O-2023-02-01 | C9: P2023-02 | D9: 2023 | E9: Bài báo đăng Kỷ yếu Hội thảo quốc tế có chỉ số ISBN | F9: Hội nghị/Hội thảo | G9: Chưa đối chiếu | K9: Hồ sơ ghi nhận | L9: Tổng hợp đề tài KHCN cấp cơ sở của GV 2021-2025.pdf, tr.4 | M9: Không khẳng định đầu ra đã công bố cho đến khi ghép được tiêu đề/tác giả/năm hoặc DOI/link.
A10: XL-009 | B10: O-2023-03-01 | C10: P2023-03 | D10: 2023 | E10: Bài báo đăng trên tạp chí trong nước có chỉ số ISSN | F10: Bài báo trong nước/khác | G10: Chưa đối chiếu | K10: Hồ sơ ghi nhưng chú thích '(ko có bài báo)' | L10: Tổng hợp đề tài KHCN cấp cơ sở của GV 2021-2025.pdf, tr.5 | M10: Không khẳng định đầu ra đã công bố cho đến khi ghép được tiêu đề/tác giả/năm hoặc DOI/link.
A11: XL-010 | B11: O-2023-04-01 | C11: P2023-04 | D11: 2023 | E11: Bài báo đăng trên tạp chí trong nước có chỉ số ISSN | F11: Bài báo trong nước/khác | G11: Chưa đối chiếu | K11: Hồ sơ ghi nhưng chú thích '(ko có bài báo)' | L11: Tổng hợp đề tài KHCN cấp cơ sở của GV 2021-2025.pdf, tr.5 | M11: Không khẳng định đầu ra đã công bố cho đến khi ghép được tiêu đề/tác giả/năm hoặc DOI/link.
A12: XL-011 | B12: O-2023-05-01 | C12: P2023-05 | D12: 2023 | E12: Bài báo đăng trên tạp chí trong nước có chỉ số ISSN | F12: Bài báo trong nước/khác | G12: Chưa đối chiếu | K12: Hồ sơ ghi nhận | L12: Tổng hợp đề tài KHCN cấp cơ sở của GV 2021-2025.pdf, tr.6 | M12: Không khẳng định đầu ra đã công bố cho đến khi ghép được tiêu đề/tác giả/năm hoặc DOI/link.
A13: XL-012 | B13: O-2023-07-01 | C13: P2023-07 | D13: 2023 | E13: Bài báo đăng trên tạp chí trong nước có chỉ số ISSN | F13: Bài báo trong nước/khác | G13: Chưa đối chiếu | K13: Hồ sơ ghi nhưng chú thích '(ko có bài báo)' | L13: Tổng hợp đề tài KHCN cấp cơ sở của GV 2021-2025.pdf, tr.6 | M13: Không khẳng định đầu ra đã công bố cho đến khi ghép được tiêu đề/tác giả/năm hoặc DOI/link.
... A31: XL-030 | B31: O-2025-09-02 | C31: P2025-09 | D31: 2025 | E31: Tạp chí có chỉ số ISSN/kỷ yếu hội thảo có chỉ số ISBN - Giai đoạn 1 | F31: Hội nghị/Hội thảo | G31: Chưa đối chiếu | K31: Hồ sơ ghi nhận | L31: Tổng hợp đề tài KHCN cấp cơ sở của GV 2021-2025.pdf, mục NĂM 2025 | M31: Không khẳng định đầu ra đã công bố cho đến khi ghép được tiêu đề/tác giả/năm hoặc DOI/link.

Sheet 11_DATA_REQUEST
A1: Request_ID | B1: Dữ liệu/hồ sơ cần xin | C1: Giai đoạn | D1: Đơn vị dự kiến lưu giữ | E1: Trường dữ liệu tối thiểu | F1: Phục vụ chỉ số/phân tích | G1: Ưu tiên | H1: Trạng thái | I1: Ghi chú
A2: R01 | B2: Danh mục toàn bộ đơn đăng ký và văn bằng SHTT của Trường giai đoạn 2021–2025 | C2: Bảo hộ | D2: Phòng KHCN | E2: Tên TSTT; loại quyền; số đơn; ngày nộp; chủ đơn; trạng thái; số văn bằng; ngày cấp | F2: IP funnel; protection rate; time-to-IP | G2: Rất cao | H2: Đã có danh sách tổng hợp | I2: Người dùng đã cung cấp danh sách 16 đối tượng trong nguồn tổng hợp; 12 đối tượng có ĐHTĐ là chủ sở hữu/đồng sở hữu, trong đó 11 thuộc 2021-2025. Vẫn thiếu số đơn/văn bằng đối với 2 sáng chế và số đơn cụ thể của Double2n.
A3: R02 | B3: Phiếu khai báo/biên bản nhận diện TSTT hoặc sổ/CSDL TSTT | C3: Nhận diện | D3: Phòng KHCN | E3: Tên tài sản; ngày khai báo; tác giả; đơn vị; nguồn kinh phí; chủ sở hữu dự kiến | F3: Disclosure rate; identification gap | G3: Rất cao | H3: Không có theo xác nhận hiện tại | I3: Theo người dùng, không có phiếu khai báo/biên bản nhận diện TSTT hoặc sổ/CSDL tương đương. Đây là một phát hiện thực chứng về hồ sơ quản trị; không tự động đồng nghĩa hoạt động nhận diện chưa từng diễn ra.
A4: R03 | B4: Biên bản/ý kiến sàng lọc khả năng bảo hộ và tra cứu tính mới | C4: Sàng lọc | D4: Phòng KHCN/đơn vị chuyên môn | E4: Ngày sàng lọc; kết luận; loại quyền khuyến nghị; lý do tiếp tục/không tiếp tục | F4: Screening rate; protection potential | G4: Rất cao | H4: Không có theo xác nhận hiện tại | I4: Theo người dùng, không có hồ sơ sàng lọc/tra cứu khả năng bảo hộ. Vì vậy không thể tính Screening Rate theo hồ sơ; có thể đánh giá 'không có bằng chứng tài liệu hóa quy trình' trong giai đoạn nghiên cứu.
A5: R04 | B5: Thuyết minh, hợp đồng và biên bản nghiệm thu đầy đủ của các đề tài có đầu ra ứng dụng | C5: Tạo lập | D5: Phòng KHCN | E5: Nguồn lực; sản phẩm đăng ký; sản phẩm đạt được; tác giả; điều khoản SHTT; kiến nghị chuyển giao | F5: Ownership audit; legal-practice gap | G5: Rất cao | H5: Chưa xin | I5: Lấy trước 10–15 case ưu tiên.
A6: R05 | B6: Hợp đồng/thỏa thuận hợp tác Nhà trường–Doanh nghiệp có điều khoản SHTT | C6: Đồng sáng tạo | D6: Phòng KHCN/Pháp chế/Đơn vị | E6: Background IP; foreground IP; quyền nộp đơn; chia sẻ lợi ích; bảo mật | F6: University-industry IP governance | G6: Cao | H6: Chưa xin | I6: Đặc biệt case tinh dầu vỏ bưởi.
A7: R06 | B7: Hợp đồng chuyển giao, cấp phép, bàn giao sản phẩm hoặc biên bản thương mại hóa | C7: Khai thác | D7: Phòng KHCN/Bộ phận Khởi nghiệp | E7: TSTT gốc; đối tác; hình thức giao dịch; thời hạn; phạm vi; giá trị | F7: IP-to-Value; commercialization rate | G7: Rất cao | H7: Không có theo xác nhận hiện tại | I7: Theo người dùng, không có hợp đồng chuyển giao/cấp phép/biên bản thương mại hóa trong bộ hồ sơ hiện có. Cần phân biệt: 'không có hồ sơ' với 'không có hoạt động'. Các dòng nghiệm thu ghi chuyển giao/ứng dụng chỉ được coi là dấu hiệu, chưa phải giao dịch thương mại đã xác nhận.
A8: R07 | B8: Dữ liệu doanh thu/thu nhập từ chuyển giao, cấp phép, bán sản phẩm dựa trên TSTT | C8: Giá trị | D8: Phòng Tài chính-Kế toán | E8: Doanh thu; năm; TSTT; hợp đồng; chi phí liên quan | F8: Economic value; ROI | G8: Rất cao | H8: Chưa xin | I8: Có thể tổng hợp theo mã hóa nếu dữ liệu nhạy cảm.
A9: R08 | B9: Chi phí đăng ký, gia hạn, duy trì và tư vấn SHTT | C9: Bảo hộ/giá trị | D9: Phòng Tài chính-Kế toán/Phòng KHCN | E9: Loại chi phí; TSTT; năm; số tiền | F9: Cost of protection; portfolio efficiency | G9: Cao | H9: Chưa xin
A10: R09 | B10: Chứng từ phân chia lợi ích, nhuận bút, thù lao liên quan khai thác TSTT | C10: Lợi ích | D10: Phòng Tài chính-Kế toán | E10: TSTT; người nhận; căn cứ; số tiền/tỷ lệ; thời điểm | F10: Incentive effectiveness; compliance gap | G10: Cao | H10: Chưa xin
A11: R10 | B11: Minh chứng sử dụng sản phẩm nghiên cứu trong giảng dạy/phòng thực hành/quản trị | C11: Ứng dụng nội bộ | D11: Khoa/Viện/Phòng Đào tạo | E11: Tên sản phẩm; học phần/đơn vị; số lớp/lượt người dùng; thời điểm; quyết định/biên bản | F11: Utilization rate; training value | G11: Rất cao | H11: Chưa xin | I11: Đặc biệt panel ô tô, bộ mẫu dược liệu, tiêu bản, quy trình thực hành.
A12: R11 | B12: Danh sách bài báo thực tế kèm DOI/link, tác giả, năm; danh mục hội thảo/kỷ yếu | C12: Công bố | D12: Phòng KHCN/Tạp chí | E12: Tiêu đề; tác giả; năm; DOI/link; loại công bố; liên kết đề tài nếu có | F12: Cross-link outputs; tránh đếm trùng | G12: Cao | H12: Một phần đã có | I12: Cần ghép 1:1 với các dòng 'bài báo' trong hồ sơ nghiệm thu.
A13: R12 | B13: Danh mục giáo trình, tài liệu giảng dạy và hồ sơ quyền tác giả/chủ sở hữu | C13: Học liệu | D13: Phòng KHCN/Thư viện/Đào tạo | E13: Tên; tác giả; đơn vị; năm; quyết định; phạm vi sử dụng; đăng ký QTG nếu có | F13: Academic IP portfolio; ownership audit | G13: Cao | H13: Một phần đã có | I13: Dữ liệu thống kê 2021–2025 đã có, còn thiếu liên kết quyền và mức sử dụng.
A14: R13 | B14: Số giảng viên/nghiên cứu viên theo đơn vị và năm | C14: Chuẩn hóa | D14: Phòng TCCB | E14: Đơn vị; năm; số GV/NV nghiên cứu; FTE nếu có | F14: IP/output per capita by faculty | G14: Trung bình | H14: Chưa xin | I14: Dùng chuẩn hóa so sánh giữa khoa, tránh thiên lệch quy mô.
A15: R14 | B15: Dữ liệu sinh viên, số học phần và quy mô đào tạo theo nhóm ngành | C15: Chuẩn hóa/giá trị | D15: Phòng Đào tạo | E15: Ngành; năm; số SV; học phần; quy mô sử dụng học liệu | F15: Training reach; value per user | G15: Trung bình | H15: Chưa xin
A16: R15 | B16: Bằng chứng sử dụng TSTT trong truyền thông, tuyển sinh, kiểm định và xếp hạng | C16: Giá trị chiến lược | D16: Phòng TT/ĐBCL/HTQT | E16: Tài sản; chỉ số/ranking/tiêu chí; minh chứng; năm | F16: Strategic/ranking value mapping | G16: Cao | H16: Chưa xin | I16: Không quy tiền trực tiếp nếu chưa có phương pháp định giá phù hợp.

Sheet 08_KPI_ALL
A1: MISSION 1.2 – IP PORTFOLIO INVENTORY 2021–2025 (DỮ LIỆU HỒ SƠ)
A3: Chỉ số | B3: Ý nghĩa | C3: Giá trị | E3: Mức ưu tiên IP | F3: Số đầu ra
A4: Tổng số đề tài cấp cơ sở | B4: Số dòng Project_ID đã kiểm kê | C4: =COUNTA(01_PROJECT_ALL!A2:A1000) -> 38 | E4: Cao | F4: =COUNTIF(02_OUTPUT_ALL!$K$2:$K$2000,E4) -> 15
A5: Tổng số dòng đầu ra | B5: Đầu ra bóc tách từ sản phẩm nghiệm thu | C5: =COUNTA(02_OUTPUT_ALL!A2:A2000) -> 90 | E5: Trung bình | F5: =COUNTIF(02_OUTPUT_ALL!$K$2:$K$2000,E5) -> 11
A6: Đầu ra ưu tiên IP (TB + Cao) | B6: Cần quản trị/sàng lọc sâu hơn | C6: =COUNTIF(02_OUTPUT_ALL!K2:K2000,"Trung bình")+COUNTIF(02_OUTPUT_ALL!K2:K2000,"Cao") -> 26 | E6: Thấp | F6: =COUNTIF(02_OUTPUT_ALL!$K$2:$K$2000,E6) -> 64
A7: Đầu ra ưu tiên IP mức Cao | B7: Prototype/quy trình/công thức/chuyển giao... | C7: =COUNTIF(02_OUTPUT_ALL!K2:K2000,"Cao") -> 15 | E7: Tổng | F7: =SUM(F4:F6) -> 90
A8: Đầu ra có dấu hiệu ứng dụng | B8: Hồ sơ ghi Có ở cột ứng dụng | C8: =COUNTIF(02_OUTPUT_ALL!L2:L2000,"Có") -> 25
A9: Đầu ra cần đối chiếu CSDL công bố | B9: Bài báo/kỷ yếu cần ghép tiêu đề/DOI | C9: =COUNTIF(02_OUTPUT_ALL!M2:M2000,"Cần đối chiếu") -> 30
A10: Bằng chứng công bố mâu thuẫn/chưa đủ | B10: Ví dụ hồ sơ ghi '(ko có bài báo)' | C10: =COUNTIF(02_OUTPUT_ALL!H2:H2000,"Hồ sơ ghi nhưng chú thích '(ko có bài báo)'") -> 3
A11: Đầu ra bảo hộ mới ở mức dự kiến | B11: GPHI/sáng chế ghi dự kiến/kế hoạch | C11: =COUNTIF(02_OUTPUT_ALL!H2:H2000,"Đã nghiệm thu; ghi 'công thức mới, dự kiến đăng ký GPHI'")+COUNTIF(02_OUTPUT_ALL!H2:H2000,"Đã nghiệm thu; ghi 'quy trình mới, dự kiến đăng ký GPHI'")+COUNTIF(02_OUTPUT_ALL!H2:H2000,"Kế hoạch giai đoạn 2; chưa có bằng chứng nộp/cấp") -> 3
A12: Số đề tài có đầu ra ứng dụng ghi trong hồ sơ | B12: Project column O = Có | C12: =COUNTIF(01_PROJECT_ALL!O2:O1000,"Có") -> 18
A13: Tỷ lệ đề tài có dấu hiệu ứng dụng | B13: Project có dấu hiệu ứng dụng / tổng project | C13: =IF(C4=0,"",C12/C4) -> 0.47368421
A16: Năm nhóm | B16: Số đề tài | C16: Số dòng đầu ra | E16: Strategic Cluster | F16: Số đề tài
A17: 2021 | B17: =COUNTIF(01_PROJECT_ALL!$B$2:$B$1000,A17) -> 6 | C17: =COUNTIF(02_OUTPUT_ALL!$C$2:$C$2000,A17) -> 11 | E17: Smart Mobility | F17: =COUNTIF(01_PROJECT_ALL!$I$2:$I$1000,E17) -> 1
A18: 2022 | B18: =COUNTIF(01_PROJECT_ALL!$B$2:$B$1000,A18) -> 10 | C18: =COUNTIF(02_OUTPUT_ALL!$C$2:$C$2000,A18) -> 14 | E18: Digital Services | F18: =COUNTIF(01_PROJECT_ALL!$I$2:$I$1000,E18) -> 4
A19: 2023 | B19: =COUNTIF(01_PROJECT_ALL!$B$2:$B$1000,A19) -> 7 | C19: =COUNTIF(02_OUTPUT_ALL!$C$2:$C$2000,A19) -> 21 | E19: Global Communication | F19: =COUNTIF(01_PROJECT_ALL!$I$2:$I$1000,E19) -> 10
A20: 2024 | B20: =COUNTIF(01_PROJECT_ALL!$B$2:$B$1000,A20) -> 8 | C20: =COUNTIF(02_OUTPUT_ALL!$C$2:$C$2000,A20) -> 27 | E20: Wellness & Care | F20: =COUNTIF(01_PROJECT_ALL!$I$2:$I$1000,E20) -> 10
A21: 2025 | B21: =COUNTIF(01_PROJECT_ALL!$B$2:$B$1000,A21) -> 7 | C21: =COUNTIF(02_OUTPUT_ALL!$C$2:$C$2000,A21) -> 17 | E21: Khác/Chưa phân loại | F21: =COUNTIF(01_PROJECT_ALL!$I$2:$I$1000,E21) -> 13
A22: Tổng | B22: =SUM(B17:B21) -> 38 | C22: =SUM(C17:C21) -> 90 | E22: Tổng | F22: =SUM(F17:F21) -> 38
A25: Lưu ý: các con số trên phản ánh dữ liệu hồ sơ đã bóc tách, không đồng nghĩa với số TSTT đã được pháp luật xác lập/bảo hộ. Hình thức quyền trong dataset là phân loại sơ bộ để sàng lọc, chưa phải kết luận pháp lý.
A28: MISSION 1.3 | B28: Liên kết đầu ra → công bố → bảo hộ | C28: Giá trị | E28: DANH MỤC SHTT NGUỒN ĐẦY ĐỦ | F28: Phạm vi | G28: Giá trị | I28: MISSION 2 | J28: Case-based IP governance audit | K28: Giá trị
A29: Công bố đã xác định/ghép mạnh | B29: Số liên kết ở 12_PUBLICATION_LINKS | C29: =COUNTA(12_PUBLICATION_LINKS!A2:A1000) -> 13 | E29: Tổng đối tượng trong danh sách nguồn | F29: Mọi chủ sở hữu/mọi năm | G29: =COUNTA(13B_PROTECTION_FULL!A2:A1000) -> 16 | I29: Số khâu trong ma trận pháp luật-thực tiễn | J29: 17_LEGAL_PRACTICE_MATRIX | K29: =COUNTA(17_LEGAL_PRACTICE_MATRIX!A2:A100) -> 12
A30: Đối tượng SHTT trong bảng văn bằng nội bộ | B30: Tổng copyright + nhãn hiệu + KDCN + sáng chế ghi trong ảnh | C30: =COUNTA(13_PROTECTION_INVENTORY!A2:A1000) -> 12 | E30: Trong giai đoạn 2021-2025 | F30: Mọi chủ sở hữu | G30: =COUNTIFS(13B_PROTECTION_FULL!E2:E1000,">=2021",13B_PROTECTION_FULL!E2:E1000,"<=2025") -> 14 | I30: Số câu hỏi phỏng vấn lõi | J30: 18_INTERVIEW_GUIDE | K30: =COUNTA(18_INTERVIEW_GUIDE!A4:A100) -> 15
A31: Đối tượng SHTT trong giai đoạn 2021-2025 | B31: Loại trừ sáng chế năm 2026 | C31: =COUNTIFS(13_PROTECTION_INVENTORY!E2:E1000,">=2021",13_PROTECTION_INVENTORY!E2:E1000,"<=2025") -> 11 | E31: ĐHTĐ là chủ sở hữu/đồng sở hữu | F31: Mọi năm | G31: =COUNTIF(13B_PROTECTION_FULL!J2:J1000,"Trực tiếp ĐHTĐ") -> 12 | I31: Số case process-tracing | J31: 19_CASE_TRACE | K31: =COUNTA(19_CASE_TRACE!A2:A100) -> 6
A32: Liên kết đề tài ↔ hồ sơ bảo hộ mức Cao/Rất cao | B32: Số dòng 14_PROJECT_PROTECTION_LINK | C32: =COUNTA(14_PROJECT_PROTECTION_LINK!A2:A1000) -> 2 | E32: ĐHTĐ trực tiếp trong 2021-2025 | F32: Portfolio chính của đề tài | G32: =COUNTIFS(13B_PROTECTION_FULL!J2:J1000,"Trực tiếp ĐHTĐ",13B_PROTECTION_FULL!E2:E1000,">=2021",13B_PROTECTION_FULL!E2:E1000,"<=2025") -> 11 | I32: Khảo sát định lượng | J32: Không thực hiện | K32: 0
A33: Đề tài có liên kết bảo hộ | B33: Distinct project trong bảng liên kết | C33: =COUNTIF(15_KNOWLEDGE_IP_CHAIN!H2:H39,">0") -> 2 | E33: ĐHTĐ trực tiếp có số đăng ký/văn bằng/ký hiệu trong 2021-2025 | F33: Loại trừ Double2n tiếp nhận đơn và sáng chế 2025 chưa có số | G33: =COUNTIFS(13B_PROTECTION_FULL!J2:J1000,"Trực tiếp ĐHTĐ",13B_PROTECTION_FULL!E2:E1000,">=2021",13B_PROTECTION_FULL!E2:E1000,"<=2025",13B_PROTECTION_FULL!I2:I1000,"Đã có số đăng ký")+COUNTIFS(13B_PROTECTION_FULL!J2:J1000,"Trực tiếp ĐHTĐ",13B_PROTECTION_FULL!E2:E1000,">=2021",13B_PROTECTION_FULL!E2:E1000,"<=2025",13B_PROTECTION_FULL!I2:I1000,"Đã có số văn bằng/ký hiệu")+COUNTIFS(13B_PROTECTION_FULL!J2:J1000,"Trực tiếp ĐHTĐ",13B_PROTECTION_FULL!E2:E1000,">=2021",13B_PROTECTION_FULL!E2:E1000,"<=2025",13B_PROTECTION_FULL!I2:I1000,"Đã có số/ký mã hiệu") -> 9 | I33: Văn bản QC TSTT 2024 | J33: Đã xác minh: QĐ 217/QĐ-ĐHTĐ ngày 21/11/2024, hiệu lực 21/11/2024 | K33: 1
A34: Đề tài có công bố đã ghép | B34: Distinct project hiện có ít nhất 1 link | C34: =COUNTIF(15_KNOWLEDGE_IP_CHAIN!G2:G39,">0") -> 12 | E34: ĐHTĐ trực tiếp ở trạng thái tiếp nhận đơn | F34: Double2n | G34: =COUNTIFS(13B_PROTECTION_FULL!J2:J1000,"Trực tiếp ĐHTĐ",13B_PROTECTION_FULL!I2:I1000,"Tiếp nhận đơn; chưa coi là đã được cấp") -> 1 | I34: Gap ưu tiên 1 | J34: Nhận diện/disclosure không có hồ sơ
A35: Đề tài có đầu ra IP mức Cao nhưng chưa nối bảo hộ | B35: Ứng viên cần sàng lọc/đối chiếu hồ sơ; chưa phải kết luận thiếu bảo hộ | C35: =COUNTIFS(15_KNOWLEDGE_IP_CHAIN!L2:L39,">0",15_KNOWLEDGE_IP_CHAIN!H2:H39,0) -> 7 | E35: ĐHTĐ trực tiếp có sáng chế chưa rõ số đơn/văn bằng | F35: 2025 và 2026 | G35: =COUNTIFS(13B_PROTECTION_FULL!J2:J1000,"Trực tiếp ĐHTĐ",13B_PROTECTION_FULL!B2:B1000,"Sáng chế",13B_PROTECTION_FULL!I2:I1000,"Có trong danh sách; chưa có số/ký mã hiệu trong nguồn") -> 2 | I35: Gap ưu tiên 2 | J35: Không có hồ sơ screening/tra cứu IP
A36: Ghi chú | B36: Không tính conversion rate chính thức trước khi nhận danh mục đơn/văn bằng đầy đủ và hồ sơ disclosure/sàng lọc. | E36: Nguyên tắc | F36: Không gộp UNIGO/cá nhân vào portfolio trực tiếp ĐHTĐ. | I36: Gap ưu tiên 3 | J36: Không có hồ sơ transfer/commercialization

Sheet 12_PUBLICATION_LINKS
A1: Link_ID | B1: Output_ID | C1: Project_ID | D1: Quan hệ | E1: Tiêu đề công bố xác định được | F1: Loại công bố | G1: Tạp chí/Hội thảo | H1: Tác giả | I1: Năm | J1: Số/Vol/ISBN | K1: DOI/Link | L1: Mức độ khớp | M1: Cơ sở khớp | N1: Nguồn dữ liệu
A2: PUB-001 | B2: O-2021-27-03 | C2: P2021-27 | D2: Đầu ra nghiệm thu | E2: Tìm hiểu thực trạng về động lực phát triển chuyên môn giáo viên tại Việt Nam | F2: Bài báo trong nước | G2: Tạp chí Giáo dục | H2: Phan Thị Thanh Thảo; Nguyễn Thị Vân Anh | I2: 2021 | J2: 59-64 | L2: Cao | M2: Chủ đề gần trùng với tên đề tài; chủ nhiệm và thành viên cùng xuất hiện trong bài. | N2: Thống kê bài báo đăng tạp chí khoa học trong nước 2021-2025.pdf
A3: PUB-002 | B3: O-2021-28-02 | C3: P2021-28 | D3: Đầu ra nghiệm thu | E3: International academic publishing in Vietnam: policy efficiency and room for development | F3: Bài báo quốc tế | G3: Science Editing | H3: Phan Thị Thanh Thảo; Hiep Hung Pham; Huong Linh Nguyen; Linh Chi Nguyen | I3: 2021 | J3: Sci Ed 2021; 8(2) | K3: https://escienceediting.org/journal/view.php?number=255 | L3: Cao | M3: Chủ đề công bố quốc tế tại Việt Nam; nhiều thành viên đề tài trùng tác giả. | N3: Thống kê bài báo đăng tạp chí khoa học quốc tế 2021-2025.pdf
A4: PUB-003 | B4: O-2021-28-03 | C4: P2021-28 | D4: Đầu ra nghiệm thu (1/2 bài trong nước đã xác định) | E4: Năng suất công bố của các cơ sở giáo dục đại học ở Việt Nam giai đoạn 2016-2020: Dữ liệu từ Scopus | F4: Bài báo trong nước | G4: Tạp chí Giáo dục | H4: Lương Đình Hải; Phan Thị Thanh Thảo; Đinh Đức Tài; Phạm Hùng Hiệp | I4: 2022 | J4: 01-06 | L4: Cao | M4: Chủ đề trực tiếp về năng suất công bố; nhóm tác giả trùng nhiều thành viên đề tài. | N4: Thống kê bài báo đăng tạp chí khoa học trong nước 2021-2025.pdf
A5: PUB-004 | B5: O-2021-37-02 | C5: P2021-37 | D5: Đầu ra nghiệm thu | E5: Rào cản của các doanh nghiệp vừa và nhỏ trong việc áp dụng thương mại điện tử tại Việt Nam | F5: Bài báo trong nước | G5: Tạp chí Nghiên cứu Tài chính Kế toán | H5: Đặng Thái Bình; Nguyễn Thị Hay | I5: 2021 | J5: 29-35 | L5: Rất cao | M5: Tiêu đề bài báo trùng tên đề tài; tác giả trùng chủ nhiệm và thành viên. | N5: Thống kê bài báo đăng tạp chí khoa học trong nước 2021-2025.pdf
A6: PUB-005 | B6: O-2023-02-01 | C6: P2023-02 | D6: Đầu ra nghiệm thu | E6: Nâng cao chất lượng đào tạo nguồn nhân lực du lịch áp dụng phương pháp tiếp cận CDIO | F6: Kỷ yếu hội thảo quốc tế | G6: Phát triển kinh tế du lịch gắn với yêu cầu chuyển đổi số: Cơ hội và thách thức đối với nhiệm vụ đào tạo nguồn nhân lực tại tỉnh Đắk Nông | H6: Nguyễn Thị Bích; Nguyễn Tuấn Ninh | I6: 2023 | J6: ISBN 978-604-79-4095-0 | L6: Rất cao | M6: Đúng phương pháp CDIO, đúng lĩnh vực du lịch và trùng toàn bộ nhóm tác giả đề tài. | N6: Thống kê báo cáo, tham luận Hội nghị, Hội thảo quốc tế 2021-2025.pdf
A7: PUB-006 | B7: O-2023-05-01 | C7: P2023-05 | D7: Đầu ra nghiệm thu | E7: Chính sách khuyến khích cho các công bố khoa học tại một số trường đại học ngoài công lập ở Việt Nam | F7: Bài báo trong nước | G7: Khoa học & Đào tạo - Trường ĐH Công nghệ Sài Gòn | H7: Nguyễn Thị Hảo; Hoàng Thị Thu Hà; Nguyễn Thị Phương Uyên | I7: 2023 | J7: Số 01/2023 | L7: Rất cao | M7: Tiêu đề công bố trùng tên đề tài; 3/4 thành viên đề tài là tác giả. | N7: Thống kê bài báo đăng tạp chí khoa học trong nước 2021-2025.pdf
A8: PUB-007 | B8: O-2023-08-01 | C8: P2023-08 | D8: Đầu ra nghiệm thu | E8: Hợp tác Nhà trường - Doanh nghiệp trong nghiên cứu khoa học và đào tạo sinh viên ngành Dược học: Nghiên cứu trường hợp tại Trường Đại học Thành Đô | F8: Bài báo trong nước | G8: Tạp chí Giáo dục | H8: Trần Thị Thu Trang; Phan Thị Thanh Thảo; Phạm Thị Thanh Huế | I8: 2024 | J8: Số 24(4) | L8: Cao | M8: Chủ đề hợp tác Nhà trường-Doanh nghiệp ngành Dược và tác giả trùng nhóm đề tài. | N8: Thống kê bài báo đăng tạp chí khoa học trong nước 2021-2025.pdf
A9: PUB-008 | B9: O-2024-06-01 | C9: P2024-06 | D9: Đầu ra nghiệm thu | E9: Nghiên cứu chế tạo xà bông từ tảo spirulina | F9: Bài báo trong nước | G9: Tạp chí NCKH&PT | H9: Đỗ Thị Huyền Thương; Vũ Quốc Mạnh; Lê Thị Hiền; Nguyễn Thị Huyền Trang; Đào Thị Mai Hương; Phạm Văn Đại; Nguyễn Ngọc Linh; Phạm Thị Bích Đào | I9: 2025 | J9: Volume 4, Issue 1 (March 2025) | K9: https://doi.org/10.58902/tcnckhpt.v4i1.215 | L9: Cao | M9: Chủ đề xà phòng từ tảo; chủ nhiệm và thành viên chủ chốt của đề tài có trong nhóm tác giả. | N9: Thống kê bài báo đăng tạp chí khoa học trong nước 2021-2025.pdf
A10: PUB-009 | B10: O-2024-10-01 | C10: P2024-10 | D10: Đầu ra nghiệm thu | E10: Triết lý nhân sinh trong truyện Lục Vân Tiên của Nguyễn Đình Chiểu | F10: Bài báo trong nước | G10: Tạp chí Giáo dục | H10: Trần Doãn Phú; Nguyễn Thị Hảo; Ngô Nhị Ngọc Linh | I10: 2024 | J10: Tháng 12/2024 | L10: Rất cao | M10: Chủ đề trùng trực tiếp với đề tài và cả 3 thành viên đề tài xuất hiện trong bài. | N10: Thống kê bài báo đăng tạp chí khoa học trong nước 2021-2025.pdf
A11: PUB-010 | B11: O-2024-12-01 | C11: P2024-12 | D11: Đầu ra nghiệm thu | E11: Thực trạng tích hợp giáo dục vì sự phát triển bền vững trong dạy học “Sinh thái học và môi trường” (Sinh học 12): Nghiên cứu tại một số trường trung học phổ thông ở Hà Nội và thành phố Hồ Chí Minh | F11: Bài báo trong nước | G11: Tạp chí NCKH&PT | H11: Hà Văn Dũng; Nguyễn Linh Chi; Đoàn Thị Phương Thục; Đỗ Thuỳ Linh; Bùi Thị Thanh Nhàn | I11: 2024 | J11: Volume 3, Issue 3 (September 2024) | K11: https://doi.org/10.58902/tcnckhpt.v3i3.164 | L11: Rất cao | M11: Tiêu đề và nhóm tác giả trùng gần như đầy đủ với đề tài. | N11: Thống kê bài báo đăng tạp chí khoa học trong nước 2021-2025.pdf
A12: PUB-011 | B12: O-2024-13-01 | C12: P2024-13 | D12: Đầu ra nghiệm thu | E12: An understanding of "universal history" in Francis Fukuyama's “The End of History and the Last Man” | F12: Bài báo quốc tế | G12: Universum: Social Sciences | H12: Ngô Nhị Ngọc Linh | I12: 2024 | J12: 4(107), 36-40 | K12: https://doi.org/10.32743/UniSoc.2024.107.4.17403 | L12: Rất cao | M12: Chủ đề trùng trực tiếp với đề tài và chủ nhiệm là tác giả. | N12: Thống kê bài báo đăng tạp chí khoa học quốc tế 2021-2025.pdf
A13: PUB-012 | B13: O-2024-14-01 | C13: P2024-14 | D13: Đầu ra nghiệm thu | E13: Một số nghiên cứu về năng lực dạy học tích hợp | F13: Bài báo trong nước | G13: Tạp chí NCKH&PT | H13: Hà Văn Dũng; Nguyễn Linh Chi; Đoàn Thị Phương Thục; Phạm Đình Văn; Nguyễn Thuỳ Dung | I13: 2025 | J13: Volume 4, Issue 1 (March 2025) | K13: https://doi.org/10.58902/tcnckhpt.v4i1.207 | L13: Rất cao | M13: Toàn bộ nhóm tác giả trùng nhóm đề tài; nội dung về năng lực dạy học tích hợp. | N13: Thống kê bài báo đăng tạp chí khoa học trong nước 2021-2025.pdf
A14: PUB-013 | B14: O-2025-02-02 | C14: P2025-02 | D14: Đầu ra nghiệm thu | E14: Phát triển năng lực đổi mới sáng tạo cho sinh viên | F14: Bài báo trong nước | G14: Tạp chí Quản lý nhà nước và lao động | H14: Nguyễn Thị Hay; Phạm Hoàng Giang; Bùi Đức Thịnh | I14: 2025 | J14: 15/12/2025 | K14: https://tcnnld.vn/news/detail/70804/Phat-trien-nang-luc-doi-moi-sang-tao-cho-sinh-vien | L14: Cao | M14: Chủ nhiệm đề tài là tác giả; chủ đề phát triển năng lực đổi mới sáng tạo cho sinh viên phù hợp trực tiếp. | N14: Thống kê bài báo đăng tạp chí khoa học trong nước 2021-2025.pdf

Sheet 13_PROTECTION_INVENTORY
A1: Protection_ID | B1: Loại hình | C1: Tên/đối tượng | D1: Số/Ký mã hiệu | E1: Năm | F1: Cơ quan | G1: Chủ sở hữu | H1: Trạng thái suy ra từ nguồn | I1: Project_ID liên quan sơ bộ | J1: Mức độ liên kết | K1: Nguồn | L1: Ghi chú
A2: PIP-001 | B2: Bản quyền tác giả | C2: Bộ Logo Trường Đại học Thành Đô | D2: 6534/2021/QTG | E2: 2021 | F2: Cục Bản quyền tác giả, Bộ Văn hóa, Thể thao và Du lịch | G2: ĐHTĐ | H2: Đã có số đăng ký | K2: Ảnh thống kê văn bằng SHTT do người dùng cung cấp | L2: TSTT thương hiệu/hình ảnh tổ chức.
A3: PIP-002 | B3: Bản quyền tác giả | C3: Bộ Logo Hệ sinh thái giáo dục Trường Đại học Thành Đô | D3: 5790/2023/QTG | E3: 2023 | F3: Cục Bản quyền tác giả, Bộ Văn hóa, Thể thao và Du lịch | G3: ĐHTĐ | H3: Đã có số đăng ký | K3: Ảnh thống kê văn bằng SHTT do người dùng cung cấp
A4: PIP-003 | B4: Nhãn hiệu | C4: Thanh do University | D4: 468353 | E4: 2023 | F4: Cục Sở hữu trí tuệ, Bộ KH&CN | G4: ĐHTĐ | H4: Đã có số văn bằng | K4: Ảnh thống kê văn bằng SHTT do người dùng cung cấp
A5: PIP-004 | B5: Nhãn hiệu | C5: Thado Edupark | D5: 545780 | E5: 2025 | F5: Cục Sở hữu trí tuệ, Bộ KH&CN | G5: ĐHTĐ | H5: Đã có số văn bằng | K5: Ảnh thống kê văn bằng SHTT do người dùng cung cấp
A6: PIP-005 | B6: Nhãn hiệu | C6: Double2n | E6: 2023 | F6: Cục Sở hữu trí tuệ, Bộ KH&CN | G6: ĐHTĐ; CTY Thanh Huế | H6: Tiếp nhận đơn | K6: Ảnh thống kê văn bằng SHTT do người dùng cung cấp | L6: Nguồn ghi rõ 'Tiếp nhận đơn', chưa coi là đã được cấp.
A7: PIP-006 | B7: Kiểu dáng công nghiệp | C7: Dung dịch vệ sinh phụ nữ | D7: 3-0039693-000 | E7: 2024 | F7: Cục Sở hữu trí tuệ, Bộ KH&CN | G7: ĐHTĐ; CTY Thanh Huế | H7: Đã có số/ký mã hiệu | K7: Ảnh thống kê văn bằng SHTT do người dùng cung cấp
A8: PIP-007 | B8: Kiểu dáng công nghiệp | C8: Tinh dầu vỏ bưởi đào | D8: 3-0039694-000 | E8: 2024 | F8: Cục Sở hữu trí tuệ, Bộ KH&CN | G8: ĐHTĐ; CTY Thanh Huế | H8: Đã có số/ký mã hiệu | I8: P2023-08 | J8: Cao | K8: Ảnh thống kê văn bằng SHTT do người dùng cung cấp | L8: Tên sản phẩm gần trùng đầu ra tinh dầu Citrus grandis; đồng chủ sở hữu có CTY Thanh Huế phù hợp bối cảnh hợp tác.
A9: PIP-008 | B9: Kiểu dáng công nghiệp | C9: Xịt miệng - họng thảo dược | D9: 3-0039902-000 | E9: 2024 | F9: Cục Sở hữu trí tuệ, Bộ KH&CN | G9: ĐHTĐ; CTY Thanh Huế | H9: Đã có số/ký mã hiệu | K9: Ảnh thống kê văn bằng SHTT do người dùng cung cấp
A10: PIP-009 | B10: Kiểu dáng công nghiệp | C10: Dầu gội nha đam - bưởi đào | D10: 3-0039695-000 | E10: 2024 | F10: Cục Sở hữu trí tuệ, Bộ KH&CN | G10: ĐHTĐ; CTY Thanh Huế | H10: Đã có số/ký mã hiệu | K10: Ảnh thống kê văn bằng SHTT do người dùng cung cấp
A11: PIP-010 | B11: Kiểu dáng công nghiệp | C11: Kem ủ xả tóc - Chiết xuất từ Bưởi - Bơ - Dừa | D11: 3-0039696-000 | E11: 2024 | F11: Cục Sở hữu trí tuệ, Bộ KH&CN | G11: ĐHTĐ; CTY Thanh Huế | H11: Đã có số/ký mã hiệu | K11: Ảnh thống kê văn bằng SHTT do người dùng cung cấp
A12: PIP-011 | B12: Sáng chế | C12: Các hợp chất furofuran lignan glucoside và phương pháp chiết các hợp chất này từ lá của cây quế hoa (Osmanthus fragrans) | E12: 2025 | F12: Cục Sở hữu trí tuệ, Bộ KH&CN | G12: ĐHTĐ | H12: Có trong bảng thống kê nội bộ; số văn bằng/đơn chưa thể hiện | I12: P2025-09 | J12: Rất cao | K12: Ảnh thống kê văn bằng SHTT do người dùng cung cấp | L12: Tên đối tượng trùng trực tiếp cây quế hoa và hướng chiết xuất của đề tài; cần xin số đơn/văn bằng để xác định trạng thái pháp lý.
A13: PIP-012 | B13: Sáng chế | C13: Phương pháp chiết tách và phân lập hợp chất Isoembigenin từ cây Piper aduncum L. | E13: 2026 | F13: Cục Sở hữu trí tuệ, Bộ KH&CN | G13: ĐHTĐ | H13: Có trong bảng thống kê nội bộ; số văn bằng/đơn chưa thể hiện | K13: Ảnh thống kê văn bằng SHTT do người dùng cung cấp | L13: Ngoài giai đoạn 2021-2025 nhưng giữ để theo dõi pipeline kế tiếp.

Sheet 14_PROJECT_PROTECTION_LINK
A1: Link_ID | B1: Project_ID | C1: Output_ID | D1: Protection_ID | E1: Tên liên kết | F1: Mức độ khớp | G1: Bằng chứng liên kết | H1: Điểm cần xác minh
A2: PPL-001 | B2: P2023-08 | C2: O-2023-08-02 | D2: PIP-007 | E2: Tinh dầu Citrus grandis ↔ KDCN 'Tinh dầu vỏ bưởi đào' | F2: Cao | G2: Tên sản phẩm cùng tinh dầu vỏ bưởi; năm KDCN 2024 ngay sau nghiệm thu 2023; chủ sở hữu có ĐHTĐ và CTY Thanh Huế, phù hợp dấu hiệu hợp tác doanh nghiệp. | H2: Cần hồ sơ KDCN để xác nhận tác giả/nguồn gốc từ đề tài và ngày nộp đơn.
A3: PPL-002 | B3: P2025-09 | C3: O-2025-09-03 | D3: PIP-011 | E3: Đề tài Quế hoa ↔ sáng chế hợp chất lignan glucoside/phương pháp chiết từ Osmanthus fragrans | F3: Rất cao | G3: Tên sáng chế trùng trực tiếp cây Quế hoa (Osmanthus fragrans) và hướng chiết xuất của đề tài; hồ sơ đề tài ghi Giai đoạn 2 có đầu ra 'Sáng chế'. | H3: Cần số đơn/văn bằng, ngày nộp, tác giả sáng chế, quan hệ với kinh phí đề tài và tình trạng thẩm định/cấp.

Sheet 15_KNOWLEDGE_IP_CHAIN
A1: Project_ID | B1: Năm | C1: Tên đề tài | D1: Strategic_Cluster | E1: Số đầu ra | F1: Đầu ra ưu tiên IP | G1: Công bố đã ghép | H1: Bảo hộ đã liên kết | I1: Đầu ra có dấu hiệu ứng dụng | J1: Giai đoạn chuỗi hiện quan sát được | K1: Khoảng trống cần kiểm chứng | L1: Đầu ra IP mức Cao
A2: =01_PROJECT_ALL!A2 -> P2021-20 | B2: =01_PROJECT_ALL!B2 -> 2021 | C2: =01_PROJECT_ALL!D2 -> Nghiên cứu năng lực nghe hiểu của sinh viên cử nhân thực hành tiếng Nhật năm thứ 2 tại Trường Đại học Thành Đô | D2: =01_PROJECT_ALL!I2 -> Global Communication | E2: =COUNTIF(02_OUTPUT_ALL!$B:$B,A2) -> 1 | F2: =COUNTIF(03_IP_PRIORITY_ALL!$C:$C,A2) -> 0 | G2: =COUNTIF(12_PUBLICATION_LINKS!$C:$C,A2) -> 0 | H2: =COUNTIF(14_PROJECT_PROTECTION_LINK!$B:$B,A2) -> 0 | I2: =COUNTIFS(02_OUTPUT_ALL!$B:$B,A2,02_OUTPUT_ALL!$L:$L,"Có") -> 0 | J2: =IF(H2>0,"Bảo hộ/xác lập có liên kết",IF(F2>0,IF(I2>0,"TSTT ưu tiên + có dấu hiệu ứng dụng","TSTT ưu tiên, chưa xác minh khai thác"),IF(G2>0,"Chủ yếu công bố học thuật","Mới ở đầu ra nghiên cứu"))) -> Mới ở đầu ra nghiên cứu | K2: =IF(AND(L2>0,H2=0),"Có đầu ra IP mức Cao nhưng chưa nối được hồ sơ bảo hộ; cần sàng lọc/đối chiếu",IF(AND(I2>0,H2=0,F2>0),"Có ứng dụng nhưng chưa xác định cơ chế quyền SHTT","")) | L2: =COUNTIFS(02_OUTPUT_ALL!$B:$B,A2,02_OUTPUT_ALL!$K:$K,"Cao") -> 0
A3: =01_PROJECT_ALL!A3 -> P2021-22 | B3: =01_PROJECT_ALL!B3 -> 2021 | C3: =01_PROJECT_ALL!D3 -> Đánh giá giáo trình Network dùng cho sinh viên năm thứ nhất Trường Đại học Thành Đô | D3: =01_PROJECT_ALL!I3 -> Global Communication | E3: =COUNTIF(02_OUTPUT_ALL!$B:$B,A3) -> 1 | F3: =COUNTIF(03_IP_PRIORITY_ALL!$C:$C,A3) -> 0 | G3: =COUNTIF(12_PUBLICATION_LINKS!$C:$C,A3) -> 0 | H3: =COUNTIF(14_PROJECT_PROTECTION_LINK!$B:$B,A3) -> 0 | I3: =COUNTIFS(02_OUTPUT_ALL!$B:$B,A3,02_OUTPUT_ALL!$L:$L,"Có") -> 0 | J3: =IF(H3>0,"Bảo hộ/xác lập có liên kết",IF(F3>0,IF(I3>0,"TSTT ưu tiên + có dấu hiệu ứng dụng","TSTT ưu tiên, chưa xác minh khai thác"),IF(G3>0,"Chủ yếu công bố học thuật","Mới ở đầu ra nghiên cứu"))) -> Mới ở đầu ra nghiên cứu | K3: =IF(AND(L3>0,H3=0),"Có đầu ra IP mức Cao nhưng chưa nối được hồ sơ bảo hộ; cần sàng lọc/đối chiếu",IF(AND(I3>0,H3=0,F3>0),"Có ứng dụng nhưng chưa xác định cơ chế quyền SHTT","")) | L3: =COUNTIFS(02_OUTPUT_ALL!$B:$B,A3,02_OUTPUT_ALL!$K:$K,"Cao") -> 0
A4: =01_PROJECT_ALL!A4 -> P2021-24 | B4: =01_PROJECT_ALL!B4 -> 2021 | C4: =01_PROJECT_ALL!D4 -> Đánh giá ứng dụng mô hình học tập kết hợp (Blended Learning) trong việc dạy và học tiếng Anh tại Trường Đại học Thành Đô | D4: =01_PROJECT_ALL!I4 -> Global Communication | E4: =COUNTIF(02_OUTPUT_ALL!$B:$B,A4) -> 1 | F4: =COUNTIF(03_IP_PRIORITY_ALL!$C:$C,A4) -> 0 | G4: =COUNTIF(12_PUBLICATION_LINKS!$C:$C,A4) -> 0 | H4: =COUNTIF(14_PROJECT_PROTECTION_LINK!$B:$B,A4) -> 0 | I4: =COUNTIFS(02_OUTPUT_ALL!$B:$B,A4,02_OUTPUT_ALL!$L:$L,"Có") -> 0 | J4: =IF(H4>0,"Bảo hộ/xác lập có liên kết",IF(F4>0,IF(I4>0,"TSTT ưu tiên + có dấu hiệu ứng dụng","TSTT ưu tiên, chưa xác minh khai thác"),IF(G4>0,"Chủ yếu công bố học thuật","Mới ở đầu ra nghiên cứu"))) -> Mới ở đầu ra nghiên cứu | K4: =IF(AND(L4>0,H4=0),"Có đầu ra IP mức Cao nhưng chưa nối được hồ sơ bảo hộ; cần sàng lọc/đối chiếu",IF(AND(I4>0,H4=0,F4>0),"Có ứng dụng nhưng chưa xác định cơ chế quyền SHTT","")) | L4: =COUNTIFS(02_OUTPUT_ALL!$B:$B,A4,02_OUTPUT_ALL!$K:$K,"Cao") -> 0
A5: =01_PROJECT_ALL!A5 -> P2021-27 | B5: =01_PROJECT_ALL!B5 -> 2021 | C5: =01_PROJECT_ALL!D5 -> Thực trạng và động lực phát triển chuyên môn của giáo viên | D5: =01_PROJECT_ALL!I5 -> Khác/Chưa phân loại | E5: =COUNTIF(02_OUTPUT_ALL!$B:$B,A5) -> 3 | F5: =COUNTIF(03_IP_PRIORITY_ALL!$C:$C,A5) -> 0 | G5: =COUNTIF(12_PUBLICATION_LINKS!$C:$C,A5) -> 1 | H5: =COUNTIF(14_PROJECT_PROTECTION_LINK!$B:$B,A5) -> 0 | I5: =COUNTIFS(02_OUTPUT_ALL!$B:$B,A5,02_OUTPUT_ALL!$L:$L,"Có") -> 0 | J5: =IF(H5>0,"Bảo hộ/xác lập có liên kết",IF(F5>0,IF(I5>0,"TSTT ưu tiên + có dấu hiệu ứng dụng","TSTT ưu tiên, chưa xác minh khai thác"),IF(G5>0,"Chủ yếu công bố học thuật","Mới ở đầu ra nghiên cứu"))) -> Chủ yếu công bố học thuật | K5: =IF(AND(L5>0,H5=0),"Có đầu ra IP mức Cao nhưng chưa nối được hồ sơ bảo hộ; cần sàng lọc/đối chiếu",IF(AND(I5>0,H5=0,F5>0),"Có ứng dụng nhưng chưa xác định cơ chế quyền SHTT","")) | L5: =COUNTIFS(02_OUTPUT_ALL!$B:$B,A5,02_OUTPUT_ALL!$K:$K,"Cao") -> 0
A6: =01_PROJECT_ALL!A6 -> P2021-28 | B6: =01_PROJECT_ALL!B6 -> 2021 | C6: =01_PROJECT_ALL!D6 -> Hoạt động công bố quốc tế tại Việt Nam: Thực trạng và ý nghĩa đối với cộng đồng và những nhà hoạch định chính sách | D6: =01_PROJECT_ALL!I6 -> Khác/Chưa phân loại | E6: =COUNTIF(02_OUTPUT_ALL!$B:$B,A6) -> 3 | F6: =COUNTIF(03_IP_PRIORITY_ALL!$C:$C,A6) -> 0 | G6: =COUNTIF(12_PUBLICATION_LINKS!$C:$C,A6) -> 2 | H6: =COUNTIF(14_PROJECT_PROTECTION_LINK!$B:$B,A6) -> 0 | I6: =COUNTIFS(02_OUTPUT_ALL!$B:$B,A6,02_OUTPUT_ALL!$L:$L,"Có") -> 0 | J6: =IF(H6>0,"Bảo hộ/xác lập có liên kết",IF(F6>0,IF(I6>0,"TSTT ưu tiên + có dấu hiệu ứng dụng","TSTT ưu tiên, chưa xác minh khai thác"),IF(G6>0,"Chủ yếu công bố học thuật","Mới ở đầu ra nghiên cứu"))) -> Chủ yếu công bố học thuật | K6: =IF(AND(L6>0,H6=0),"Có đầu ra IP mức Cao nhưng chưa nối được hồ sơ bảo hộ; cần sàng lọc/đối chiếu",IF(AND(I6>0,H6=0,F6>0),"Có ứng dụng nhưng chưa xác định cơ chế quyền SHTT","")) | L6: =COUNTIFS(02_OUTPUT_ALL!$B:$B,A6,02_OUTPUT_ALL!$K:$K,"Cao") -> 0
A7: =01_PROJECT_ALL!A7 -> P2021-37 | B7: =01_PROJECT_ALL!B7 -> 2021 | C7: =01_PROJECT_ALL!D7 -> Rào cản của các doanh nghiệp vừa và nhỏ trong việc áp dụng thương mại điện tử tại Việt Nam | D7: =01_PROJECT_ALL!I7 -> Digital Services | E7: =COUNTIF(02_OUTPUT_ALL!$B:$B,A7) -> 2 | F7: =COUNTIF(03_IP_PRIORITY_ALL!$C:$C,A7) -> 0 | G7: =COUNTIF(12_PUBLICATION_LINKS!$C:$C,A7) -> 1 | H7: =COUNTIF(14_PROJECT_PROTECTION_LINK!$B:$B,A7) -> 0 | I7: =COUNTIFS(02_OUTPUT_ALL!$B:$B,A7,02_OUTPUT_ALL!$L:$L,"Có") -> 0 | J7: =IF(H7>0,"Bảo hộ/xác lập có liên kết",IF(F7>0,IF(I7>0,"TSTT ưu tiên + có dấu hiệu ứng dụng","TSTT ưu tiên, chưa xác minh khai thác"),IF(G7>0,"Chủ yếu công bố học thuật","Mới ở đầu ra nghiên cứu"))) -> Chủ yếu công bố học thuật | K7: =IF(AND(L7>0,H7=0),"Có đầu ra IP mức Cao nhưng chưa nối được hồ sơ bảo hộ; cần sàng lọc/đối chiếu",IF(AND(I7>0,H7=0,F7>0),"Có ứng dụng nhưng chưa xác định cơ chế quyền SHTT","")) | L7: =COUNTIFS(02_OUTPUT_ALL!$B:$B,A7,02_OUTPUT_ALL!$K:$K,"Cao") -> 0
A8: =01_PROJECT_ALL!A8 -> P2022-01 | B8: =01_PROJECT_ALL!B8 -> 2022 | C8: =01_PROJECT_ALL!D8 -> Đề án thành lập Tạp chí Nghiên cứu khoa học và phát triển thuộc Trường Đại học Thành Đô | D8: =01_PROJECT_ALL!I8 -> Khác/Chưa phân loại | E8: =COUNTIF(02_OUTPUT_ALL!$B:$B,A8) -> 1 | F8: =COUNTIF(03_IP_PRIORITY_ALL!$C:$C,A8) -> 1 | G8: =COUNTIF(12_PUBLICATION_LINKS!$C:$C,A8) -> 0 | H8: =COUNTIF(14_PROJECT_PROTECTION_LINK!$B:$B,A8) -> 0 | I8: =COUNTIFS(02_OUTPUT_ALL!$B:$B,A8,02_OUTPUT_ALL!$L:$L,"Có") -> 1 | J8: =IF(H8>0,"Bảo hộ/xác lập có liên kết",IF(F8>0,IF(I8>0,"TSTT ưu tiên + có dấu hiệu ứng dụng","TSTT ưu tiên, chưa xác minh khai thác"),IF(G8>0,"Chủ yếu công bố học thuật","Mới ở đầu ra nghiên cứu"))) -> TSTT ưu tiên + có dấu hiệu ứng dụng | K8: =IF(AND(L8>0,H8=0),"Có đầu ra IP mức Cao nhưng chưa nối được hồ sơ bảo hộ; cần sàng lọc/đối chiếu",IF(AND(I8>0,H8=0,F8>0),"Có ứng dụng nhưng chưa xác định cơ chế quyền SHTT","")) -> Có ứng dụng nhưng chưa xác định cơ chế quyền SHTT | L8: =COUNTIFS(02_OUTPUT_ALL!$B:$B,A8,02_OUTPUT_ALL!$K:$K,"Cao") -> 0
A9: =01_PROJECT_ALL!A9 -> P2022-02 | B9: =01_PROJECT_ALL!B9 -> 2022 | C9: =01_PROJECT_ALL!D9 -> Nghiên cứu xây dựng Quy chế tuyển sinh và đào tạo trình độ thạc sỹ theo Thông tư số 23/2021/TT-BGDĐT của Bộ Giáo dục và Đào tạo tại Trường Đại học Thành Đô | D9: =01_PROJECT_ALL!I9 -> Khác/Chưa phân loại | E9: =COUNTIF(02_OUTPUT_ALL!$B:$B,A9) -> 1 | F9: =COUNTIF(03_IP_PRIORITY_ALL!$C:$C,A9) -> 1 | G9: =COUNTIF(12_PUBLICATION_LINKS!$C:$C,A9) -> 0 | H9: =COUNTIF(14_PROJECT_PROTECTION_LINK!$B:$B,A9) -> 0 | I9: =COUNTIFS(02_OUTPUT_ALL!$B:$B,A9,02_OUTPUT_ALL!$L:$L,"Có") -> 1 | J9: =IF(H9>0,"Bảo hộ/xác lập có liên kết",IF(F9>0,IF(I9>0,"TSTT ưu tiên + có dấu hiệu ứng dụng","TSTT ưu tiên, chưa xác minh khai thác"),IF(G9>0,"Chủ yếu công bố học thuật","Mới ở đầu ra nghiên cứu"))) -> TSTT ưu tiên + có dấu hiệu ứng dụng | K9: =IF(AND(L9>0,H9=0),"Có đầu ra IP mức Cao nhưng chưa nối được hồ sơ bảo hộ; cần sàng lọc/đối chiếu",IF(AND(I9>0,H9=0,F9>0),"Có ứng dụng nhưng chưa xác định cơ chế quyền SHTT","")) -> Có ứng dụng nhưng chưa xác định cơ chế quyền SHTT | L9: =COUNTIFS(02_OUTPUT_ALL!$B:$B,A9,02_OUTPUT_ALL!$K:$K,"Cao") -> 0
A10: =01_PROJECT_ALL!A10 -> P2022-12 | B10: =01_PROJECT_ALL!B10 -> 2022 | C10: =01_PROJECT_ALL!D10 -> Nâng cao khả năng được tuyển dụng của sinh viên ngành tiếng Anh Khoa Du lịch - Ngoại ngữ qua kỳ thực tập doanh nghiệp | D10: =01_PROJECT_ALL!I10 -> Global Communication | E10: =COUNTIF(02_OUTPUT_ALL!$B:$B,A10) -> 1 | F10: =COUNTIF(03_IP_PRIORITY_ALL!$C:$C,A10) -> 0 | G10: =COUNTIF(12_PUBLICATION_LINKS!$C:$C,A10) -> 0 | H10: =COUNTIF(14_PROJECT_PROTECTION_LINK!$B:$B,A10) -> 0 | I10: =COUNTIFS(02_OUTPUT_ALL!$B:$B,A10,02_OUTPUT_ALL!$L:$L,"Có") -> 0 | J10: =IF(H10>0,"Bảo hộ/xác lập có liên kết",IF(F10>0,IF(I10>0,"TSTT ưu tiên + có dấu hiệu ứng dụng","TSTT ưu tiên, chưa xác minh khai thác"),IF(G10>0,"Chủ yếu công bố học thuật","Mới ở đầu ra nghiên cứu"))) -> Mới ở đầu ra nghiên cứu | K10: =IF(AND(L10>0,H10=0),"Có đầu ra IP mức Cao nhưng chưa nối được hồ sơ bảo hộ; cần sàng lọc/đối chiếu",IF(AND(I10>0,H10=0,F10>0),"Có ứng dụng nhưng chưa xác định cơ chế quyền SHTT","")) | L10: =COUNTIFS(02_OUTPUT_ALL!$B:$B,A10,02_OUTPUT_ALL!$K:$K,"Cao") -> 0
A11: =01_PROJECT_ALL!A11 -> P2022-13 | B11: =01_PROJECT_ALL!B11 -> 2022 | C11: =01_PROJECT_ALL!D11 -> Đánh giá giáo trình "New English file" dành cho học viên cao học tại Trường Đại học Thành Đô | D11: =01_PROJECT_ALL!I11 -> Global Communication | E11: =COUNTIF(02_OUTPUT_ALL!$B:$B,A11) -> 1 | F11: =COUNTIF(03_IP_PRIORITY_ALL!$C:$C,A11) -> 0 | G11: =COUNTIF(12_PUBLICATION_LINKS!$C:$C,A11) -> 0 | H11: =COUNTIF(14_PROJECT_PROTECTION_LINK!$B:$B,A11) -> 0 | I11: =COUNTIFS(02_OUTPUT_ALL!$B:$B,A11,02_OUTPUT_ALL!$L:$L,"Có") -> 0 | J11: =IF(H11>0,"Bảo hộ/xác lập có liên kết",IF(F11>0,IF(I11>0,"TSTT ưu tiên + có dấu hiệu ứng dụng","TSTT ưu tiên, chưa xác minh khai thác"),IF(G11>0,"Chủ yếu công bố học thuật","Mới ở đầu ra nghiên cứu"))) -> Mới ở đầu ra nghiên cứu | K11: =IF(AND(L11>0,H11=0),"Có đầu ra IP mức Cao nhưng chưa nối được hồ sơ bảo hộ; cần sàng lọc/đối chiếu",IF(AND(I11>0,H11=0,F11>0),"Có ứng dụng nhưng chưa xác định cơ chế quyền SHTT","")) | L11: =COUNTIFS(02_OUTPUT_ALL!$B:$B,A11,02_OUTPUT_ALL!$K:$K,"Cao") -> 0
A12: =01_PROJECT_ALL!A12 -> P2022-14 | B12: =01_PROJECT_ALL!B12 -> 2022 | C12: =01_PROJECT_ALL!D12 -> A study on job satisfaction among teachers at TDU (Đánh giá sự hài lòng của giảng viên tại Đại học Thành Đô) | D12: =01_PROJECT_ALL!I12 -> Khác/Chưa phân loại | E12: =COUNTIF(02_OUTPUT_ALL!$B:$B,A12) -> 1 | F12: =COUNTIF(03_IP_PRIORITY_ALL!$C:$C,A12) -> 0 | G12: =COUNTIF(12_PUBLICATION_LINKS!$C:$C,A12) -> 0 | H12: =COUNTIF(14_PROJECT_PROTECTION_LINK!$B:$B,A12) -> 0 | I12: =COUNTIFS(02_OUTPUT_ALL!$B:$B,A12,02_OUTPUT_ALL!$L:$L,"Có") -> 0 | J12: =IF(H12>0,"Bảo hộ/xác lập có liên kết",IF(F12>0,IF(I12>0,"TSTT ưu tiên + có dấu hiệu ứng dụng","TSTT ưu tiên, chưa xác minh khai thác"),IF(G12>0,"Chủ yếu công bố học thuật","Mới ở đầu ra nghiên cứu"))) -> Mới ở đầu ra nghiên cứu | K12: =IF(AND(L12>0,H12=0),"Có đầu ra IP mức Cao nhưng chưa nối được hồ sơ bảo hộ; cần sàng lọc/đối chiếu",IF(AND(I12>0,H12=0,F12>0),"Có ứng dụng nhưng chưa xác định cơ chế quyền SHTT","")) | L12: =COUNTIFS(02_OUTPUT_ALL!$B:$B,A12,02_OUTPUT_ALL!$K:$K,"Cao") -> 0
A13: =01_PROJECT_ALL!A13 -> P2022-15 | B13: =01_PROJECT_ALL!B13 -> 2022 | C13: =01_PROJECT_ALL!D13 -> Nghiên cứu ảnh hưởng của hình thức dạy học trực tuyến đến kết quả học tập của sinh viên Khoa Du lịch - Ngoại ngữ, Trường Đại học Thành Đô | D13: =01_PROJECT_ALL!I13 -> Global Communication | E13: =COUNTIF(02_OUTPUT_ALL!$B:$B,A13) -> 1 | F13: =COUNTIF(03_IP_PRIORITY_ALL!$C:$C,A13) -> 0 | G13: =COUNTIF(12_PUBLICATION_LINKS!$C:$C,A13) -> 0 | H13: =COUNTIF(14_PROJECT_PROTECTION_LINK!$B:$B,A13) -> 0 | I13: =COUNTIFS(02_OUTPUT_ALL!$B:$B,A13,02_OUTPUT_ALL!$L:$L,"Có") -> 0 | J13: =IF(H13>0,"Bảo hộ/xác lập có liên kết",IF(F13>0,IF(I13>0,"TSTT ưu tiên + có dấu hiệu ứng dụng","TSTT ưu tiên, chưa xác minh khai thác"),IF(G13>0,"Chủ yếu công bố học thuật","Mới ở đầu ra nghiên cứu"))) -> Mới ở đầu ra nghiên cứu | K13: =IF(AND(L13>0,H13=0),"Có đầu ra IP mức Cao nhưng chưa nối được hồ sơ bảo hộ; cần sàng lọc/đối chiếu",IF(AND(I13>0,H13=0,F13>0),"Có ứng dụng nhưng chưa xác định cơ chế quyền SHTT","")) | L13: =COUNTIFS(02_OUTPUT_ALL!$B:$B,A13,02_OUTPUT_ALL!$K:$K,"Cao") -> 0
... A39: =01_PROJECT_ALL!A39 -> P2025-09 | B39: =01_PROJECT_ALL!B39 -> 2025 | C39: =01_PROJECT_ALL!D39 -> Nghiên cứu chiết xuất và đánh giá hoạt tính dược học của lá Quế hoa (Osmanthus fragrans) hướng tới ứng dụng trong thực phẩm chức năng | D39: =01_PROJECT_ALL!I39 -> Wellness & Care | E39: =COUNTIF(02_OUTPUT_ALL!$B:$B,A39) -> 3 | F39: =COUNTIF(03_IP_PRIORITY_ALL!$C:$C,A39) -> 1 | G39: =COUNTIF(12_PUBLICATION_LINKS!$C:$C,A39) -> 0 | H39: =COUNTIF(14_PROJECT_PROTECTION_LINK!$B:$B,A39) -> 1 | I39: =COUNTIFS(02_OUTPUT_ALL!$B:$B,A39,02_OUTPUT_ALL!$L:$L,"Có") -> 0 | J39: =IF(H39>0,"Bảo hộ/xác lập có liên kết",IF(F39>0,IF(I39>0,"TSTT ưu tiên + có dấu hiệu ứng dụng","TSTT ưu tiên, chưa xác minh khai thác"),IF(G39>0,"Chủ yếu công bố học thuật","Mới ở đầu ra nghiên cứu"))) -> Bảo hộ/xác lập có liên kết | K39: =IF(AND(L39>0,H39=0),"Có đầu ra IP mức Cao nhưng chưa nối được hồ sơ bảo hộ; cần sàng lọc/đối chiếu",IF(AND(I39>0,H39=0,F39>0),"Có ứng dụng nhưng chưa xác định cơ chế quyền SHTT","")) | L39: =COUNTIFS(02_OUTPUT_ALL!$B:$B,A39,02_OUTPUT_ALL!$K:$K,"Cao") -> 1

Sheet 16_VERIFICATION_FINDINGS
A1: Finding_ID | B1: Nội dung xác nhận | C1: Bằng chứng hiện có | D1: Cách diễn giải được phép | E1: Không được suy diễn | F1: Hệ quả đối với chỉ số | G1: Phương pháp thay thế/bổ sung | H1: Mức quan trọng
A2: VF01 | B2: Có danh sách tổng hợp SHTT gồm 16 đối tượng trong nguồn người dùng cung cấp. | C2: 4 bản quyền tác giả; 5 nhãn hiệu; 5 kiểu dáng công nghiệp; 2 sáng chế. | D2: Có thể dùng làm inventory nguồn; cần tách tài sản trực tiếp của ĐHTĐ khỏi tài sản UNIGO/cá nhân. | E2: Không coi toàn bộ 16 là TSTT của ĐHTĐ. | F2: Có thể tính số lượng/cơ cấu portfolio theo nguồn và theo phạm vi chủ sở hữu. | G2: Đối chiếu hồ sơ gốc nếu cần xác nhận trạng thái pháp lý chi tiết. | H2: Rất cao
A3: VF02 | B3: Trong danh sách nguồn, có 12 đối tượng mà ĐHTĐ là chủ sở hữu/đồng sở hữu; 11 đối tượng thuộc giai đoạn 2021-2025. | C3: 2 QTG; 3 nhãn hiệu (gồm Double2n ở trạng thái tiếp nhận đơn); 5 KDCN; 2 sáng chế, trong đó một sáng chế năm 2026. | D3: Đây là portfolio trực tiếp phù hợp nhất cho nghiên cứu quản trị SHTT tại Trường. | E3: Không coi Double2n là đã được cấp; không coi 2 sáng chế là đã nộp/cấp khi thiếu số đơn/văn bằng. | F3: Có thể mô tả cấu trúc tài sản, nhưng protection success rate phải dùng mẫu số/trạng thái được xác minh. | G3: Xin số đơn/ngày nộp hoặc bản sao hồ sơ nếu còn khả năng tiếp cận. | H3: Rất cao
A4: VF03 | B4: Không có phiếu khai báo/biên bản nhận diện TSTT hoặc sổ/CSDL tương đương theo xác nhận hiện tại. | C4: Xác nhận trực tiếp của người dùng trong quá trình nghiên cứu. | D4: Có thể kết luận: chưa có bằng chứng tài liệu hóa khâu disclosure/nhận diện trong bộ hồ sơ hiện có. | E4: Không kết luận rằng hoạt động nhận diện chưa từng diễn ra hoặc cá nhân không trao đổi không chính thức. | F4: Không tính được Disclosure/Identification Rate dựa trên hồ sơ. | G4: Phỏng vấn bán cấu trúc để tái dựng quy trình thực tế; process tracing theo 2-5 case. | H4: Rất cao
A5: VF04 | B5: Không có hồ sơ sàng lọc/tra cứu khả năng bảo hộ theo xác nhận hiện tại. | C5: Xác nhận trực tiếp của người dùng. | D5: Có thể đánh giá khoảng trống về khả năng truy vết quyết định chọn/không chọn bảo hộ. | E5: Không kết luận rằng không ai từng tra cứu hoặc cân nhắc khả năng bảo hộ. | F5: Không tính được Screening Rate hoặc thời gian từ disclosure đến screening. | G5: Phỏng vấn người phụ trách; kiểm tra email/quyết định/tra cứu bên ngoài nếu có. | H5: Rất cao
A6: VF05 | B6: Không có hợp đồng chuyển giao/cấp phép/biên bản thương mại hóa trong bộ hồ sơ hiện có theo xác nhận hiện tại. | C6: Xác nhận trực tiếp của người dùng; một số hồ sơ nghiệm thu chỉ ghi dấu hiệu 'chuyển giao/ứng dụng'. | D6: Có thể phân biệt rõ 'dấu hiệu ứng dụng/chuyển giao' với 'giao dịch thương mại đã được chứng minh'. | E6: Không kết luận rằng chưa từng có ứng dụng thực tế; cũng không coi dòng nghiệm thu là hợp đồng chuyển giao. | F6: Không tính được Commercialization Rate, licensing revenue hoặc IP-to-Value chính thức. | G6: Case study + phỏng vấn + chứng từ tài chính/biên bản bàn giao nếu tìm được; nếu không, chỉ đo giá trị phi tài chính. | H6: Rất cao
A7: VF06 | B7: Tồn tại chuỗi sản phẩm nghiên cứu có khả năng liên kết với quyền SHTT, nhưng mới có 2 liên kết đề tài↔bảo hộ có bằng chứng mạnh. | C7: P2023-08 ↔ KDCN Tinh dầu vỏ bưởi đào; P2025-09 ↔ sáng chế về Osmanthus fragrans. | D7: Dùng làm case tracing để kiểm tra cách một đầu ra đi từ nghiên cứu sang bảo hộ. | E7: Không ngoại suy 2 case này cho toàn bộ portfolio. | F7: Tạo 'Observed Project-to-Protection Link' mô tả, không gọi là conversion rate chính thức. | G7: Phỏng vấn chủ nhiệm + Phòng KHCN, lập timeline của từng case. | H7: Cao

Sheet 17_LEGAL_PRACTICE_MATRIX
A1: Matrix_ID | B1: Khâu quản trị | C1: Tầng chuẩn | D1: Văn bản/Điều | E1: Nội dung chuẩn cần đối chiếu | F1: Tình trạng hiệu lực/áp dụng | G1: Bằng chứng thực tế 2021-2025 | H1: Đánh giá sơ bộ | I1: Loại khoảng cách | J1: Mức rủi ro | K1: Câu hỏi cần xác minh | L1: Nguồn/URL
A2: M01 | B2: Phạm vi TSTT | C2: Quy chế nội bộ | D2: QC quản trị TSTT 2024, Điều 2-3 | E2: TSTT được hiểu rộng: công bố, dữ liệu, học liệu, phần mềm, thông tin kỹ thuật, nhãn hiệu, KDCN, bí quyết và các kết quả sáng tạo khác; TSTT của Trường là tài sản thuộc sở hữu/đồng sở hữu của Trường. | F2: Đã ban hành theo QĐ số 217/QĐ-ĐHTĐ ngày 21/11/2024; hiệu lực từ 21/11/2024. | G2: Dataset đã nhận diện 90 đầu ra từ 38 đề tài; 26 đầu ra cần quản trị IP sâu hơn. | H2: Khung nội bộ bao quát rộng hơn danh mục văn bằng; dữ liệu thực tế hiện mới quản lý chắc chắn phần quyền đã đăng ký và đầu ra đề tài. | I2: Documentation/data gap | J2: Trung bình | K2: Sau khi Quy chế có hiệu lực từ 21/11/2024, Trường đã ban hành/triển khai những biểu mẫu và quy trình nào để thực hiện các yêu cầu về nhận diện, theo dõi và khai thác TSTT? | L2: QĐ 217/QĐ-ĐHTĐ ngày 21/11/2024 – Quy chế quản trị TSTT
A3: M02 | B3: Xác định sở hữu | C3: Quy chế nội bộ | D3: QC quản trị TSTT 2024, Điều 3-6 | E3: Trường sở hữu TSTT tạo ra chủ yếu từ ngân sách/nguồn lực do Trường quản lý; có thể đồng sở hữu khi dùng nguồn lực nhiều bên; tỷ lệ sở hữu cần thỏa thuận bằng văn bản. NLĐ/người học có quyền sở hữu riêng trong các trường hợp không dùng nguồn lực Trường hoặc theo điều kiện quy định. | F3: QC quản trị TSTT đã ban hành theo QĐ số 217/QĐ-ĐHTĐ ngày 21/11/2024, hiệu lực 21/11/2024; QĐ 213/QĐ-ĐHTĐ năm 2021 tiếp tục là căn cứ cho Quy chế hoạt động KHCN. | G3: Portfolio có tài sản ĐHTĐ sở hữu, đồng sở hữu với CTY Thanh Huế, và tài sản ngoài phạm vi ĐHTĐ (UNIGO/cá nhân). | H3: Có thực tiễn phân biệt chủ sở hữu, nhưng hồ sơ đầu ra đề tài hiện chưa luôn cho thấy quyết định sở hữu/đồng sở hữu cụ thể. | I3: Documentation/ownership traceability gap | J3: Cao | K3: Đối với từng case đồng sáng tạo, quyền sở hữu được quyết định khi ký hợp đồng, khi nghiệm thu hay khi nộp đơn? | L3: QĐ 217/QĐ-ĐHTĐ ngày 21/11/2024; QĐ 213/QĐ-ĐHTĐ năm 2021
A4: M03 | B4: Nhận diện/kê khai TSTT | C4: Quy chế nội bộ | D4: QC quản trị TSTT 2024, Điều 11 | E4: Phòng KHCN xây dựng quy trình, biểu mẫu ghi nhận/khai báo; nhận diện, ghi nhận TSTT mới; lập hồ sơ thống kê, theo dõi, lưu trữ tập trung. | F4: Đã ban hành theo QĐ số 217/QĐ-ĐHTĐ ngày 21/11/2024; hiệu lực từ 21/11/2024. | G4: Người dùng xác nhận hiện không có phiếu khai báo/biên bản nhận diện hoặc sổ/CSDL disclosure tương đương. | H4: Không có bằng chứng tài liệu hóa một cơ chế disclosure/identification có khả năng truy vết. | I4: Documentation gap | J4: Rất cao | K4: Nếu không dùng phiếu khai báo, tài sản mới được báo cho Phòng KHCN bằng kênh nào? Ai quyết định một kết quả cần bảo hộ? | L4: QĐ 217/QĐ-ĐHTĐ ngày 21/11/2024 – Quy chế quản trị TSTT
A5: M04 | B5: Công bố trước bảo hộ | C5: Quy chế nội bộ | D5: QC quản trị TSTT 2024, Điều 10 | E5: Công bố không được ảnh hưởng khả năng bảo hộ/khai thác; tác giả cần xác định TSTT có thể bảo hộ và xin ý kiến Phòng KHCN trước khi bộc lộ công khai. | F5: QC quản trị TSTT có hiệu lực từ 21/11/2024 theo QĐ 217/QĐ-ĐHTĐ; QĐ 213/QĐ-ĐHTĐ năm 2021 cũng có quy định bảo mật và phổ biến/sử dụng kết quả. | G5: Có đề tài vừa có bài báo vừa có công thức/quy trình dự kiến GPHI; chưa có hồ sơ screening/timing. | H5: Rủi ro không nằm ở việc đã công bố hay chưa, mà ở việc không truy vết được quyết định 'công bố trước hay nộp đơn trước'. | I5: Process traceability/risk gap | J5: Cao | K5: Trong case cồn xoa bóp, viên ngậm, Quế hoa: thời điểm bài báo, thời điểm quyết định bảo hộ và thời điểm nộp đơn là khi nào? | L5: QĐ 217/QĐ-ĐHTĐ ngày 21/11/2024; QĐ 213/QĐ-ĐHTĐ năm 2021
A6: M05 | B6: Đăng ký quyền SHTT | C6: Quy chế nội bộ | D6: QĐ 213/QĐ-ĐHTĐ 2021, Điều 35 | E6: Tác giả nộp đơn tại Phòng KHCN; Phòng KHCN kiểm tra hình thức, yêu cầu sửa đổi nếu cần, trình Hiệu trưởng ký và nộp đơn/lệ phí tại cơ quan nhà nước. | F6: Có hiệu lực từ 01/01/2022 theo Quyết định 213/2021. | G6: Danh mục nguồn có 11 đối tượng ĐHTĐ trực tiếp trong 2021-2025; 9 có số đăng ký/văn bằng/ký hiệu, 1 nhãn hiệu ở trạng thái tiếp nhận đơn, 1 sáng chế 2025 chưa có số trong danh sách. | H6: Có đầu ra đăng ký/bảo hộ thực tế, nhưng không có hồ sơ trung gian để đo thời gian xử lý hay tỷ lệ từ đề xuất → nộp đơn. | I6: Documentation/process measurement gap | J6: Cao | K6: Quy trình Điều 35 thực tế được khởi động bằng biểu mẫu nào? Có lưu ngày nhận đơn nội bộ/ngày trình ký/ngày nộp không? | L6: 02. QĐ 213_QĐ-ĐHTĐ- Quy chế HĐ KHCN năm 2021.pdf
A7: M06 | B7: Sàng lọc loại quyền | C7: Thông lệ quản trị + nội bộ | D7: QC 2024 Điều 10-11; QĐ 213 Điều 35 | E7: Trước công bố/đăng ký cần nhận diện đối tượng và lựa chọn cơ chế bảo hộ phù hợp; QC giao Phòng KHCN quản lý/nhận diện và QĐ 213 quy định quy trình đăng ký. | F7: QC quản trị TSTT có hiệu lực từ 21/11/2024 theo QĐ 217/QĐ-ĐHTĐ; QĐ 213/QĐ-ĐHTĐ năm 2021 có hiệu lực. | G7: Người dùng xác nhận không có hồ sơ sàng lọc/tra cứu khả năng bảo hộ. | H7: Không thể biết tiêu chí vì sao chọn KDCN, nhãn hiệu, sáng chế/GPHI hoặc không đăng ký. | I7: Decision-documentation gap | J7: Rất cao | K7: Ai tư vấn loại quyền? Có thuê đại diện SHTT/tra cứu ngoài trường không? Quyết định dựa trên tiêu chí nào? | L7: QĐ 217/QĐ-ĐHTĐ ngày 21/11/2024; QĐ 213/QĐ-ĐHTĐ năm 2021
A8: M07 | B8: Quyền đăng ký với nhiệm vụ dùng NSNN | C8: Pháp luật quốc gia | D8: Luật SHTT hiện hành (sửa đổi 2025), Điều 86; NĐ hướng dẫn về kết quả nhiệm vụ dùng NSNN | E8: Tổ chức được giao quyền quản lý/sử dụng hoặc quyền sở hữu kết quả nhiệm vụ KH,CN&ĐMST dùng NSNN có quyền đăng ký sáng chế, KDCN, thiết kế bố trí là kết quả nhiệm vụ; với nhiệm vụ dùng NSNN có cơ chế quyền/ nghĩa vụ riêng. | F8: Áp dụng trực tiếp cho nhiệm vụ dùng NSNN; không tự động áp dụng cho mọi đề tài cấp cơ sở bằng nguồn Trường. | G8: Dataset có đề tài cấp cơ sở và một số đề tài quốc gia/NAFOSTED; chưa trộn hai nhóm trong cùng mẫu phân tích bảo hộ. | H8: Cần phân tầng nguồn kinh phí khi phân tích quyền đăng ký và nghĩa vụ. | I8: Scope/classification gap | J8: Trung bình | K8: Các sáng chế/KDCN nào hình thành từ nhiệm vụ NSNN, nguồn Trường, doanh nghiệp hay nguồn hỗn hợp? | L8: https://vbpl.vn/TW/Pages/vbpq-toanvan.aspx?ItemID=187492 ; https://vbpl.vn/TW/Pages/vbpq-toanvan.aspx?ItemID=164372
A9: M08 | B9: Thương mại hóa | C9: Pháp luật quốc gia | D9: Luật KH,CN&ĐMST 93/2025/QH15, Điều 27 | E9: Chủ sở hữu tự quyết định thương mại hóa; tổ chức được giao quản lý/sử dụng kết quả có quyền tự quyết hình thức, phương án, giá và phân chia lợi nhuận; luật quy định cơ chế thưởng tác giả trong trường hợp thuộc phạm vi điều chỉnh. | F9: Luật có hiệu lực 01/10/2025; cần phân biệt thời kỳ trước/sau hiệu lực và phạm vi nguồn vốn. | G9: Không có hợp đồng chuyển giao/cấp phép/biên bản thương mại hóa trong bộ hồ sơ hiện có; một số hồ sơ nghiệm thu chỉ ghi dấu hiệu ứng dụng/chuyển giao. | H9: Không đủ bằng chứng để tính commercialization rate hay doanh thu SHTT. | I9: Evidence/commercialization gap | J9: Rất cao | K9: Có ứng dụng nội bộ, bán thử, bàn giao mẫu, hợp tác doanh nghiệp hoặc thu nhập nào không được ghi dưới dạng hợp đồng chuyển giao? | L9: https://vbpl.vn/TW/Pages/ivbpq-toanvan.aspx?ItemID=179265
A10: M09 | B10: Chuyển giao/khai thác | C10: Quy chế nội bộ | D10: QĐ 213/2021, Điều 36; QC 2024, Điều 11 | E10: QĐ 213 quy định chuyển giao/thương mại hóa và phân chia lợi nhuận; QC giao Phòng KHCN xúc tiến thương mại hóa và phối hợp ký hợp đồng chuyển giao, li-xăng, góp vốn, liên doanh/liên kết bằng TSTT. | F10: QĐ 213/QĐ-ĐHTĐ năm 2021 có hiệu lực; QC quản trị TSTT có hiệu lực từ 21/11/2024 theo QĐ 217/QĐ-ĐHTĐ. | G10: Case tinh dầu vỏ bưởi ghi 'sản phẩm chuyển giao công nghệ cho Trường ... thương mại hóa' nhưng không có hợp đồng/biên bản thương mại hóa trong hồ sơ hiện có. | H10: Có dấu hiệu khai thác nhưng thiếu bằng chứng giao dịch và định nghĩa thống nhất về 'chuyển giao'. | I10: Documentation/definition gap | J10: Rất cao | K10: Trong hồ sơ 2023, 'chuyển giao cho Trường để thương mại hóa' nghĩa là bàn giao nội bộ, chuyển quyền, chuyển giao công nghệ hay chỉ nghiệm thu sản phẩm? | L10: QĐ 213/QĐ-ĐHTĐ năm 2021; QĐ 217/QĐ-ĐHTĐ ngày 21/11/2024
A11: M10 | B11: Phân chia lợi ích | C11: Quy chế nội bộ + pháp luật | D11: QĐ 213/2021 Điều 36; Luật 93/2025 Điều 27 | E11: QĐ 213 có công thức phân chia cho một số trường hợp; pháp luật 2025 quy định cơ chế tự chủ và mức thưởng tối thiểu cho tác giả trong phạm vi luật. | F11: Cần xem lại tính tương thích của công thức nội bộ cũ với pháp luật mới từ 01/10/2025, đặc biệt theo nguồn vốn/kết quả. | G11: Chưa có chứng từ phân chia lợi ích trong dataset. | H11: Policy update + evidence gap | I11: Cao | J11: Quy chế nội bộ đã được rà soát sau Luật 93/2025 chưa? Có trường hợp nào từng chi thù lao/lợi ích từ TSTT? | K11: QĐ 213/QĐ-ĐHTĐ 2021; https://vbpl.vn/TW/Pages/ivbpq-toanvan.aspx?ItemID=179265
A12: M11 | B12: Theo dõi portfolio | C12: Quy chế nội bộ | D12: QC quản trị TSTT 2024, Điều 11 | E12: Phòng KHCN lập hồ sơ thống kê, theo dõi TSTT sở hữu/đồng sở hữu, lưu trữ tập trung và phối hợp khai thác. | F12: Đã ban hành theo QĐ số 217/QĐ-ĐHTĐ ngày 21/11/2024; hiệu lực từ 21/11/2024. | G12: Có danh sách tổng hợp văn bằng/đơn; tuy nhiên trạng thái một số mục chưa đủ số đơn/văn bằng và portfolio chưa nối hoàn chỉnh với nguồn đề tài. | H12: Có inventory nhưng chưa đạt mức lifecycle database đầy đủ. | I12: Data architecture gap | J12: Cao | K12: Có file theo dõi ngày nộp, ngày cấp, gia hạn, chi phí, tác giả, đề tài nguồn và tình trạng khai thác hay không? | L12: QĐ 217/QĐ-ĐHTĐ ngày 21/11/2024 – Quy chế quản trị TSTT
A13: M12 | B13: Số hóa dữ liệu KH,CN&ĐMST | C13: Pháp luật quốc gia | D13: Luật 93/2025 và văn bản hướng dẫn về thông tin/chuyển đổi số | E13: Khung pháp luật mới nhấn mạnh nền tảng số quản lý toàn diện và số hóa kết quả, dữ liệu KH,CN&ĐMST. | F13: Khung pháp luật có hiệu lực từ 2025; mức áp dụng cụ thể tại cơ sở tư thục cần đặt trong bối cảnh nghĩa vụ/quản trị nội bộ. | G13: Dữ liệu hiện phân tán ở nhiều danh mục PDF/Word/ảnh; nhóm nghiên cứu phải tự nối Project–Output–Publication–Protection. | H13: Mức trưởng thành dữ liệu còn phân tán, khó đo vòng đời TSTT. | I13: Digital governance gap | J13: Cao | K13: Trường hiện dùng phần mềm/CSDL nào cho KHCN và SHTT? Có mã định danh thống nhất cho đề tài–đầu ra–TSTT không? | L13: https://vbpl.vn/TW/Pages/vbpq-toanvan.aspx?ItemID=183315

Sheet 18_INTERVIEW_GUIDE
A1: BỘ PHỎNG VẤN BÁN CẤU TRÚC – PROCESS TRACING (KHÔNG PHẢI KHẢO SÁT ĐỊNH LƯỢNG)
A3: Q_ID | B3: Nhóm người trả lời | C3: Câu hỏi chính | D3: Mục đích bằng chứng | E3: Case ưu tiên | F3: Câu hỏi gợi mở | G3: Không được dẫn dắt theo hướng | H3: Mã hóa sau phỏng vấn
A4: Q01 | B4: Phòng KHCN/Quản lý | C4: Khi một đề tài tạo ra sản phẩm, công thức, quy trình hoặc thiết kế mới, bằng cách nào Phòng KHCN biết rằng có TSTT cần xem xét? | D4: Tái dựng khâu nhận diện/disclosure | E4: Tất cả | F4: Ai báo? bằng email, văn bản, họp hay khi nghiệm thu? Có mốc thời gian không? | G4: Không hỏi 'vì sao không có phiếu disclosure' ngay từ đầu | H4: Trigger; channel; actor; timing
A5: Q02 | B5: Phòng KHCN/Quản lý | C5: Ai quyết định một kết quả nên đăng ký SHTT, giữ bí mật, chỉ công bố hay không tiếp tục bảo hộ? | D5: Tái dựng decision rule | E5: Quế hoa; cồn xoa bóp; viên ngậm; xà phòng | F5: Có tiêu chí về tính mới, thị trường, chi phí, khả năng áp dụng không? | G5: Không mặc định quyết định là sai hoặc thiếu | H5: Decision maker; criteria; alternatives
A6: Q03 | B6: Phòng KHCN/Chủ nhiệm | C6: Trước khi bài báo hoặc kết quả được công bố, có bước nào kiểm tra nguy cơ mất khả năng bảo hộ không? | D6: Kiểm tra publication-before-protection control | E6: Quế hoa; cồn xoa bóp; viên ngậm | F6: Ai kiểm tra? khi nào? bằng tài liệu gì? | G6: Không gợi ý rằng đã có vi phạm tính mới | H6: Timing; confidentiality; review
A7: Q04 | B7: Phòng KHCN | C7: Quy trình đăng ký theo Điều 35 của Quy chế KHCN 2021 được thực hiện trên thực tế như thế nào? | D7: So sánh formal process vs actual process | E7: Các nhãn hiệu/KDCN/sáng chế | F7: Có bước nhận nội bộ, trình ký, nộp phí, theo dõi trạng thái không? | G7: Không coi quy chế giấy là quy trình thực tế | H7: Actual steps; deviations; records
A8: Q05 | B8: Chủ nhiệm/Tác giả | C8: Anh/chị biết kết quả của mình có khả năng đăng ký SHTT từ thời điểm nào? Ai là người gợi ý đầu tiên? | D8: Nguồn hình thành ý định bảo hộ | E8: 5 case công nghệ | F8: Do cá nhân, Phòng KHCN, doanh nghiệp, đại diện SHTT hay hội đồng nghiệm thu? | G8: Không hỏi nhận thức chung chung | H8: Awareness trigger; initiator
A9: Q06 | B9: Chủ nhiệm/Tác giả | C9: Yếu tố nào khiến nhóm quyết định tiếp tục hoặc không tiếp tục đăng ký? | D9: Nguyên nhân dừng/tiếp tục | E9: Panel ô tô; xà phòng; cồn; viên ngậm | F9: Chi phí, thời gian, tính mới, lợi ích, thủ tục, doanh nghiệp, công bố? | G9: Không ép chọn danh sách nguyên nhân | H9: Barrier/enabler; priority
A10: Q07 | B10: Chủ nhiệm/Tác giả + Quản lý | C10: Trong trường hợp có nhiều bên tham gia, quyền sở hữu và quyền nộp đơn được thỏa thuận ở thời điểm nào? | D10: Ownership governance | E10: Tinh dầu vỏ bưởi; tài sản ĐHTĐ–Thanh Huế | F10: Có hợp đồng từ đầu không? ai đứng tên? phân chia thế nào? | G10: Không giả định có tranh chấp | H10: Ownership timing; agreement; co-ownership
A11: Q08 | B11: Quản lý + Đơn vị sử dụng | C11: Sau khi có văn bằng/đơn, ai chịu trách nhiệm theo dõi và tìm cách sử dụng hoặc khai thác tài sản? | D11: Post-protection governance | E11: KDCN; nhãn hiệu; sáng chế | F11: Có mục tiêu sử dụng, đối tác, ngân sách khai thác không? | G11: Không đồng nhất 'có văn bằng' với 'có giá trị' | H11: Owner after grant; exploitation plan
A12: Q09 | B12: Quản lý/Doanh nghiệp/Chủ nhiệm | C12: Khái niệm 'chuyển giao' được hiểu và ghi nhận trong Trường như thế nào? | D12: Làm rõ định nghĩa thực hành | E12: Tinh dầu vỏ bưởi | F12: Bàn giao nội bộ khác hợp đồng CGCN/cấp phép như thế nào? | G12: Không gọi mọi bàn giao là thương mại hóa | H12: Transfer definition; evidence
A13: Q10 | B13: Đơn vị sử dụng/Chủ nhiệm | C13: Sản phẩm nghiên cứu đã được dùng trong giảng dạy, nghiên cứu tiếp, vận hành nội bộ hoặc bởi bên ngoài như thế nào? | D13: Đo giá trị phi tài chính | E13: Panel; bộ mẫu; tiêu bản; xà phòng | F13: Bao nhiêu lớp/người dùng/lần sử dụng? thay thế chi phí gì? | G13: Không chỉ hỏi doanh thu | H13: Utilization; reach; replacement value
A14: Q11 | B14: Quản lý/Tài chính | C14: Nếu TSTT tạo ra thu nhập hoặc được định giá, cơ chế phân chia lợi ích và ghi nhận tài chính được thực hiện thế nào? | D14: Kiểm tra incentive/value governance | E14: Case có khai thác nếu có | F14: Có từng phát sinh trường hợp thực tế chưa? | G14: Không giả định đã có doanh thu | H14: Revenue; benefit share; accounting
... A18: Q15 | B18: Chuyên gia/Quản lý | C18: Những chỉ số nào nên dùng để đánh giá hiệu quả quản trị TSTT của một trường tư thục như Thành Đô? | D18: Thẩm định KPI | E18: Toàn hệ thống | F18: Nên ưu tiên output, protection, use, revenue, time-to-IP hay strategic value? | G18: Không áp đặt bộ KPI đã xây | H18: KPI relevance; weights

Sheet 19_CASE_TRACE
A1: Case_ID | B1: Project_ID | C1: Case | D1: Lý do chọn | E1: Mốc 1: Đề tài | F1: Mốc 2: Đầu ra kỹ thuật | G1: Mốc 3: Công bố | H1: Mốc 4: Quyết định IP | I1: Mốc 5: Đơn/Văn bằng | J1: Mốc 6: Ứng dụng | K1: Bằng chứng còn thiếu | L1: Người nên phỏng vấn | M1: Kết luận được phép hiện tại
A2: C01 | B2: P2023-08 | C2: Tinh dầu vỏ bưởi | D2: Có hợp tác DN + sản phẩm + KDCN liên kết mạnh + ghi dấu hiệu thương mại hóa | E2: Đề tài 08-2023/KHCN; nghiệm thu 13/11/2023 | F2: Tinh dầu Citrus grandis 100ml | G2: Có bài báo liên quan hợp tác Nhà trường-DN ngành Dược | H2: Chưa có hồ sơ quyết định/sàng lọc | I2: KDCN 'Tinh dầu vỏ bưởi đào' 3-0039694-000, 2024; ĐHTĐ + CTY Thanh Huế | J2: Hồ sơ đề tài ghi 'chuyển giao cho Trường ... thương mại hóa' | K2: Hồ sơ KDCN gốc; ngày nộp; tác giả; thỏa thuận sở hữu; nghĩa của 'chuyển giao'; bằng chứng sử dụng/doanh thu | L2: Phan Thị Thanh Thảo; đại diện CTY Thanh Huế; Phòng KHCN | M2: Có chuỗi nghiên cứu→KDCN có khả năng cao; chưa xác nhận giao dịch thương mại.
A3: C02 | B3: P2025-09 | C3: Quế hoa (Osmanthus fragrans) | D3: Đề tài ghi đầu ra sáng chế; danh mục SHTT có sáng chế trùng trực tiếp đối tượng | E3: Đề tài 09-2025/KHCN; giai đoạn 1 nghiệm thu 25/12/2025 | F3: Chiết xuất/đánh giá hoạt tính lá Quế hoa | G3: Có công bố giai đoạn 1 theo hồ sơ, cần ghép chi tiết | H3: Chưa có hồ sơ sàng lọc/quyết định | I3: Sáng chế 'Các hợp chất furofuran lignan glucoside...' năm 2025; chưa có số trong danh sách | J3: Chưa có bằng chứng khai thác | K3: Số đơn/văn bằng; ngày nộp; tác giả sáng chế; nguồn kinh phí; timeline công bố-bảo hộ | L3: Nguyễn Ngọc Linh; Phòng KHCN | M3: Liên kết đề tài→sáng chế rất cao; chưa được phép gọi là văn bằng đã cấp.
A4: C03 | B4: P2024-06 | C4: Xà phòng tảo biển | D4: Có prototype số lượng lớn + công thức/quy trình + bài báo nhưng chưa nối được bảo hộ | E4: Đề tài 06-2024/KHCN; nghiệm thu 15/11/2024 | F4: 200 bánh xà phòng + quy trình/công thức | G4: Bài 'Nghiên cứu chế tạo xà bông từ tảo spirulina' | H4: Chưa có bằng chứng sàng lọc | I4: Chưa nối được đơn/văn bằng từ danh mục hiện có | J4: Có sản phẩm vật chất; chưa có bằng chứng mức sử dụng | K4: Có tra cứu tính mới không; vì sao không đăng ký/GPHI/BMKD; sản phẩm có dùng/bán/thử nghiệm không | L4: Nguyễn Ngọc Linh; Phạm Thị Bích Đào; Phòng KHCN | M4: Case 'high potential but no observed protection link' để giải thích điểm nghẽn.
A5: C04 | B5: P2025-06 | C5: Cồn xoa bóp | D5: Hồ sơ ghi công thức mới, dự kiến GPHI; chưa có liên kết bảo hộ | E5: Đề tài 06-2025/KHCN; nghiệm thu 25/12/2025 | F5: Công thức + 50 chai sản phẩm | G5: Có bài NCKH&PT theo hồ sơ | H5: Dự kiến đăng ký GPHI | I5: Chưa có số đơn/văn bằng trong danh sách hiện có | J5: Chưa có bằng chứng khai thác | K5: Đã nộp đơn chưa; ai quyết định; timing bài báo; tra cứu novelty; lý do tiếp tục/dừng | L5: Nguyễn Đăng Việt; Phòng KHCN | M5: Chỉ được gọi là 'dự kiến đăng ký' cho tới khi có bằng chứng đơn.
A6: C05 | B6: P2025-07 | C6: Viên ngậm Gừng – Húng chanh | D6: Quy trình mới, dự kiến GPHI + sản phẩm 50 thanh; chưa nối bảo hộ | E6: Đề tài 07-2025/KHCN; nghiệm thu 25/12/2025 | F6: Quy trình + sản phẩm viên ngậm | G6: Có bài báo theo hồ sơ | H6: Dự kiến đăng ký GPHI | I6: Chưa có số đơn/văn bằng trong danh sách hiện có | J6: Chưa có bằng chứng khai thác | K6: Đã nộp đơn chưa; ai sàng lọc; thời điểm công bố; bằng chứng sử dụng/đối tác | L6: Ngô Thị Thu; Phòng KHCN | M6: Case chuyển đổi tiềm năng để kiểm tra từ 'dự kiến' sang 'nộp đơn'.
A7: C06 | B7: P2022-37 | C7: Panel ô tô | D7: Prototype rõ, phục vụ đào tạo, không thấy bảo hộ – phù hợp đo giá trị ứng dụng phi tài chính | E7: Đề tài 37-2022/KHCN; nghiệm thu 09/11/2022 | F7: Mô hình kiểm tra/sửa chữa hệ thống khởi động ô tô | G7: Không phải case công bố trọng tâm | H7: Không có hồ sơ sàng lọc | I7: Chưa nối được bảo hộ | J7: Có khả năng sử dụng trong thực hành nhưng cần minh chứng | K7: Mô hình còn được dùng không; số học phần/lượt SV; chi phí mua ngoài thay thế; có tính mới kỹ thuật không | L7: Phạm Viết Xuân; Khoa Ô tô; Phòng Đào tạo/KHCN | M7: Case đo training value và nguyên nhân không bảo hộ.

Sheet 20_METHODS_REVISION
A1: PHƯƠNG PHÁP NGHIÊN CỨU ĐỀ XUẤT – BẢN CHỐT KHÔNG KHẢO SÁT ĐỊNH LƯỢNG
A3: Thành phần | B3: Nội dung | C3: Dữ liệu | D3: Đơn vị phân tích | E3: Đầu ra | F3: Ghi chú
A4: 1. Phân tích tài liệu và pháp lý | B4: Phân tích pháp luật hiện hành, Quy chế KHCN 2021, Quy chế quản trị TSTT ban hành theo QĐ 217/QĐ-ĐHTĐ ngày 21/11/2024, hồ sơ đề tài và danh mục SHTT. | C4: Văn bản pháp luật; quy chế; quyết định; hồ sơ 2021-2025 | D4: Quy định/điều khoản | E4: Ma trận chuẩn quản trị | F4: Phân tầng chuẩn đối sánh: pháp luật quốc gia → quy chế nội bộ có hiệu lực → bằng chứng thực tiễn.
A5: 2. IP portfolio audit | B5: Kiểm kê Project→Output→IP potential→Protection→Utilization. | C5: 38 đề tài; 90 đầu ra; danh mục SHTT | D5: Đề tài/đầu ra/TSTT | E5: Cơ cấu, IP funnel, gap | F5: Không gọi mọi đầu ra là đối tượng bảo hộ.
A6: 3. Compliance/process gap analysis | B6: Đối sánh 'quy định phải làm' với 'bằng chứng thực tế có thể truy vết'. | C6: Legal-practice matrix + hồ sơ xác minh | D6: Khâu quy trình | E6: Documentation gap vs activity gap | F6: Không suy từ thiếu hồ sơ thành thiếu hoạt động.
A7: 4. Multiple case study / process tracing | B7: Tái dựng timeline và cơ chế ra quyết định ở 5-6 case điển hình. | C7: Quế hoa, tinh dầu bưởi, xà phòng, cồn, viên ngậm, panel ô tô | D7: Case/TSTT | E7: Cơ chế tạo lập-bảo hộ-khai thác | F7: Chọn case theo logic khác biệt, không nhằm đại diện thống kê.
A8: 5. Phỏng vấn bán cấu trúc | B8: 5-7 người để xác minh quy trình thực tế, bottleneck và nguyên nhân. | C8: Phòng KHCN, chủ nhiệm/tác giả, lãnh đạo/chuyên gia | D8: Người cung cấp thông tin/case | E8: Giải thích nguyên nhân và process map | F8: Không xử lý như khảo sát định lượng; không cần SPSS/SEM.
A9: 6. Phương pháp chuyên gia | B9: Thẩm định bộ tiêu chí ưu tiên IP, giải pháp và KPI. | C9: 3-5 chuyên gia phù hợp | D9: Giải pháp/tiêu chí | E9: Tính phù hợp, khả thi, rủi ro | F9: Có thể lồng với phỏng vấn chuyên gia; không nhất thiết AHP nếu đề tài muốn gọn.
A10: 7. Thống kê mô tả | B10: Tính số lượng, cơ cấu, tỷ lệ theo năm, đơn vị, strategic cluster và trạng thái vòng đời. | C10: Master Dataset | D10: Dòng dữ liệu | E10: Bảng/biểu đồ thực trạng | F10: Chỉ tính conversion rate khi mẫu số và trạng thái được xác định đáng tin cậy.

Sheet 21_CHAPTER2_BLUEPRINT
A1: CHƯƠNG 2 – THỰC TRẠNG QUẢN LÝ QUYỀN SHTT TẠI TRƯỜNG ĐẠI HỌC THÀNH ĐÔ
A3: Mục | B3: Tên mục đề xuất | C3: Câu hỏi phải trả lời | D3: Dữ liệu sử dụng | E3: Bảng/biểu đồ chính | F3: Phát hiện dự kiến | G3: Mức kết luận cho phép | H3: Ghi chú viết
A4: 2.1 | B4: Khái quát bối cảnh quản lý KHCN và SHTT của Trường | C4: Hệ thống văn bản, chủ thể và phạm vi quản lý TSTT của Trường được thiết kế như thế nào? | D4: QĐ 213/QĐ-ĐHTĐ năm 2021; QĐ 217/QĐ-ĐHTĐ ngày 21/11/2024; hồ sơ đề tài | E4: Bảng 2.1 – Hệ thống văn bản và chức năng quản trị SHTT | F4: Từ 21/11/2024 Trường có Quy chế chuyên biệt về quản trị TSTT bên cạnh Quy chế KHCN 2021. | G4: Mô tả thể chế; chưa đánh giá hiệu quả ở mục này. | H4: Viết ngắn, làm nền cho các mục sau.
A5: 2.2 | B5: Năng lực tạo ra kết quả KHCN và TSTT tiềm năng | C5: Giai đoạn 2021–2025 Trường tạo ra bao nhiêu đề tài, đầu ra và nhóm tài sản có tiềm năng quản trị IP? | D5: 01_PROJECT_ALL; 02_OUTPUT_ALL; 03_IP_PRIORITY_ALL | E5: Bảng 2.2 – Đề tài/đầu ra theo năm; Hình 2.1 – Output→IP priority funnel | F5: 38 đề tài được kiểm kê, 90 dòng đầu ra; 26 đầu ra cần quản trị IP sâu hơn, trong đó 15 mức ưu tiên cao. | G5: Chỉ gọi là 'đầu ra cần quản trị/sàng lọc IP', không gọi là 26 đối tượng đủ điều kiện bảo hộ. | H5: Phân biệt rõ output và legally protectable IP.
A6: 2.3 | B6: Cơ cấu TSTT và văn bằng/đơn SHTT của Trường | C6: Portfolio SHTT trực tiếp của ĐHTĐ có cơ cấu ra sao theo loại quyền và trạng thái? | D6: 13B_PROTECTION_FULL; danh sách SHTT do Trường cung cấp | E6: Bảng 2.3 – Cơ cấu portfolio; Hình 2.2 – Cơ cấu quyền theo loại hình | F6: Có 12 đối tượng ĐHTĐ sở hữu/đồng sở hữu trong danh sách nguồn; 11 thuộc 2021–2025; 9 có số đăng ký/văn bằng/ký hiệu, 1 ở trạng thái tiếp nhận đơn, 1 sáng chế 2025 chưa có số trong danh sách. | G6: Không gộp tài sản UNIGO/cá nhân vào portfolio trực tiếp ĐHTĐ; không mặc nhiên coi mục không có số là đã cấp. | H6: Đây là phần thống kê quyền đã quan sát được.
A7: 2.4 | B7: Thực trạng nhận diện, xác lập và bảo vệ quyền SHTT | C7: Quy trình chính thức yêu cầu gì và hồ sơ thực tế cho phép truy vết đến đâu? | D7: 17_LEGAL_PRACTICE_MATRIX; 11_DATA_REQUEST; 16_VERIFICATION_FINDINGS | E7: Bảng 2.4 – Normative requirement vs evidence; Hình 2.3 – Process traceability gap | F7: Có quy định về nhận diện/kê khai, công bố trước bảo hộ và quy trình đăng ký; nhưng chưa có bằng chứng tài liệu hóa disclosure và screening trong bộ hồ sơ hiện có. | G7: Kết luận về 'documentation gap'; chỉ nâng lên 'activity gap' nếu phỏng vấn xác nhận hoạt động thực tế không diễn ra. | H7: Đây là mục trung tâm của chương.
A8: 2.5 | B8: Thực trạng ứng dụng, chuyển giao và thương mại hóa | C8: Các kết quả/TSTT đã được sử dụng hay khai thác như thế nào và bằng chứng ở mức nào? | D8: 02_OUTPUT_ALL; 05_UTIL_VALUE; hồ sơ nghiệm thu; 17_LEGAL_PRACTICE_MATRIX | E8: Bảng 2.5 – Dấu hiệu ứng dụng; Hình 2.4 – Protection→Use evidence ladder | F8: Hồ sơ có 25 dòng đầu ra ghi dấu hiệu ứng dụng và 18/38 đề tài có ít nhất một dấu hiệu ứng dụng; tuy nhiên chưa có hồ sơ hợp đồng chuyển giao/cấp phép/thương mại hóa trong bộ dữ liệu hiện có. | G8: Không gọi dấu hiệu ứng dụng là commercialization; không tính doanh thu nếu không có chứng từ. | H8: Tách application, internal use, transfer, commercialization.
A9: 2.6 | B9: Phân tích các trường hợp điển hình theo chuỗi hình thành–bảo hộ–khai thác | C9: Tại sao có tài sản đi từ nghiên cứu tới bảo hộ, trong khi tài sản khác dừng ở prototype/quy trình? | D9: 19_CASE_TRACE; 18_INTERVIEW_GUIDE; 14_PROJECT_PROTECTION_LINK | E9: Bảng 2.6 – Timeline 6 case; Hình 2.5 – Case comparison matrix | F9: Tinh dầu vỏ bưởi và Quế hoa là hai case có liên kết đề tài↔bảo hộ mạnh; xà phòng/cồn/viên ngậm/panel là case so sánh để nhận diện bottleneck. | G9: Kết luận cơ chế chỉ sau khi có phỏng vấn xác minh. | H9: Dùng process tracing, không đại diện thống kê.
A10: 2.7 | B10: Đối sánh pháp luật/quy chế với thực tiễn quản trị | C10: Khoảng cách nào là thể chế, quy trình, dữ liệu hay thực thi? | D10: 17_LEGAL_PRACTICE_MATRIX; QĐ 213; QĐ 217 | E10: Bảng 2.7 – Gap matrix xếp hạng rủi ro | F10: Ba gap nổi bật: disclosure/identification, screening/decision documentation, transfer/commercialization evidence; thêm gap về lifecycle database. | G10: Phân biệt documentation gap và activity gap. | H10: Nên xếp rủi ro Rất cao/Cao/Trung bình.
A11: 2.8 | B11: Đánh giá chung về hiệu quả quản lý quyền SHTT | C11: Điểm mạnh, hạn chế và nguyên nhân cốt lõi là gì? | D11: Tổng hợp 2.1–2.7 + phỏng vấn/chuyên gia | E11: Bảng 2.8 – Strengths/weaknesses/causes; Hình 2.6 – Bottleneck map | F11: Điểm mạnh: đã có khung thể chế và portfolio quyền; hạn chế chính dự kiến nằm ở khả năng truy vết quy trình và bằng chứng khai thác giá trị. | G11: Nguyên nhân chỉ viết khi có dữ liệu phỏng vấn/chuyên gia; chưa suy đoán từ hồ sơ. | H11: Là cầu nối sang Chương 3 giải pháp.

Sheet 22_TABLE_FIGURE_PLAN
A1: ID | B1: Loại | C1: Tên đề xuất | D1: Nguồn dữ liệu | E1: Biến/công thức | F1: Thông điệp chính | G1: Mức ưu tiên
A2: B2.1 | B2: Bảng | C2: Hệ thống văn bản nội bộ điều chỉnh quản lý SHTT | D2: QĐ 213; QĐ 217 | E2: Văn bản – phạm vi – chủ thể – nội dung – hiệu lực | F2: Khung thể chế đã chuyển từ quy định SHTT trong Quy chế KHCN sang Quy chế quản trị TSTT chuyên biệt từ 21/11/2024. | G2: Bắt buộc
A3: B2.2 | B3: Bảng | C3: Số đề tài và đầu ra KHCN theo năm 2021–2025 | D3: 01_PROJECT_ALL; 02_OUTPUT_ALL | E3: COUNT theo năm | F3: Cho thấy quy mô nguồn tạo tri thức trước khi nói về bảo hộ. | G3: Bắt buộc
A4: H2.1 | B4: Biểu đồ | C4: Phễu kết quả KHCN → đầu ra ưu tiên IP | D4: 02_OUTPUT_ALL | E4: 90 output → 26 medium/high → 15 high | F4: Minh họa chênh lệch giữa tổng output và nhóm cần quản trị IP sâu. | G4: Bắt buộc
A5: B2.3 | B5: Bảng | C5: Danh mục và cơ cấu TSTT trực tiếp của ĐHTĐ | D5: 13B_PROTECTION_FULL | E5: Lọc Chủ sở hữu có ĐHTĐ | F5: Phân biệt rõ quyền của Trường với tài sản hệ sinh thái/cá nhân. | G5: Bắt buộc
A6: H2.2 | B6: Biểu đồ | C6: Cơ cấu portfolio SHTT theo loại hình | D6: 13B_PROTECTION_FULL | E6: COUNT QTG/Nhãn hiệu/KDCN/Sáng chế | F6: Portfolio hiện quan sát được thiên về thương hiệu/KDCN bên cạnh tài sản công nghệ. | G6: Nên có
A7: B2.4 | B7: Bảng | C7: Đối sánh yêu cầu quản trị với bằng chứng thực tế | D7: 17_LEGAL_PRACTICE_MATRIX | E7: Chuẩn – evidence – gap – risk | F7: Bảng trung tâm chứng minh documentation/process gap. | G7: Bắt buộc
A8: H2.3 | B8: Sơ đồ | C8: Chuỗi quản trị và điểm đứt gãy khả năng truy vết | D8: 17_LEGAL_PRACTICE_MATRIX | E8: Research output→identify→screen→file→protect→use→commercialize | F8: Làm rõ 'có đầu ra và quyền nhưng thiếu hồ sơ trung gian'. | G8: Bắt buộc
A9: B2.5 | B9: Bảng | C9: Dấu hiệu ứng dụng của kết quả nghiên cứu | D9: 02_OUTPUT_ALL | E9: COUNT cột dấu hiệu ứng dụng; phân loại loại đầu ra | F9: Ứng dụng tồn tại ở mức dấu hiệu nhưng chưa tương đương chuyển giao/thương mại hóa. | G9: Bắt buộc
A10: B2.6 | B10: Bảng | C10: So sánh 6 case process tracing | D10: 19_CASE_TRACE | E10: Timeline từng case | F10: Giải thích cơ chế khác biệt giữa case bảo hộ và chưa nối được bảo hộ. | G10: Bắt buộc
A11: H2.4 | B11: Biểu đồ | C11: Ma trận mức ưu tiên IP × bằng chứng ứng dụng | D11: 03_IP_PRIORITY_ALL; 02_OUTPUT_ALL | E11: Priority vs application evidence | F11: Chọn tài sản ưu tiên cho giải pháp quản trị sau này. | G11: Nên có
A12: B2.7 | B12: Bảng | C12: Tổng hợp khoảng cách và mức rủi ro | D12: 17_LEGAL_PRACTICE_MATRIX | E12: COUNT theo gap type/risk | F12: Ưu tiên giải pháp theo mức độ rủi ro quản trị. | G12: Bắt buộc

Sheet 23_DRAFT_2_1_2_4
A1: BẢN NHÁP NỘI DUNG CHƯƠNG 2 – 2.1 ĐẾN 2.4
A3: Mục | B3: Đoạn | C3: Nội dung nháp | D3: Nguồn phải trích khi viết báo cáo
A4: 2.1 | B4: 1 | C4: Giai đoạn nghiên cứu cho thấy quản lý quyền sở hữu trí tuệ tại Trường Đại học Thành Đô được đặt trong hai lớp thể chế nội bộ. Quy chế hoạt động khoa học và công nghệ năm 2021 đã dành Chương VI cho sở hữu trí tuệ và chuyển giao công nghệ, trong đó xác định quyền SHTT đối với kết quả đề tài thuộc Trường, quy định trách nhiệm của tác giả, quyền nộp đơn, bảo mật và cơ chế chuyển giao. Từ ngày 21/11/2024, Trường ban hành Quy chế quản trị Tài sản trí tuệ theo QĐ 217/QĐ-ĐHTĐ, mở rộng phạm vi quản trị từ khâu tạo lập, xác lập, bảo vệ đến khai thác thương mại TSTT. | D4: QĐ 213/QĐ-ĐHTĐ 2021; QĐ 217/QĐ-ĐHTĐ ngày 21/11/2024
A5: 2.1 | B5: 2 | C5: So với Quy chế KHCN 2021, Quy chế quản trị TSTT năm 2024 có phạm vi tài sản rộng hơn, bao gồm không chỉ sáng chế, kiểu dáng và nhãn hiệu mà còn công bố nghiên cứu, dữ liệu, học liệu, phần mềm, thông tin kỹ thuật, bí quyết, hình ảnh và thương hiệu của Trường. Điều này tạo cơ sở để đánh giá TSTT của Trường theo logic portfolio thay vì chỉ thống kê văn bằng bảo hộ. | D5: QC quản trị TSTT – Điều 2-3
A6: 2.2 | B6: 1 | C6: Trên cơ sở kiểm kê hồ sơ đề tài cấp cơ sở giai đoạn 2021–2025, nghiên cứu chuẩn hóa được 38 đề tài và bóc tách thành 90 dòng đầu ra. Các đầu ra không chỉ gồm báo cáo và bài báo mà còn có mô hình, bộ mẫu, tiêu bản, quy trình, công thức, sản phẩm thử nghiệm và các giải pháp ứng dụng. Cách tiếp cận này cho phép tách rõ 'nhiệm vụ nghiên cứu' khỏi 'tài sản/kết quả do nhiệm vụ tạo ra'. | D6: Tổng hợp đề tài KHCN cấp cơ sở của GV 2021-2025; Master Dataset
A7: 2.2 | B7: 2 | C7: Từ 90 đầu ra, 26 đầu ra được xếp vào nhóm cần quản trị hoặc sàng lọc IP sâu hơn, trong đó 15 đầu ra ở mức ưu tiên cao. Nhóm ưu tiên cao chủ yếu là prototype, sản phẩm vật chất, công thức, quy trình và kết quả có dấu hiệu liên quan đến bảo hộ hoặc khai thác. Con số này không được hiểu là 26 đối tượng chắc chắn đáp ứng điều kiện bảo hộ, mà là danh mục ứng viên cần được đánh giá chuyên môn và pháp lý. | D7: 02_OUTPUT_ALL; 03_IP_PRIORITY_ALL
A8: 2.3 | B8: 1 | C8: Danh sách SHTT do Trường cung cấp cho thấy 16 đối tượng trong toàn bộ nguồn, nhưng sau khi phân loại theo chủ sở hữu chỉ có 12 đối tượng mà ĐHTĐ là chủ sở hữu hoặc đồng sở hữu. Trong số này, 11 đối tượng thuộc giai đoạn 2021–2025. Nghiên cứu không gộp các tài sản do Công ty/Trường UNIGO hoặc cá nhân sở hữu vào portfolio trực tiếp của ĐHTĐ. | D8: Danh sách thống kê văn bằng SHTT do Trường cung cấp; 13B_PROTECTION_FULL
A9: 2.3 | B9: 2 | C9: Trong 11 đối tượng trực tiếp của ĐHTĐ giai đoạn 2021–2025, 9 đối tượng có số đăng ký, văn bằng hoặc ký mã hiệu trong danh sách nguồn; nhãn hiệu Double2n được ghi ở trạng thái 'Tiếp nhận đơn', còn sáng chế liên quan đến lá Quế hoa năm 2025 chưa thể hiện số đơn/văn bằng trong danh sách. Vì vậy, hai trường hợp sau không được nghiên cứu mặc nhiên xem là quyền đã được cấp. | D9: 13B_PROTECTION_FULL
A10: 2.4 | B10: 1 | C10: Đối sánh giữa quy chế và hồ sơ thực tế cho thấy khoảng cách đáng chú ý nhất không nằm ở việc Trường hoàn toàn thiếu quy định, mà ở khả năng truy vết quá trình thực thi. Quy chế quản trị TSTT năm 2024 giao Phòng KHCN xây dựng quy trình, biểu mẫu ghi nhận/khai báo, nhận diện TSTT mới, lập hồ sơ thống kê và theo dõi tập trung; tuy nhiên trong bộ hồ sơ hiện có chưa ghi nhận phiếu khai báo, biên bản nhận diện hoặc sổ/CSDL disclosure tương đương. | D10: QĐ 217/QĐ-ĐHTĐ; 16_VERIFICATION_FINDINGS
A11: 2.4 | B11: 2 | C11: Tương tự, nghiên cứu chưa ghi nhận hồ sơ sàng lọc hoặc tra cứu khả năng bảo hộ. Trong bối cảnh một số đề tài đồng thời có bài báo, công thức/quy trình mới và dự kiến đăng ký giải pháp hữu ích, việc thiếu dấu vết sàng lọc khiến nghiên cứu không thể xác định tiêu chí lựa chọn đối tượng, loại quyền và thời điểm quyết định bảo hộ. Do đó, phát hiện hiện tại nên được diễn giải là 'khoảng trống về tài liệu hóa quyết định và khả năng truy vết quy trình', chưa phải kết luận rằng hoạt động sàng lọc không từng diễn ra. | D11: QĐ 217/QĐ-ĐHTĐ; hồ sơ đề tài 2025; 16_VERIFICATION_FINDINGS
A12: 2.4 | B12: 3 | C12: Quy chế KHCN 2021 đã quy định một quy trình đăng ký quyền SHTT từ khâu tác giả nộp đơn tại Phòng KHCN, kiểm tra hình thức, trình Hiệu trưởng ký đến nộp hồ sơ và lệ phí tại cơ quan nhà nước. Việc danh mục hiện có đã xuất hiện các đăng ký quyền tác giả, nhãn hiệu, kiểu dáng công nghiệp và sáng chế cho thấy hoạt động xác lập quyền đã tạo ra kết quả thực tế. Tuy nhiên, do thiếu dữ liệu trung gian về thời điểm tiếp nhận, sàng lọc, quyết định và nộp đơn, chưa thể tính các chỉ số như Time-to-IP hoặc tỷ lệ chuyển đổi từ TSTT tiềm năng sang đơn đăng ký. | D12: QĐ 213/QĐ-ĐHTĐ 2021; danh sách SHTT; Master Dataset

Sheet TPL_04_PROTECTION
A1: Protection_ID | B1: IP_ID | C1: Loại quyền/hồ sơ | D1: Ngày phát sinh kết quả | E1: Ngày khai báo IP | F1: Ngày sàng lọc | G1: Ngày nộp đơn | H1: Số đơn | I1: Cơ quan nhận đơn | J1: Chủ đơn | K1: Tình trạng | L1: Ngày cấp | M1: Số văn bằng | N1: Chi phí bảo hộ_VND | O1: Time_to_IP_days | P1: Nguồn bằng chứng | Q1: Ghi chú
A2: PR2025-06-A | B2: IP2025-06-A | C2: Giải pháp hữu ích (dự kiến) | J2: Trường/đồng sở hữu - chưa xác minh | K2: Dự kiến đăng ký | O2: =IF(OR(D2="",G2=""),"",G2-D2) | P2: Tổng hợp đề tài KHCN cấp cơ sở của GV 2021-2025.pdf | Q2: Chưa có bằng chứng trong bộ hồ sơ hiện trích xuất về việc đã nộp đơn.
A3: PR2025-07-A | B3: IP2025-07-A | C3: Giải pháp hữu ích (dự kiến) | J3: Trường/đồng sở hữu - chưa xác minh | K3: Dự kiến đăng ký | O3: =IF(OR(D3="",G3=""),"",G3-D3) | P3: Tổng hợp đề tài KHCN cấp cơ sở của GV 2021-2025.pdf | Q3: Chưa có bằng chứng trong bộ hồ sơ hiện trích xuất về việc đã nộp đơn.
O4: =IF(OR(D4="",G4=""),"",G4-D4)
O5: =IF(OR(D5="",G5=""),"",G5-D5)
O6: =IF(OR(D6="",G6=""),"",G6-D6)
O7: =IF(OR(D7="",G7=""),"",G7-D7)
O8: =IF(OR(D8="",G8=""),"",G8-D8)
O9: =IF(OR(D9="",G9=""),"",G9-D9)
O10: =IF(OR(D10="",G10=""),"",G10-D10)
O11: =IF(OR(D11="",G11=""),"",G11-D11)
O12: =IF(OR(D12="",G12=""),"",G12-D12)
O13: =IF(OR(D13="",G13=""),"",G13-D13)
O14: =IF(OR(D14="",G14=""),"",G14-D14)
O15: =IF(OR(D15="",G15=""),"",G15-D15)
... O1000: =IF(OR(D1000="",G1000=""),"",G1000-D1000)

Sheet TPL_05_UTIL_VALUE
A1: Util_ID | B1: IP_ID | C1: Project_ID | D1: Hình thức sử dụng | E1: Mức sử dụng (0-7) | F1: Đơn vị sử dụng | G1: Đối tác | H1: Bằng chứng sử dụng | I1: Ngày bắt đầu | J1: Doanh thu_VND | K1: Tiết kiệm chi phí_VND | L1: Số người dùng/đối tượng hưởng lợi | M1: Giá trị khoa học (0-3) | N1: Giá trị đào tạo (0-3) | O1: Giá trị công nghệ (0-3) | P1: Giá trị kinh tế (0-3) | Q1: Giá trị chiến lược (0-3) | R1: Tình trạng định giá | S1: Nguồn | T1: Ghi chú
A2: U2023-08-A | B2: IP2023-08-A | C2: P2023-08 | D2: Chuyển giao nội bộ cho Trường để thương mại hóa | E2: 4 | F2: Trường Đại học Thành Đô | G2: Chưa xác minh | H2: Dòng sản phẩm nghiệm thu ghi 'Sản phẩm chuyển giao công nghệ cho trường ĐHTĐ thương mại hóa' | R2: Chưa định giá | S2: Tổng hợp đề tài KHCN cấp cơ sở của GV 2021-2025.pdf | T2: Chưa đủ bằng chứng để kết luận đã có hợp đồng chuyển giao ra bên ngoài hoặc phát sinh doanh thu.

Sheet ZZ_CU_01_PROJECT
A1: Project_ID | B1: Năm | C1: Mã đề tài | D1: Tên đề tài | E1: Cấp đề tài | F1: Chủ nhiệm | G1: Đơn vị chủ trì | H1: Nhóm ngành chuẩn hóa | I1: Strategic_Cluster | J1: Ngày nghiệm thu | K1: Xếp loại | L1: Kinh phí_VND | M1: Số thành viên | N1: Có DN tham gia? | O1: Có SV tham gia? | P1: Số đầu ra (formula) | Q1: Nguồn hồ sơ | R1: Ghi chú xác minh
A2: P2022-37 | B2: 2022 | C2: 37-2022/KHCN | D2: Tính toán thiết kế panel kiểm tra và sửa chữa hệ thống khởi động điện trên ô tô | E2: Cơ sở | F2: Phạm Viết Xuân | G2: Khoa CNKT Ô tô | H2: Kỹ thuật ô tô | I2: Smart Mobility | J2: 44874 | K2: Đạt | L2: 5000000 | M2: 1 | N2: Chưa xác minh | O2: Chưa xác minh | P2: =COUNTIF(ZZ_CU_02_OUTPUT!$B:$B,A2) -> 2 | Q2: Tổng hợp đề tài KHCN cấp cơ sở của GV 2021-2025.pdf, tr.3
A3: P2022-39 | B3: 2022 | C3: 39-2022/KHCN | D3: Nghiên cứu chế tạo vật liệu cầm máu trên cơ sở chitosan và cao nhọ nồi | E3: Cơ sở | F3: Nguyễn Ngọc Linh | G3: Khoa Dược | H3: Dược/Vật liệu y sinh | I3: Wellness & Care | J3: 44875 | K3: Đạt | L3: 29000000 | M3: 5 | N3: Chưa xác minh | O3: Chưa xác minh | P3: =COUNTIF(ZZ_CU_02_OUTPUT!$B:$B,A3) -> 2 | Q3: Tổng hợp đề tài KHCN cấp cơ sở của GV 2021-2025.pdf, tr.3
A4: P2022-40 | B4: 2022 | C4: 40-2022/KHCN | D4: Nghiên cứu xây dựng bộ mẫu dược liệu áp dụng giảng dạy tại Trường Đại học Thành Đô | E4: Cơ sở | F4: Lê Văn Tuyến | G4: Khoa Dược | H4: Dược/Giáo dục dược | I4: Wellness & Care | J4: 44875 | K4: Đạt | L4: 50000000 | M4: 7 | N4: Chưa xác minh | O4: Chưa xác minh | P4: =COUNTIF(ZZ_CU_02_OUTPUT!$B:$B,A4) -> 2 | Q4: Tổng hợp đề tài KHCN cấp cơ sở của GV 2021-2025.pdf, tr.3
A5: P2023-08 | B5: 2023 | C5: 08-2023/KHCN | D5: Ứng dụng mô hình hợp tác giáo dục giữa Nhà trường - Doanh nghiệp trong nghiên cứu chiết xuất tinh dầu từ vỏ bưởi | E5: Cơ sở | F5: Phan Thị Thanh Thảo | G5: Viện REK | H5: Dược/Hợp tác ĐH-DN | I5: Wellness & Care | J5: 45243 | K5: Tốt | L5: 50000000 | M5: 8 | N5: Có dấu hiệu | O5: Chưa xác minh | P5: =COUNTIF(ZZ_CU_02_OUTPUT!$B:$B,A5) -> 2 | Q5: Tổng hợp đề tài KHCN cấp cơ sở của GV 2021-2025.pdf | R5: Sản phẩm ghi 'chuyển giao công nghệ cho trường ĐHTĐ thương mại hóa'; cần xác minh nghĩa và chứng từ.
A6: P2024-06 | B6: 2024 | C6: 06-2024/KHCN | D6: Nghiên cứu ứng dụng quy trình sản xuất xà phòng tảo biển hữu cơ | E6: Cơ sở | F6: Nguyễn Ngọc Linh | G6: Khoa Dược | H6: Dược/Mỹ phẩm | I6: Wellness & Care | J6: 45611 | K6: Tốt | L6: 58000000 | M6: 4 | N6: Chưa xác minh | O6: Chưa xác minh | P6: =COUNTIF(ZZ_CU_02_OUTPUT!$B:$B,A6) -> 4 | Q6: Tổng hợp đề tài KHCN cấp cơ sở của GV 2021-2025.pdf
A7: P2025-06 | B7: 2025 | C7: 06-2025/KHCN | D7: Nghiên cứu bào chế cồn thuốc xoa bóp hỗ trợ giảm đau nhức xương khớp quy mô phòng thí nghiệm | E7: Cơ sở | F7: Nguyễn Đăng Việt | G7: Viện Y-Dược | H7: Dược/Bào chế | I7: Wellness & Care | J7: 46016 | K7: Tốt | L7: 30000000 | M7: 4 | N7: Chưa xác minh | O7: Chưa xác minh | P7: =COUNTIF(ZZ_CU_02_OUTPUT!$B:$B,A7) -> 3 | Q7: Tổng hợp đề tài KHCN cấp cơ sở của GV 2021-2025.pdf | R7: Kinh phí còn kèm tính giờ NCKH theo hồ sơ.
A8: P2025-07 | B8: 2025 | C8: 07-2025/KHCN | D8: Nghiên cứu bào chế viên ngậm hỗ trợ giảm ho từ Gừng và Húng chanh | E8: Cơ sở | F8: Ngô Thị Thu | G8: Viện Y-Dược | H8: Dược/Bào chế | I8: Wellness & Care | J8: 46016 | K8: Tốt | L8: 30000000 | M8: 4 | N8: Chưa xác minh | O8: Chưa xác minh | P8: =COUNTIF(ZZ_CU_02_OUTPUT!$B:$B,A8) -> 4 | Q8: Tổng hợp đề tài KHCN cấp cơ sở của GV 2021-2025.pdf | R8: Kinh phí còn kèm tính giờ NCKH theo hồ sơ.

Sheet ZZ_CU_02_OUTPUT
A1: Output_ID | B1: Project_ID | C1: Năm | D1: Tên đầu ra | E1: Loại đầu ra | F1: Số lượng | G1: Đơn vị tính | H1: Tác giả/chủ trì liên quan | I1: Đã công bố? | J1: DOI/Link/Mã | K1: Dấu hiệu TSTT? | L1: Nhóm TSTT sơ bộ | M1: Khả năng tạo giá trị | N1: Bằng chứng nguồn | O1: Mức tin cậy | P1: Ghi chú
A2: O2022-37-01 | B2: P2022-37 | C2: 2022 | D2: Báo cáo tổng kết đề tài | E2: Báo cáo nghiên cứu | F2: 1 | G2: báo cáo | H2: Phạm Viết Xuân | I2: Có nội bộ | K2: Có | L2: Tác phẩm học thuật | M2: Khoa học/đào tạo | N2: Tổng hợp đề tài KHCN cấp cơ sở của GV 2021-2025.pdf, tr.3 | O2: Cao
A3: O2022-37-02 | B3: P2022-37 | C3: 2022 | D3: Mô hình kiểm tra và sửa chữa hệ thống khởi động điện trên ô tô | E3: Mô hình/prototype | F3: 1 | G3: mô hình | H3: Phạm Viết Xuân | I3: Chưa xác minh | K3: Có | L3: Giải pháp kỹ thuật/thiết kế - cần sàng lọc | M3: Công nghệ/đào tạo | N3: Tổng hợp đề tài KHCN cấp cơ sở của GV 2021-2025.pdf, tr.3 | O3: Cao | P3: Chưa đủ dữ liệu để kết luận sáng chế/KDCN.
A4: O2022-39-01 | B4: P2022-39 | C4: 2022 | D4: Báo cáo tổng kết đề tài | E4: Báo cáo nghiên cứu | F4: 1 | G4: báo cáo | H4: Nhóm đề tài | I4: Có nội bộ | K4: Có | L4: Tác phẩm học thuật | M4: Khoa học | N4: Tổng hợp đề tài KHCN cấp cơ sở của GV 2021-2025.pdf, tr.3 | O4: Cao
A5: O2022-39-02 | B5: P2022-39 | C5: 2022 | D5: Sản phẩm cầm máu ở dạng màng | E5: Sản phẩm/prototype | F5: 1 | G5: sản phẩm | H5: Nhóm đề tài | I5: Chưa xác minh | K5: Có | L5: Giải pháp kỹ thuật/know-how - cần sàng lọc | M5: Công nghệ/y tế | N5: Tổng hợp đề tài KHCN cấp cơ sở của GV 2021-2025.pdf, tr.3 | O5: Cao
A6: O2022-40-01 | B6: P2022-40 | C6: 2022 | D6: Báo cáo tổng kết đề tài | E6: Báo cáo nghiên cứu | F6: 1 | G6: báo cáo | H6: Nhóm đề tài | I6: Có nội bộ | K6: Có | L6: Tác phẩm học thuật | M6: Khoa học | N6: Tổng hợp đề tài KHCN cấp cơ sở của GV 2021-2025.pdf, tr.3 | O6: Cao
A7: O2022-40-02 | B7: P2022-40 | C7: 2022 | D7: Bộ mẫu cây thuốc | E7: Bộ mẫu/collection | F7: 1 | G7: bộ | H7: Nhóm đề tài | I7: Chưa xác minh | K7: Có | L7: TSTT học thuật/collection - hình thức quyền cần xác minh | M7: Đào tạo | N7: Tổng hợp đề tài KHCN cấp cơ sở của GV 2021-2025.pdf, tr.3 | O7: Cao
A8: O2023-08-01 | B8: P2023-08 | C8: 2023 | D8: 01 bài báo khoa học đăng tạp chí có chỉ số ISSN | E8: Bài báo | F8: 1 | G8: bài | H8: Nhóm đề tài | I8: Có | K8: Có | L8: Tác phẩm học thuật | M8: Khoa học/uy tín | N8: Tổng hợp đề tài KHCN cấp cơ sở của GV 2021-2025.pdf | O8: Cao | P8: Cần nối với danh mục bài báo để xác định tên/DOI.
A9: O2023-08-02 | B9: P2023-08 | C9: 2023 | D9: Tinh dầu Citrus grandis (L.) Osbeck 100ml | E9: Sản phẩm/prototype | F9: 1 | G9: mẫu 100ml | H9: Nhóm đề tài | I9: Chưa xác minh | K9: Có | L9: Giải pháp kỹ thuật/know-how - cần sàng lọc | M9: Công nghệ/thương mại | N9: Tổng hợp đề tài KHCN cấp cơ sở của GV 2021-2025.pdf | O9: Cao | P9: Có ghi sản phẩm chuyển giao cho trường thương mại hóa.
A10: O2024-06-01 | B10: P2024-06 | C10: 2024 | D10: 01 bài báo khoa học đăng Tạp chí NCKH&PT Trường Đại học Thành Đô | E10: Bài báo | F10: 1 | G10: bài | H10: Nhóm đề tài | I10: Có | K10: Có | L10: Tác phẩm học thuật | M10: Khoa học/uy tín | N10: Tổng hợp đề tài KHCN cấp cơ sở của GV 2021-2025.pdf | O10: Cao
A11: O2024-06-02 | B11: P2024-06 | C11: 2024 | D11: Bánh xà phòng hữu cơ tảo biển 60 gam | E11: Sản phẩm/prototype | F11: 200 | G11: bánh | H11: Nhóm đề tài | I11: Chưa xác minh | K11: Có | L11: Sản phẩm hiện thân của TSTT | M11: Công nghệ/thị trường | N11: Tổng hợp đề tài KHCN cấp cơ sở của GV 2021-2025.pdf | O11: Cao | P11: Không tách thành quyền riêng nếu không có thiết kế/nhãn hiệu độc lập.
A12: O2024-06-03 | B12: P2024-06 | C12: 2024 | D12: Quy trình sản xuất và công thức xà phòng hữu cơ tảo biển | E12: Quy trình/công thức | F12: 1 | G12: bộ | H12: Nhóm đề tài | I12: Chưa xác minh | K12: Có | L12: Giải pháp kỹ thuật/know-how | M12: Công nghệ/thương mại | N12: Tổng hợp đề tài KHCN cấp cơ sở của GV 2021-2025.pdf | O12: Cao | P12: Đầu ra ưu tiên sàng lọc khả năng bảo hộ/bí mật kinh doanh.
A13: O2024-06-04 | B13: P2024-06 | C13: 2024 | D13: Báo cáo đề tài | E13: Báo cáo nghiên cứu | F13: 1 | G13: báo cáo | H13: Nhóm đề tài | I13: Có nội bộ | K13: Có | L13: Tác phẩm học thuật | M13: Khoa học | N13: Tổng hợp đề tài KHCN cấp cơ sở của GV 2021-2025.pdf | O13: Cao
A14: O2025-06-01 | B14: P2025-06 | C14: 2025 | D14: Bài đăng trên Tạp chí NCKH&PT | E14: Bài báo | F14: 1 | G14: bài | H14: Nhóm đề tài | I14: Có | K14: Có | L14: Tác phẩm học thuật | M14: Khoa học/uy tín | N14: Tổng hợp đề tài KHCN cấp cơ sở của GV 2021-2025.pdf | O14: Cao
A15: O2025-06-02 | B15: P2025-06 | C15: 2025 | D15: Công thức bào chế cồn thuốc xoa bóp hỗ trợ giảm đau nhức xương khớp | E15: Công thức/quy trình | F15: 1 | G15: công thức | H15: Nhóm đề tài | I15: Chưa xác minh | K15: Có | L15: Giải pháp hữu ích tiềm năng | M15: Công nghệ/thương mại | N15: Tổng hợp đề tài KHCN cấp cơ sở của GV 2021-2025.pdf | O15: Cao | P15: Hồ sơ ghi 'công thức mới, dự kiến đăng ký bằng độc quyền giải pháp hữu ích'.
A16: O2025-06-03 | B16: P2025-06 | C16: 2025 | D16: Cồn thuốc xoa bóp hỗ trợ giảm đau nhức xương khớp chai 50ml | E16: Sản phẩm/prototype | F16: 50 | G16: chai | H16: Nhóm đề tài | I16: Chưa xác minh | K16: Có | L16: Sản phẩm hiện thân của TSTT | M16: Công nghệ/thị trường | N16: Tổng hợp đề tài KHCN cấp cơ sở của GV 2021-2025.pdf | O16: Cao
A17: O2025-07-01 | B17: P2025-07 | C17: 2025 | D17: Báo cáo đề tài | E17: Báo cáo nghiên cứu | F17: 1 | G17: báo cáo | H17: Nhóm đề tài | I17: Có nội bộ | K17: Có | L17: Tác phẩm học thuật | M17: Khoa học | N17: Tổng hợp đề tài KHCN cấp cơ sở của GV 2021-2025.pdf | O17: Cao
A18: O2025-07-02 | B18: P2025-07 | C18: 2025 | D18: Bài báo đăng trên tạp chí tính điểm/chỉ số ISSN | E18: Bài báo | F18: 1 | G18: bài | H18: Nhóm đề tài | I18: Có | K18: Có | L18: Tác phẩm học thuật | M18: Khoa học/uy tín | N18: Tổng hợp đề tài KHCN cấp cơ sở của GV 2021-2025.pdf | O18: Cao
A19: O2025-07-03 | B19: P2025-07 | C19: 2025 | D19: Quy trình bào chế viên ngậm hỗ trợ giảm ho từ Gừng và Húng chanh | E19: Quy trình/công thức | F19: 1 | G19: quy trình | H19: Nhóm đề tài | I19: Chưa xác minh | K19: Có | L19: Giải pháp hữu ích tiềm năng | M19: Công nghệ/thương mại | N19: Tổng hợp đề tài KHCN cấp cơ sở của GV 2021-2025.pdf | O19: Cao | P19: Hồ sơ ghi 'quy trình mới, dự kiến đăng ký bằng độc quyền giải pháp hữu ích'.
A20: O2025-07-04 | B20: P2025-07 | C20: 2025 | D20: Sản phẩm bào chế viên ngậm hỗ trợ giảm ho từ Gừng và Húng chanh | E20: Sản phẩm/prototype | F20: 50 | G20: thanh/10 viên | H20: Nhóm đề tài | I20: Chưa xác minh | K20: Có | L20: Sản phẩm hiện thân của TSTT | M20: Công nghệ/thị trường | N20: Tổng hợp đề tài KHCN cấp cơ sở của GV 2021-2025.pdf | O20: Cao

Sheet ZZ_CU_03_IP_ASSET
A1: IP_ID | B1: Project_ID | C1: Output_ID chính | D1: Tên TSTT/cụm TSTT | E1: Nhóm TSTT | F1: Hình thức quyền dự kiến | G1: Chủ thể sáng tạo rõ? | H1: Chủ sở hữu rõ? | I1: Trường sở hữu/đồng sở hữu? | J1: Nguồn lực trường? | K1: Có đối tác ngoài trường? | L1: Đã được nhận diện chính thức? | M1: Đã sàng lọc khả năng bảo hộ? | N1: Mức tiềm năng bảo hộ (0-3) | O1: Mức tiềm năng ứng dụng (0-3) | P1: Rủi ro công bố trước bảo hộ | Q1: Tình trạng IP | R1: Mức tin cậy | S1: Bằng chứng | T1: Ghi chú chuyên gia
A2: IP2022-37-A | B2: P2022-37 | C2: O2022-37-02 | D2: Mô hình panel kiểm tra và sửa chữa hệ thống khởi động điện trên ô tô | E2: Công nghệ | F2: Chưa xác minh: sáng chế/GPHI/KDCN | G2: Có | H2: Có theo quy chế/hợp đồng - cần hồ sơ cụ thể | I2: Có khả năng | J2: Có khả năng | K2: Chưa xác minh | L2: Chưa xác minh | M2: Chưa xác minh | P2: Chưa xác minh | Q2: Tiềm năng | R2: Trung bình | S2: Sản phẩm nghiệm thu là mô hình | T2: Cần rà soát tính mới và phần hình dáng/kết cấu.
A3: IP2022-39-A | B3: P2022-39 | C3: O2022-39-02 | D3: Vật liệu/sản phẩm cầm máu trên cơ sở chitosan và cao nhọ nồi | E3: Công nghệ | F3: Chưa xác minh: sáng chế/GPHI/know-how | G3: Có | H3: Có theo quy chế/hợp đồng - cần hồ sơ cụ thể | I3: Có khả năng | J3: Có khả năng | K3: Chưa xác minh | L3: Chưa xác minh | M3: Chưa xác minh | P3: Chưa xác minh | Q3: Tiềm năng | R3: Trung bình | S3: Sản phẩm nghiệm thu dạng màng | T3: Ưu tiên tra cứu sáng chế và đánh giá novelty.
A4: IP2022-40-A | B4: P2022-40 | C4: O2022-40-02 | D4: Bộ mẫu cây thuốc phục vụ giảng dạy | E4: Học thuật/đào tạo | F4: Chưa xác minh: tác phẩm sưu tập/CSDL/quyền khác | G4: Có | H4: Chưa xác minh | I4: Có khả năng | J4: Có khả năng | K4: Chưa xác minh | L4: Chưa xác minh | M4: Chưa xác minh | P4: Thấp | Q4: Tiềm năng | R4: Trung bình | S4: Sản phẩm nghiệm thu là bộ mẫu cây thuốc | T4: Giá trị đào tạo có thể cao dù quyền độc quyền hạn chế.
A5: IP2023-08-A | B5: P2023-08 | C5: O2023-08-02 | D5: Tinh dầu Citrus grandis (L.) Osbeck và tri thức/quy trình liên quan | E5: Công nghệ | F5: Chưa xác minh: know-how/sáng chế/GPHI | G5: Có | H5: Chưa xác minh | I5: Có khả năng | J5: Có khả năng | K5: Có dấu hiệu hợp tác DN | L5: Có dấu hiệu qua hồ sơ | M5: Chưa xác minh | P5: Chưa xác minh | Q5: Có bằng chứng khai thác nội bộ | R5: Trung bình | S5: Hồ sơ ghi chuyển giao sản phẩm cho trường để thương mại hóa | T5: Cần làm rõ sản phẩm nào được chuyển giao, chủ sở hữu, doanh thu/hợp đồng.
A6: IP2024-06-A | B6: P2024-06 | C6: O2024-06-03 | D6: Quy trình sản xuất và công thức xà phòng hữu cơ tảo biển | E6: Công nghệ | F6: Sáng chế/GPHI hoặc bí mật kinh doanh - cần sàng lọc | G6: Có | H6: Có theo quy chế/hợp đồng - cần hồ sơ cụ thể | I6: Có khả năng | J6: Có khả năng | K6: Chưa xác minh | L6: Chưa xác minh | M6: Chưa xác minh | P6: Trung bình | Q6: Tiềm năng | R6: Cao | S6: Quy trình và công thức là sản phẩm nghiệm thu | T6: Ưu tiên sàng lọc trước công bố/tiếp thị.
A7: IP2025-06-A | B7: P2025-06 | C7: O2025-06-02 | D7: Công thức bào chế cồn thuốc xoa bóp hỗ trợ giảm đau nhức xương khớp | E7: Công nghệ | F7: Giải pháp hữu ích tiềm năng | G7: Có | H7: Có theo quy chế/hợp đồng - cần hồ sơ cụ thể | I7: Có khả năng | J7: Có khả năng | K7: Chưa xác minh | L7: Có dấu hiệu | M7: Có dấu hiệu | P7: Cần kiểm tra bài báo/timing | Q7: Dự kiến đăng ký | R7: Cao | S7: Hồ sơ ghi 'công thức mới, dự kiến đăng ký bằng độc quyền GPHI' | T7: Cần xác minh đã nộp đơn hay mới dự kiến.
A8: IP2025-07-A | B8: P2025-07 | C8: O2025-07-03 | D8: Quy trình bào chế viên ngậm hỗ trợ giảm ho từ Gừng và Húng chanh | E8: Công nghệ | F8: Giải pháp hữu ích tiềm năng | G8: Có | H8: Có theo quy chế/hợp đồng - cần hồ sơ cụ thể | I8: Có khả năng | J8: Có khả năng | K8: Chưa xác minh | L8: Có dấu hiệu | M8: Có dấu hiệu | P8: Cần kiểm tra bài báo/timing | Q8: Dự kiến đăng ký | R8: Cao | S8: Hồ sơ ghi 'quy trình mới, dự kiến đăng ký bằng độc quyền GPHI' | T8: Cần xác minh đã nộp đơn hay mới dự kiến.

Sheet ZZ_CU_08_KPI_DASHBOARD
A1: KPI / IP FUNNEL – BẢN MẪU (CHƯA PHẢI KẾT QUẢ TOÀN TRƯỜNG)
A3: Chỉ số | B3: Công thức/ý nghĩa | C3: Giá trị
A4: Số đề tài đã nhập | B4: COUNTA Project_ID | C4: =COUNTA(ZZ_CU_01_PROJECT!A2:A1000) -> 7
A5: Số đầu ra đã bóc tách | B5: COUNTA Output_ID | C5: =COUNTA(ZZ_CU_02_OUTPUT!A2:A2000) -> 19
A6: Số TSTT/cụm TSTT sơ bộ | B6: COUNTA IP_ID | C6: =COUNTA(ZZ_CU_03_IP_ASSET!A2:A2000) -> 7
A7: Đã nhận diện chính thức | B7: IP asset = Có | C7: =COUNTIF(ZZ_CU_03_IP_ASSET!L2:L2000,"Có") -> 0
A8: Đã sàng lọc bảo hộ | B8: Screening = Có | C8: =COUNTIF(ZZ_CU_03_IP_ASSET!M2:M2000,"Có") -> 0
A9: Có hồ sơ nộp/đã cấp | B9: Protection status: Đã nộp/Được cấp | C9: =COUNTIF(TPL_04_PROTECTION!K2:K2000,"Đã nộp")+COUNTIF(TPL_04_PROTECTION!K2:K2000,"Được cấp") -> 0
A10: Có bằng chứng ứng dụng/khai thác | B10: Mức sử dụng > 0 | C10: =COUNTIF(TPL_05_UTIL_VALUE!E2:E2000,">0") -> 1
A11: Có thương mại hóa xác nhận | B11: Mức sử dụng = 7 | C11: =COUNTIF(TPL_05_UTIL_VALUE!E2:E2000,7) -> 0
A13: Mã mức sử dụng | B13: Diễn giải | D13: Điểm tiềm năng | E13: Diễn giải
A14: 0 | B14: Chưa sử dụng | D14: 0 | E14: Không/không phù hợp
A15: 1 | B15: Sử dụng trong giảng dạy | D15: 1 | E15: Thấp
A16: 2 | B16: Dùng cho nghiên cứu tiếp | D16: 2 | E16: Trung bình
A17: 3 | B17: Ứng dụng nội bộ | D17: 3 | E17: Cao
A18: 4 | B18: Chuẩn bị/thử nghiệm với đối tác
A19: 5 | B19: Đơn vị ngoài trường sử dụng
A20: 6 | B20: Chuyển giao/cấp phép
A21: 7 | B21: Thương mại hóa xác nhận
